Workbook
Name Engagement_evaluation_status: #REF!

Sheet 교육대상자
A1: 구분 | B1: Eng Code | C1: Eng Name | D1: Name | E1: Email | F1: 구분
A2: 리뷰어 | B2: 1661228 | C2: FY2025_비씨월드제약_외부(지정)감사 | D2: 김소희 | E2: skim66@kr.kpmg.com | F2: 추가 | H2: 2/10 송부
A3: 리뷰어 | B3: 1661228 | C3: FY2025_비씨월드제약_외부(지정)감사 | D3: 이민규 | E3: mingyulee@kr.kpmg.com | F3: 제거 | G3: < 퇴사 | H3: 2/10 송부
A4: 실무자 | B4: 1689529 | C4: [케이씨씨건설] FY2025 외부감사 | D4: 강신형 | E4: shinhyungkang@kr.kpmg.com | F4: 추가 | H4: 2/10 송부
A5: 실무자 | B5: 1685841 | C5: 메가스터디교육_FY2025 외부감사 | D5: 육형문 | E5: hyuk1@kr.kpmg.com | F5: 추가 | H5: 2/19 송부
A6: 실무자 | B6: 1685841 | C6: 메가스터디교육_FY2025 외부감사 | D6: 한청원 | E6: cheongwonhan@kr.kpmg.com | F6: 추가 | H6: 2/19 송부
A7: 실무자 | B7: 1669115 | C7: 현대백화점 2025년 외부감사 | D7: 박정주 | E7: jungjoopark@kr.kpmg.com | F7: 추가 | H7: 2/19 송부
A8: 실무자 | B8: 1666520 | C8: 2025년 카카오 외부감사 | D8: 오청민 | E8: chungminoh@kr.kpmg.com | F8: 추가 | H8: 2/19 송부
A9: 실무자 | B9: 1666520 | C9: 2025년 카카오 외부감사 | D9: 권혜빈 | E9: hyebinkwon@kr.kpmg.com | F9: 추가 | H9: 2/19 송부
A10: 실무자 | B10: 1684195 | C10: 드림어스컴퍼니_FY2025_외부감사 | D10: 정지은 | E10: jjung30@kr.kpmg.com | F10: 추가 | H10: 2/19 송부
A11: 실무자 | B11: 1657536 | C11: 한일홀딩스 2025년 지정감사(주기적) | D11: 김영준 | E11: ykim186@kr.kpmg.com | F11: 추가 | H11: 2/23 송부
A12: 실무자 | B12: 1682797 | C12: 비와이엔블랙야크 FY25 회계감사 | D12: 한창수 | E12: changsuhan@kr.kpmg.com | F12: 추가 | H12: 2/25 송부
A13: 리뷰어 | B13: 1684738 | C13: FY25 디와이덕양(구, 덕양산업) 외부감사 | D13: 최준성 | E13: jchoi13@kr.kpmg.com | F13: 추가 | H13: 3/3 송부
A14: 실무자 | B14: 1684738 | C14: FY25 디와이덕양(구, 덕양산업) 외부감사 | D14: 정서정 | E14: seojungjung@kr.kpmg.com | F14: 추가 | H14: 3/3 송부
A15: 실무자 | B15: 1684738 | C15: FY25 디와이덕양(구, 덕양산업) 외부감사 | D15: 정현욱 | E15: hyunwookjeong@kr.kpmg.com | F15: 추가 | H15: 3/3 송부
... A22: 실무자 | B22: 1656724 | C22: FY25_아스플로_지정감사 | D22: 김학송 | E22: haksongkim@kr.kpmg.com | F22: 추가 | H22: 3/4 송부

Sheet 보고자료
B2: 1. 현황 요약
B3: 항목 | C3: Eng 현황 | E3: 비고 | J3: #N/A | K3: 0 | L3: 미회신 - STS미신청
B4: 최초 Scoping | D4: 223 | F4: 223 | J4: 1. 서비스 요청 | K4: {=SUMPRODUCT( --IFERROR( ( (COUNTIF($P$4:$P$6, FY25_현황!$AF$8:$AF$998)>0) + (FY25_현황!$AF$8:$AF$998="") )>0,0), --IFERROR(FY25_현황!$DA$8:$DA$998=J4,0) )} -> 0 | L4: 미회신 - 데이터 미업로드
B5: (+) 추가신청 | D5: =FY25_현황!D4-FY25_현황!C4 -> 10 | F5: 9 | J5: 2-1. 데이터 재요청 | K5: {=SUMPRODUCT( --IFERROR( ( (COUNTIF($P$4:$P$6, FY25_현황!$AF$8:$AF$998)>0) + (FY25_현황!$AF$8:$AF$998="") )>0,0), --IFERROR(FY25_현황!$DA$8:$DA$998=J5,0) )} -> 0 | L5: interim 진행중 | P5: 사용
B6: (-) 제외 | D6: =C8+C7 -> -123 | J6: 2. 데이터 업로드 완료 | K6: {=SUMPRODUCT( --IFERROR( ( (COUNTIF($P$4:$P$6, FY25_현황!$AF$8:$AF$998)>0) + (FY25_현황!$AF$8:$AF$998="") )>0,0), --IFERROR(FY25_현황!$DA$8:$DA$998=J6,0) )} -> 0 | L6: interim 진행중
B7: (-) 확인중 | C7: =-(COUNTIF(FY25_현황!AF:AF,"확인중")+COUNTIF(FY25_현황!AF:AF,"통화안됨")) -> 0 | E7: (*) 통화안됨, 확인중 포함 | J7: 3-0. 담당자 지정 완료 | K7: {=SUMPRODUCT( --IFERROR( ( (COUNTIF($P$4:$P$6, FY25_현황!$AF$8:$AF$998)>0) + (FY25_현황!$AF$8:$AF$998="") )>0,0), --IFERROR(FY25_현황!$DA$8:$DA$998=J7,0) )} -> 0 | L7: interim 진행중
B8: (-) 사용 불가 신청 | C8: =-COUNTIF(FY25_현황!AF:AF,"제외요청") -> -123 | J8: 3-3. 앱 프로세싱 중 | K8: {=SUMPRODUCT( --IFERROR( ( (COUNTIF($P$4:$P$6, FY25_현황!$AF$8:$AF$998)>0) + (FY25_현황!$AF$8:$AF$998="") )>0,0), --IFERROR(FY25_현황!$DA$8:$DA$998=J8,0) )} -> 0 | L8: interim 진행중
B9: 현재 Scoping | D9: =SUM(D4:D6) -> 110 | J9: 4. 전처리 오류 처리 중 | K9: {=SUMPRODUCT( --IFERROR( ( (COUNTIF($P$4:$P$6, FY25_현황!$AF$8:$AF$998)>0) + (FY25_현황!$AF$8:$AF$998="") )>0,0), --IFERROR(FY25_현황!$DA$8:$DA$998=J9,0) )} -> 1 | L9: interim 진행중
B10: Interim 완료 | C10: =K10 -> 109 | J10: 5. 작업 완료 | K10: {=SUMPRODUCT( --IFERROR( ( (COUNTIF($P$4:$P$6, FY25_현황!$AF$8:$AF$998)>0) + (FY25_현황!$AF$8:$AF$998="") )>0,0), --IFERROR(FY25_현황!$DA$8:$DA$998=J10,0) )} -> 109 | L10: interim 완료
B11: Interim 진행중 | C11: =D9-C10 -> 1 | E11: (*) 사용예정 포함 | J11: 9. 서비스 취소 | K11: {=SUMPRODUCT( --IFERROR( ( (COUNTIF($P$4:$P$6, FY25_현황!$AF$8:$AF$998)>0) + (FY25_현황!$AF$8:$AF$998="") )>0,0), --IFERROR(FY25_현황!$DA$8:$DA$998=J11,0) )} -> 0 | L11: 미회신 - STS미신청
F12: =D9=(C10+C11) -> TRUE | J12: 합계 | K12: =SUM(K3:K11) -> 110
J13: 3-0. 담당자 지정 완료
B14: Total Feel | C14: Fee/Eng | D14: Eng
B15: 199500
C16: =B15/D16 -> 1830.2752 | D16: 109
C17: =B15/D17 -> 1813.6364 | D17: =D9 -> 110
B21: 항목 | C21: Eng 현황 | E21: 비고
B22: 미확인 | D22: 35
B23: 제외 | C23: 20
B24: 확인중 | C24: 10
B25: 통화안됨 | C25: 1
B26: 사용예정 | C26: 4

Sheet FY25>>>

Sheet FY25_현황
D3: =C4+AF3+AF4 -> 100 | AF3: =COUNTIF(AF8:AF395,"추가신청") -> 0 | AL3: =COUNTIF(AL8:AL1048576,"V") -> 145
C4: =COUNTA(C8:C395) -> 223 | D4: =COUNTA(D8:D395) -> 233 | AF4: =-(COUNTIF(AF8:AF395,"제외요청")+COUNTIF(AF8:AF395,"제외")) -> -123 | AK4: 계(제외요청/제외 빼고) | AL4: =SUBTOTAL(103,AL8:AL236) -> 201 | AM4: =COUNTIF(AM8:AM297,"V")-COUNTIFS(AM8:AM297,"V",$AF$8:$AF$297,"제외요청") -> 102 | AN4: =COUNTIF(AN8:AN297,"V")-COUNTIFS(AN8:AN297,"V",$AF$8:$AF$297,"제외요청") -> 99 | AO4: =COUNTIF(AO8:AO297,"V")-COUNTIFS(AO8:AO297,"V",$AF$8:$AF$297,"제외요청") -> 99 | AP4: =COUNTIF(AP8:AP297,"V")-COUNTIFS(AP8:AP297,"V",$AF$8:$AF$297,"제외요청") -> 99 | AQ4: =SUBTOTAL(103,AQ8:AQ236) -> 104 | AR4: =SUBTOTAL(103,AR8:AR236) -> 104 | AS4: =SUBTOTAL(103,AS8:AS236) -> 56 | AT4: =COUNTIF(AT8:AT297,"V")-COUNTIFS(AT8:AT297,"V",$AF$8:$AF$297,"제외요청") -> 2 | AU4: =COUNTIF(AU8:AU297,"V")-COUNTIFS(AU8:AU297,"V",$AF$8:$AF$297,"제외요청") -> 2 | AW4: =COUNTIF(AW8:AW297,"V")-COUNTIFS(AW8:AW297,"V",$AF$8:$AF$297,"제외요청") -> 78 | AX4: =COUNTIF(AX8:AX297,"V")-COUNTIFS(AX8:AX297,"V",$AF$8:$AF$297,"제외요청") -> 78 | AY4: =COUNTIF(AY8:AY297,"V")-COUNTIFS(AY8:AY297,"V",$AF$8:$AF$297,"제외요청") -> 78 | AZ4: =COUNTIF(AZ8:AZ297,"V")-COUNTIFS(AZ8:AZ297,"V",$AF$8:$AF$297,"제외요청") -> 78 | DC4: {=SUMPRODUCT(--(TRIM(SUBSTITUTE(FY25_현황!DC8:DC998,CHAR(160),""))="V"))} -> 35 | DD4: {=SUMPRODUCT(--(TRIM(SUBSTITUTE(FY25_현황!DD8:DD998,CHAR(160),""))="V"))} -> 123 | DF4: {=SUMPRODUCT(--(TRIM(SUBSTITUTE(FY25_현황!DF8:DF998,CHAR(160),""))="V"))} -> 109
C5: Eng 정보 | D5: Eng 정보 | P5: AITS Setting | AD5: Scoping | AH5: Interim | AV5: Year-end | AW5: Year-end | BA5: 연락처 | DA5: "5. 작업완료"제외하고 붙여넣기
AW6: 감사팀 | AY6: ITA | AZ6: AI | CZ6: 상태값 | DA6: 46056.521
B7: 대기/맵핑/분석/완료 | C7: 최초선정 | D7: NO | E7: 본부명 | F7: 고객코드 | G7: 회사명 | H7: 계약코드 | I7: 계약명 | J7: 법인구분 | K7: KCw | L7: 업종-대분류 | M7: KCw Industry | N7: ERP | O7: 최대 JE Line | P7: Revenue RMM | Q7: Revenue 통제의존 | R7: COGS RMM | S7: COGS 통제의존 | T7: Opex RMM | U7: Opex 통제의존 | V7: Interest income RMM | W7: Interest income 통제의존 | X7: Interest expense RMM | Y7: Interest expense 통제의존 | Z7: Subledger Revenue | AA7: Subledger Opex | AB7: Library | AC7: Industry | AD7: 전년도 참여 | AE7: 변동날짜 | AF7: 변동사항 | AG7: 변동사유 | AH7: 1분기 | AI7: 2분기 | AJ7: 3분기 | AK7: 4분기 | AL7: STS신청 | AM7: Eng 생성 | AN7: Data Upload완료 | AO7: Mapping 완료 | AP7: 감사팀 안내메일(mapping) 발송 | AQ7: 분석 완료 | AR7: AITS 감사팀 전달 | AS7: CAAT조서 작성 | AT7: 추가작업 필요 | AU7: 추가작업 완료 | AV7: 미사용 | AW7: STS Ticket 생성 | AX7: 데이터업로드 | AY7: 전처리/업로드 | AZ7: 분석 결과 제공 | BA7: DPP | BB7: DPP | BC7: DPP | BD7: DPP | BE7: DPP - IT | BF7: DPP - IT | BG7: DPP - Partner | BH7: DPP - Partner | BI7: EQCR | BJ7: EQCR | BK7: EP | BL7: EP | BM7: EP | BN7: EP | BO7: EP | BP7: EP | BQ7: EP | BR7: EP | BS7: EP | BT7: EP | BU7: EM | BV7: EM | BW7: EM | BX7: EM | BY7: EM | BZ7: EM | CA7: EM | CB7: EM | CC7: EM | CD7: EM | CE7: EM | CF7: EM | CG7: ICA | CH7: ICA | CI7: ICA | CJ7: ICA | CK7: Staff | CL7: Staff | CM7: Staff | CN7: Staff | CO7: Staff | CP7: Staff | CQ7: Staff | CR7: Staff | CS7: Staff | CT7: Staff | CU7: Staff | CV7: Staff | CW7: s | CX7: s | CY7: s | CZ7: Eng | DA7: 진행상황 | DC7: 미회신35건 관리 | DD7: 제외 | DF7: 비용청구
C8: 1668793 | D8: 1 | E8: ICE1 | F8: 1000316445 | G8: 에스케이하이닉스 | H8: 1668793 | I8: SK하이닉스 FY2025 외부감사 | J8: 유가증권 | K8: Enhanced | L8: 제조업 | M8: Industrial Products | N8: SAP S4 HANA | O8: 6821774 | P8: 115.2.02 115.2.12b 115.2.13 115.3.01 | Q8: O | R8: N/A | S8: N/A | T8: N/A | U8: N/A | V8: N/A | W8: N/A | X8: N/A | Y8: N/A | Z8: N/A | AA8: N/A | AB8: KR_KPMG Dashboards - IFRS v3.1 - Base Industry: UpdateMay2025 | AC8: Manufacturing | AD8: Y | AH8: V | AI8: V | AJ8: V | AK8: V | AL8: V | AM8: V | AN8: V | AO8: V | AP8: V | AQ8: V | AR8: V | AS8: V | AW8: V | AX8: V | AY8: V | AZ8: V | BA8: 이현경 | BB8: hyunkyunglee@kr.kpmg.com | BE8: 이현강 | BF8: hyeonganglee@kr.kpmg.com | BG8: 이승훈 | BH8: seunghoonlee@kr.kpmg.com | BI8: 변재준 | BJ8: jbyun@kr.kpmg.com | BK8: 윤주헌 | BL8: joohunyoon@kr.kpmg.com | BU8: 김병민 | BV8: byungminkim@kr.kpmg.com | BW8: 송성화 | BX8: sunghwasong@kr.kpmg.com | CG8: 김성훈 | CH8: skim130@kr.kpmg.com | CK8: 이하린 | CL8: harinlee@kr.kpmg.com | CM8: 이가은 | CN8: glee34@kr.kpmg.com | CY8: s | CZ8: SK하이닉스 FY2025 외부감사 | DA8: 5. 작업 완료 | DD8: =IF(AF8="제외요청", "V","") | DF8: V
A9: 박정빈 | B9: 완료 | C9: 1698103 | D9: 2 | E9: IM4 | F9: 1000317342 | G9: Korea Electric Power Corporation | H9: 1698103 | I9: FY25_한국전력공사_외부회계감사 | J9: 유가증권(FPI) | K9: Enhanced | L9: 전력사업 | M9: Energy and Natural Resources | N9: SAP S4 ECC | O9: 240745021 | P9: N/A | Q9: N/A | R9: N/A | S9: N/A | T9: 100.2.02 | U9: O | V9: N/A | W9: N/A | X9: N/A | Y9: N/A | Z9: N/A | AA9: N/A | AB9: KR_KPMG Dashboards - IFRS v3.1 - Base Industry: UpdateMay2025 | AC9: Utilities | AD9: N | AH9: V | AL9: V | AM9: V | AN9: V | AO9: V | AP9: V | AQ9: V | AR9: V | AT9: V | AU9: V | AW9: V | AX9: V | AY9: V | AZ9: V | BA9: 김수연 | BB9: sooyeonkim@kr.kpmg.com | BE9: 서은아 | BF9: eseo@kr.kpmg.com | BG9: Cao, Leah | BH9: leahcao@kr.kpmg.com | BI9: 황재남 | BJ9: jaenamhwang@kr.kpmg.com | BK9: 이정수 | BL9: jungsoolee@kr.kpmg.com | BU9: 전태웅 | BV9: taeungjeon@kr.kpmg.com | CG9: 정재정 | CH9: jaejeongjeong@kr.kpmg.com | CK9: 김상훈 | CL9: skim191@kr.kpmg.com | CM9: 최서영 | CN9: seoyoungchoi@kr.kpmg.com | CZ9: FY25_한국전력공사_외부회계감사 | DA9: 5. 작업 완료 | DD9: =IF(AF9="제외요청", "V","") | DF9: V
C10: 1698595 | D10: 3 | E10: IM4 | F10: 1000314674 | G10: 한국수력원자력 ㈜ | H10: 1698595 | I10: [한국수력원자력] FY2025 회계감사 | J10: 유가증권 | K10: Enhanced | M10: 에너지 및 천연자원 사업 | N10: SAP S4 HANA | O10: 1701147 | P10: 115.2.02 115.2.13 115.2.02 115.2.12b | Q10: O | R10: N/A | S10: N/A | T10: 100.2.02 | U10: O | V10: N/A | W10: N/A | X10: N/A | Y10: N/A | Z10: N/A | AA10: N/A | AB10: KR_KPMG Dashboards - IFRS v3.1 - Base Industry: UpdateMay2025 | AC10: Utilities | AD10: N | AE10: 46036 | AF10: 제외요청 | AG10: 전수검토 수행 | AH10: V | AL10: V | AM10: V | AN10: V | AO10: V | AP10: V | AQ10: V | AR10: V | AT10: V | AU10: V | BA10: 김수연 | BB10: sooyeonkim@kr.kpmg.com | BE10: 이현강 | BF10: hyeonganglee@kr.kpmg.com | BG10: Cao, Leah | BH10: leahcao@kr.kpmg.com | BI10: 황재남 | BJ10: jaenamhwang@kr.kpmg.com | BK10: 김연정 | BL10: yeonjungkim@kr.kpmg.com | BU10: 김성욱 | BV10: sunguckkim@kr.kpmg.com | CG10: 윤광현 | CH10: kwanghyunyun@kr.kpmg.com | CI10: 이준학 | CJ10: jlee214@kr.kpmg.com | CK10: 김상식 | CL10: sangseekkim@kr.kpmg.com | CM10: 김혜수 | CN10: hyesukim@kr.kpmg.com | CZ10: [한국수력원자력] FY2025 회계감사 | DA10: 5. 작업 완료 | DD10: =IF(AF10="제외요청", "V","") -> V
C11: 1683891 | D11: 4 | E11: ICE3 | F11: 1000315445 | G11: 에스케이브로드밴드 주식회사 | H11: 1683891 | I11: SK브로드밴드 2025년 외부감사 | J11: 일반(채권상장/FPI) | K11: Enhanced | L11: 유선통신업 | O11: 2823049 | P11: 115.2.02 115.2.13 115.2.12b | Q11: O | R11: N/A | S11: N/A | T11: 100.2.02 | U11: O | V11: N/A | W11: N/A | X11: N/A | Y11: N/A | Z11: N/A | AA11: N/A | AB11: KR_KPMG Dashboards - IFRS v3.1 - Media & Telecoms Industry | AC11: Information | AD11: N | AH11: V | AL11: V | AM11: V | AN11: V | AO11: V | AP11: V | AQ11: V | AR11: V | AW11: V | AX11: V | AY11: V | AZ11: V | BA11: 이현경 | BB11: hyunkyunglee@kr.kpmg.com | BE11: 이현강 | BF11: hyeonganglee@kr.kpmg.com | BG11: Cao, Leah | BH11: leahcao@kr.kpmg.com | BI11: 박성배 | BJ11: sungbaepark@kr.kpmg.com | BK11: 최진석 | BL11: jinseokchoi@kr.kpmg.com | BU11: 이준혁 | BV11: junhyeoklee@kr.kpmg.com | CG11: 김연하 | CH11: yeonhakim@kr.kpmg.com | CK11: 유용훈 | CL11: yonghoonyoo@kr.kpmg.com | CM11: 유인혁 | CN11: inhyugryu@kr.kpmg.com | CZ11: SK브로드밴드 2025년 외부감사 | DA11: 5. 작업 완료 | DD11: =IF(AF11="제외요청", "V","") | DF11: V
C12: 1658093 | D12: 5 | E12: IM2 | F12: 1000316943 | G12: SK이노베이션㈜ | H12: 1658093 | I12: SK이노베이션 2025년 외부감사 | J12: 유가증권 | L12: 석유 정제품 제조업 | M12: Energy and Natural Resources | O12: 892475 | P12: 115.2.02 | Q12: O | R12: N/A | S12: N/A | T12: 100.2.02 | U12: O | V12: N/A | W12: N/A | X12: N/A | Y12: N/A | Z12: N/A | AA12: N/A | AB12: KR_KPMG Dashboards - IFRS v3.1 - Base Industry: UpdateMay2025 | AC12: Manufacturing | AD12: Y | AI12: V | AL12: V | AM12: V | AN12: V | AO12: V | AP12: V | AQ12: V | AR12: V | AS12: V | AW12: V | AX12: V | AY12: V | AZ12: V | BA12: 이동영 | BB12: dongyounglee@kr.kpmg.com | BE12: 서은아 | BF12: eseo@kr.kpmg.com | BG12: 신재혁 | BH12: chaehyokshin@kr.kpmg.com | BK12: 이채능 | BL12: chaeneunglee@kr.kpmg.com | BU12: 정필재 | BV12: pjeong@kr.kpmg.com | CG12: 김준수 | CH12: jkim142@kr.kpmg.com | CK12: 최현지 | CL12: hyunjichoi@kr.kpmg.com | CM12: 신동민 | CN12: dshin6@kr.kpmg.com | CO12: 김윤 | CP12: ykim188@kr.kpmg.com | CQ12: 장상수 | CR12: sangsoojang@kr.kpmg.com | CS12: 한상훈 | CT12: shan24@kr.kpmg.com | CZ12: SK이노베이션 2025년 외부감사 | DA12: 5. 작업 완료 | DD12: =IF(AF12="제외요청", "V","") | DF12: V
C13: 1683431 | D13: 7 | E13: IM1 | F13: 1000325286 | G13: SK에너지 주식회사 | H13: 1683431 | I13: 2025 SK에너지 외부감사 | J13: 일반 | L13: 석유 정제품 제조업 | M13: Consumer Products, Energy and Natural Resources, Industrial Products, Retail | N13: SAP S/4 HANA | O13: 20333929 | P13: 115.2.02 115.2.13 | Q13: O | R13: N/A | S13: N/A | T13: N/A | U13: N/A | V13: N/A | W13: N/A | X13: N/A | Y13: N/A | Z13: N/A | AA13: N/A | AB13: KR_KPMG Dashboards - IFRS v3.1 - Oil & Gas Industry | AC13: Manufacturing | AD13: Y | AI13: V | AL13: V | AM13: V | AN13: V | AO13: V | AP13: V | AQ13: V | AR13: V | AS13: V | AW13: V | AX13: V | AY13: V | AZ13: V | BG13: 신재혁 | BH13: chaehyokshin@kr.kpmg.com | BI13: 강성채 | BJ13: sungchaekang@kr.kpmg.com | BK13: 변상현 | BL13: sanghyunbyun@kr.kpmg.com | BU13: 송기백 | BV13: gibaeksong@kr.kpmg.com | CG13: 탁현우 | CH13: hyunwootak@kr.kpmg.com | CK13: 곽정화 | CL13: jeonghwagwak@kr.kpmg.com | CM13: 김정태 | CN13: jkim448@kr.kpmg.com | CO13: 유지호 | CP13: jryou@kr.kpmg.com | CQ13: 황유진 | CR13: yhwang2@kr.kpmg.com | CS13: 김도형 | CT13: dkim213@kr.kpmg.com | CU13: 하창균 | CV13: changkyunha@kr.kpmg.com | CZ13: 2025 SK에너지 외부감사 | DA13: 5. 작업 완료 | DD13: =IF(AF13="제외요청", "V","") | DF13: V
C14: 1669411 | D14: 8 | E14: ICE2 | F14: 1000314822 | G14: 삼성전자 ㈜ | H14: 1669411 | I14: FY25 삼성전자 외부감사 | J14: 유가증권 | L14: 통신 및 방송장비 제조업 | O14: 104049452 | P14: 115.2.02 115.2.13 | Q14: O | R14: N/A | S14: N/A | T14: 100.2.02 | U14: O | V14: N/A | W14: N/A | X14: N/A | Y14: N/A | Z14: N/A | AA14: N/A | AB14: KR_KPMG Dashboards - IFRS v3.1 - Technology Industry | AC14: Manufacturing | AD14: Y | AI14: V | AL14: V | AM14: V | AN14: V | AO14: V | AP14: V | AQ14: V | AR14: V | AS14: V | AW14: V | AX14: V | AY14: V | AZ14: V | BA14: 이영롱 | BB14: younglonglee@kr.kpmg.com | BC14: 김수영 | BD14: skim40@kr.kpmg.com | BE14: 서은아 | BF14: eseo@kr.kpmg.com | BG14: 오헌창 | BH14: heonchangoh@kr.kpmg.com | BI14: 남상민 | BJ14: sangminnam@kr.kpmg.com | BK14: 한상현 | BL14: sanghyunhan@kr.kpmg.com | BM14: 김영선 | BN14: ykim66@kr.kpmg.com | BO14: 최이현 | BP14: yeehyunchoi@kr.kpmg.com | BQ14: 노정한 | BR14: jroh@kr.kpmg.com | BS14: 심진보 | BT14: jinboshim@kr.kpmg.com | BU14: 김지만 | BV14: jkim139@kr.kpmg.com | BW14: 한송희 | BX14: shan9@kr.kpmg.com | BY14: 김대진 | BZ14: dkim23@kr.kpmg.com | CA14: 남서영 | CB14: seoyoungnam@kr.kpmg.com | CC14: 정주희 | CD14: juheejeong@kr.kpmg.com | CE14: 민대홍 | CF14: daehongmin@kr.kpmg.com | CG14: 정성규 | CH14: sungkyujung@kr.kpmg.com | CK14: 이재하 | CL14: jaehalee@kr.kpmg.com | CZ14: FY25 삼성전자 외부감사 | DA14: 5. 작업 완료 | DD14: =IF(AF14="제외요청", "V","") | DF14: V
C15: 1658135 | D15: 9 | E15: IM2 | F15: 1000326113 | G15: SK (주) | H15: 1658135 | I15: SK(주) 2025년 외부감사 | J15: 유가증권 | L15: 지주회사 | AD15: N | AE15: 45862 | AF15: 제외요청 | AG15: 투자부문: 영업수익 및 운영비용의 거래구조가 복잡하지 않으므로 적용하지 아니함 / 사업부문: 진행매출로 적용하지 아니함 | BA15: 이동영 | BB15: dongyounglee@kr.kpmg.com | BE15: 서은아 | BF15: eseo@kr.kpmg.com | BG15: 신재혁 | BH15: chaehyokshin@kr.kpmg.com | BI15: 황재남 | BJ15: jaenamhwang@kr.kpmg.com | BK15: 최세홍 | BL15: sehongchoi@kr.kpmg.com | BM15: 이상근 | BN15: sangkeunlee@kr.kpmg.com | BU15: 정환욱 | BV15: hwanukjung@kr.kpmg.com | BW15: 이충기 | BX15: choongkilee@kr.kpmg.com | CG15: 안다영 | CH15: dayeongahn@kr.kpmg.com | CZ15: #N/A | DA15: #N/A | DD15: =IF(AF15="제외요청", "V","") -> V
A16: 박정빈 | B16: 완료 | C16: 1666520 | D16: 10 | E16: ICE2 | F16: 1000317527 | G16: 주식회사 카카오 | H16: 1666520 | I16: 2025년 카카오 외부감사 | J16: 유가증권 | L16: 포털 및 기타 인터넷 정보매개 서비스업 | M16: Media, Technology | N16: SAP | O16: 36413933 | P16: 115.2.02 115.2.13 115.2.12b | Q16: O | R16: N/A | S16: N/A | T16: N/A | U16: N/A | V16: N/A | W16: N/A | X16: N/A | Y16: N/A | Z16: N/A | AA16: N/A | AB16: KR_KPMG Dashboards - IFRS v3.1 - Media & Telecoms Industry | AC16: Information | AD16: N | AF16: 사용 | AL16: V | AW16: V | AX16: V | AY16: V | AZ16: V | BA16: 김수영 | BB16: skim40@kr.kpmg.com | BE16: 서은아 | BF16: eseo@kr.kpmg.com | BG16: 현승임 | BH16: shyun@kr.kpmg.com | BI16: 강승미 | BJ16: seungmikang@kr.kpmg.com | BK16: 이지원 | BL16: jeewonlee@kr.kpmg.com | BM16: 심진보 | BN16: jinboshim@kr.kpmg.com | BO16: 이재영 | BP16: jlee79@kr.kpmg.com | BU16: 김세모 | BV16: semokim@kr.kpmg.com | CG16: 정진우 | CH16: jjung9@kr.kpmg.com | CK16: 곽승준 | CL16: seungjunkwak@kr.kpmg.com | CM16: 이은영 | CN16: elee44@kr.kpmg.com | CO16: 윤민철 | CP16: mincheolyun@kr.kpmg.com | CQ16: 오청민 | CR16: chungminoh@kr.kpmg.com | CS16: 권혜빈 | CT16: hyebinkwon@kr.kpmg.com | CZ16: 2025년 카카오 외부감사 | DA16: 5. 작업 완료 | DC16: V | DD16: =IF(AF16="제외요청", "V","") | DF16: V
C17: 1669406 | D17: 11 | E17: ICE3 | F17: 1000317244 | G17: 네이버 주식회사 | H17: 1669406 | I17: FY25 네이버 외부감사 | J17: 유가증권 | L17: 포털 및 기타 인터넷 정보매개 서비스업 | M17: 서비스(관리 용역) 산업 , 기술 지원 산업 | N17: NEON | O17: 5875231 | P17: 115.2.02 115.2.13 115.3.01 115.2.12b | Q17: O | R17: N/A | S17: N/A | T17: 100.2.02 | U17: O | V17: N/A | W17: N/A | X17: N/A | Y17: N/A | Z17: N/A | AA17: N/A | AB17: KR_KPMG Dashboards - IFRS v3.1 - Media & Telecoms Industry | AC17: Information | AD17: N | AI17: V | AL17: V | AM17: V | AN17: V | AO17: V | AP17: V | AQ17: V | AR17: V | AW17: V | AX17: V | AY17: V | AZ17: V | BA17: 김수영 | BB17: skim40@kr.kpmg.com | BE17: 서은아 | BF17: eseo@kr.kpmg.com | BG17: 한상현 | BH17: sanghyunhan@kr.kpmg.com | BI17: 김정기 | BJ17: jungkikim@kr.kpmg.com | BK17: 최이현 | BL17: yeehyunchoi@kr.kpmg.com | BU17: 김의진 | BV17: euijinkim@kr.kpmg.com | CG17: 이성범 | CH17: seongbeomlee@kr.kpmg.com | CK17: 김부성 | CL17: boosungkim@kr.kpmg.com | CM17: 김승기 | CN17: seungkikim@kr.kpmg.com | CO17: 배슬기 | CP17: seulgibae@kr.kpmg.com | CQ17: 송경현 | CR17: ksong2@kr.kpmg.com | CS17: 김범수 | CT17: beomsookim@kr.kpmg.com | CU17: 서지원 | CV17: jseo6@kr.kpmg.com | CW17: 성현식 | CX17: hyunsikseong@kr.kpmg.com | CZ17: FY25 네이버 외부감사 | DA17: 5. 작업 완료 | DD17: =IF(AF17="제외요청", "V","") | DF17: V
A18: 김찬영 | B18: 완료 | C18: 1668904 | D18: 12 | E18: IM3 | F18: 1000317488 | G18: 현대모비스 ㈜ | H18: 1668904 | I18: FY25 현대모비스 외부감사 | J18: 유가증권 | L18: 자동차부품제조업 | O18: 700851222 | P18: 115.2.02 115.2.13 | Q18: O | R18: N/A | S18: N/A | T18: N/A | U18: N/A | V18: N/A | W18: N/A | X18: N/A | Y18: N/A | Z18: N/A | AA18: N/A | AB18: KR_KPMG Dashboards - IFRS v3.1 - Base Industry: UpdateMay2025 | AC18: Manufacturing | AD18: N | AJ18: V | AL18: V | AM18: V | AN18: V | AO18: V | AP18: V | AQ18: V | AR18: V | AW18: V | AX18: V | AY18: V | AZ18: V | BA18: 김미희 | BB18: mkim181@kr.kpmg.com | BE18: 서은아 | BF18: eseo@kr.kpmg.com | BG18: 신재혁 | BH18: chaehyokshin@kr.kpmg.com | BI18: 정양기 | BJ18: yangkijung@kr.kpmg.com | BK18: 강성채 | BL18: sungchaekang@kr.kpmg.com | BU18: 신준희 | BV18: juneheeshin@kr.kpmg.com | CG18: 정대주 | CH18: djung4@kr.kpmg.com | CZ18: FY25 현대모비스 외부감사 | DA18: 5. 작업 완료 | DD18: =IF(AF18="제외요청", "V","") | DF18: V
C19: 1668870 | D19: 13 | E19: IM3 | F19: 1000316588 | G19: (주)대한항공 | H19: 1668870 | I19: 2025 회계연도 법정감사_대한항공 | J19: 유가증권 | L19: 항공 여객 운송업 | M19: Aviation Services | N19: Oracle | O19: 30497511 | P19: 115.2.02 | Q19: O | R19: N/A | S19: N/A | T19: N/A | U19: N/A | V19: N/A | W19: N/A | X19: N/A | Y19: N/A | Z19: N/A | AA19: N/A | AB19: KR_KPMG Dashboards - IFRS v3.1 - Base Industry: UpdateMay2025 | AC19: Transportation and Warehousing | AD19: N | AI19: V | AL19: V | AM19: V | AN19: V | AO19: V | AP19: V | AQ19: V | AR19: V | AS19: V | AW19: V | AX19: V | AY19: V | AZ19: V | BA19: 이채영 | BB19: clee46@kr.kpmg.com | BE19: 서은아 | BF19: eseo@kr.kpmg.com | BG19: 오헌창 | BH19: heonchangoh@kr.kpmg.com | BI19: 황재남 | BJ19: jaenamhwang@kr.kpmg.com | BK19: 신동준 | BL19: dongjunshin@kr.kpmg.com | BU19: 김상우 | BV19: skim56@kr.kpmg.com | CG19: 고요섭 | CH19: yosupgo@kr.kpmg.com | CM19: 김민지 | CN19: mkim196@kr.kpmg.com | CZ19: 2025 회계연도 법정감사_대한항공 | DA19: 5. 작업 완료 | DD19: =IF(AF19="제외요청", "V","") | DF19: V
A20: 박정빈 | B20: 완료 | C20: 1668853 | D20: 14 | E20: IM3 | F20: 1000316585 | G20: 아시아나항공 | H20: 1668853 | I20: [아시아나항공] 2025년 지정 감사 | J20: 유가증권 | L20: 항공 여객 운송업 | M20: Aviation / Services | N20: SAP S/4 HANA | O20: 13817517 | P20: 115.2.13 115.3.01 | Q20: O | R20: N/A | S20: N/A | T20: N/A | U20: N/A | V20: N/A | W20: N/A | X20: N/A | Y20: N/A | Z20: N/A | AA20: N/A | AB20: KR_KPMG Dashboards - IFRS v3.1 - Base Industry: UpdateMay2025 | AC20: Transportation and Warehousing | AD20: N | AI20: V | AK20: V | AL20: V | AM20: V | AN20: V | AO20: V | AP20: V | AQ20: V | AR20: V | AS20: V | AW20: V | AX20: V | AY20: V | AZ20: V | BA20: 노민경 | BB20: minkyungro@kr.kpmg.com | BE20: 서은아 | BF20: eseo@kr.kpmg.com | BG20: 오헌창 | BH20: heonchangoh@kr.kpmg.com | BI20: 이채능 | BJ20: chaeneunglee@kr.kpmg.com | BK20: 백명종 | BL20: mbaek@kr.kpmg.com | BU20: 조윤기 | BV20: yungicho@kr.kpmg.com | CG20: 오재욱 | CH20: jaeukoh@kr.kpmg.com | CK20: 조영진 | CL20: ycho14@kr.kpmg.com | CZ20: [아시아나항공] 2025년 지정 감사 | DA20: 5. 작업 완료 | DD20: =IF(AF20="제외요청", "V","") | DF20: V
C21: 1667371 | D21: 15 | E21: IM1 | F21: 1000314665 | G21: 삼성바이오로직스 주식회사 | H21: 1667371 | I21: 삼성바이오로직스 외부감사_FY25 | J21: 유가증권 | L21: 기초 의약 물질 제조업 | M21: Industrial Products, Healthcare | N21: SAP | O21: 1146540 | P21: 115.2.02 115.2.13 115.3.01 | Q21: O | R21: N/A | S21: N/A | T21: 100.2.02 | U21: O | V21: N/A | W21: N/A | X21: N/A | Y21: N/A | Z21: N/A | AA21: N/A | AB21: KR_KPMG Dashboards - IFRS v3.1 - Healthcare Industry | AC21: Manufacturing | AD21: N | AI21: V | AL21: V | AM21: V | AN21: V | AO21: V | AP21: V | AQ21: V | AR21: V | AS21: V | AW21: V | AX21: V | AY21: V | AZ21: V | BA21: 이채영 | BB21: clee46@kr.kpmg.com | BE21: 이현강 | BF21: hyeonganglee@kr.kpmg.com | BG21: 현승임 | BH21: shyun@kr.kpmg.com | BI21: 임근구 | BJ21: gleem@kr.kpmg.com | BK21: 나재광 | BL21: jra@kr.kpmg.com | BU21: 김수연 | BV21: suyeonkim@kr.kpmg.com | CG21: 임혁순 | CH21: hyim@kr.kpmg.com | CK21: 백진주 | CL21: jinjubaek@kr.kpmg.com | CZ21: 삼성바이오로직스 외부감사_FY25 | DA21: 5. 작업 완료 | DD21: =IF(AF21="제외요청", "V","") | DF21: V
C22: 1683436 | D22: 16 | E22: ICE3 | F22: 1000325445 | G22: 삼성디스플레이 주식회사 | H22: 1683436 | I22: FY25_삼성디스플레이_외부감사 | J22: 일반 | L22: 액정 표시장치 제조업 | AB22: KR_KPMG Dashboards - IFRS v3.1 - Technology Industry | AC22: Manufacturing | AD22: Y | AF22: 사용 | AI22: V | AL22: V | AM22: V | AN22: V | AO22: V | AP22: V | AQ22: V | AR22: V | AW22: V | AX22: V | AY22: V | AZ22: V | BI22: 설하영 | BJ22: hsul@kr.kpmg.com | BK22: 설유진 | BL22: yseol@kr.kpmg.com | BU22: 장진 | BV22: jinjang@kr.kpmg.com | CG22: 이은상 | CH22: eunsanglee@kr.kpmg.com | CZ22: FY25_삼성디스플레이_외부감사 | DA22: 5. 작업 완료 | DC22: V | DD22: =IF(AF22="제외요청", "V","") | DF22: V
A23: 박정빈 | B23: 완료 | C23: 1663086 | D23: 17 | E23: IM1 | F23: 1000325538 | G23: SK 네트웍스 ㈜ | H23: 1663086 | I23: FY2025_SK네트웍스_법정감사 | J23: 유가증권 | L23: 기타 전문 도매업 | M23: Consumer Products , Retail, Services, Telecommunications | N23: SAP | O23: 3885124 | P23: 115.2.02 115.2.12b 115.2.13 115.3.01 | Q23: O | R23: N/A | S23: N/A | T23: N/A | U23: N/A | V23: N/A | W23: N/A | X23: N/A | Y23: N/A | Z23: N/A | AA23: N/A | AB23: KR_KPMG Dashboards - IFRS v3.1 - Retail Industry | AC23: Wholesale Trade | AD23: Y | AI23: V | AL23: V | AM23: V | AN23: V | AO23: V | AP23: V | AQ23: V | AR23: V | AW23: V | AX23: V | AY23: V | AZ23: V | BA23: 황인영 | BB23: ihwang7@kr.kpmg.com | BE23: 이현강 | BF23: hyeonganglee@kr.kpmg.com | BG23: 신재혁 | BH23: chaehyokshin@kr.kpmg.com | BI23: 도정욱 | BJ23: jungwookdo@kr.kpmg.com | BK23: 이주영 | BL23: jooyounglee@kr.kpmg.com | BU23: 박율철 | BV23: yulcheolpark@kr.kpmg.com | CG23: 천의성 | CH23: euiseongcheon@kr.kpmg.com | CK23: 손인수 | CL23: insooson@kr.kpmg.com | CM23: 이미현 | CN23: mihyeonlee@kr.kpmg.com | CO23: 이상원 | CP23: slee227@kr.kpmg.com | CZ23: FY2025_SK네트웍스_법정감사 | DA23: 5. 작업 완료 | DD23: =IF(AF23="제외요청", "V","") | DF23: V
C24: 1683711 | D24: 18 | E24: ICE2 | F24: 1000844981 | G24: 두나무 주식회사 | H24: 1683711 | I24: 두나무_외부감사_FY2025 | J24: 일반 | L24: 정보서비스업 | AB24: KR_KPMG Dashboards - IFRS v3.1 - Banking Industry | AC24: Finance and Insurance | AD24: N | AE24: 45891 | AF24: 제외요청 | AG24: 적용 시 비효율적이라 판단 | BA24: 김수영 | BB24: skim40@kr.kpmg.com | BE24: 서은아 | BF24: eseo@kr.kpmg.com | BG24: 오헌창 | BH24: heonchangoh@kr.kpmg.com | BI24: 안창범 | BJ24: cahn@kr.kpmg.com | BK24: 최연택 | BL24: yeontaekchoi@kr.kpmg.com | BM24: 신문철 | BN24: moonchulshin@kr.kpmg.com | BU24: 김현준 | BV24: hkim108@kr.kpmg.com | CG24: 한민규 | CH24: mingyuhan@kr.kpmg.com | CZ24: #N/A | DA24: #N/A | DD24: =IF(AF24="제외요청", "V","") -> V
C25: 1667197 | D25: 19 | E25: CM2 | F25: 1000314625 | G25: 롯데지주 주식회사 | H25: 1667197 | I25: 롯데지주 2025년 외부감사(지정) | J25: 유가증권 | L25: 지주회사 | AB25: KR_KPMG Dashboards - IFRS v3.1 - Banking Industry | AC25: Management of Companies and Enterprises | AD25: N | AE25: 45902 | AF25: 제외요청 | AG25: 지주회사로 매출의 경우 SR이며, 비용의 경우 양적/질적으로 중요한 샘플은 specific으로 확인하고 있고, 잔여모집단에 대해서만 mus로 샘플을 추출하여 AITS 사용 실익이 적을 것으로 보임 | BA25: 김미희 | BB25: mkim181@kr.kpmg.com | BE25: 이현강 | BF25: hyeonganglee@kr.kpmg.com | BG25: 오헌창 | BH25: heonchangoh@kr.kpmg.com | BI25: 현윤호 | BJ25: yhyun@kr.kpmg.com | BK25: 김시우 | BL25: siwookim@kr.kpmg.com | BU25: 오승재 | BV25: seungjaeoh@kr.kpmg.com | CG25: 이광수 | CH25: kwangsulee@kr.kpmg.com | CZ25: #N/A | DA25: #N/A | DD25: =IF(AF25="제외요청", "V","") -> V
C26: 1670326 | D26: 20 | E26: ICE3 | F26: 1000314621 | G26: 넷마블 주식회사 | H26: 1670326 | I26: FY25 넷마블 외부감사 | J26: 유가증권 | L26: 게임 소프트웨어 개발 및 공급업 | M26: 서비스(관리 용역) 산업, 통신 산업 | N26: SAP | O26: 400432 | P26: 115.2.02 | Q26: O | R26: N/A | S26: N/A | T26: 100.2.02 | U26: O | V26: N/A | W26: N/A | X26: N/A | Y26: N/A | Z26: N/A | AA26: N/A | AB26: KR_KPMG Dashboards - IFRS v3.1 - Media & Telecoms Industry | AC26: Information | AD26: N | AL26: V | AM26: V | AN26: V | AO26: V | AP26: V | AQ26: V | AR26: V | AS26: V | AW26: V | AX26: V | AY26: V | AZ26: V | BA26: 이영롱 | BB26: younglonglee@kr.kpmg.com | BE26: 서은아 | BF26: eseo@kr.kpmg.com | BG26: 오헌창 | BH26: heonchangoh@kr.kpmg.com | BI26: 윤주헌 | BJ26: joohunyoon@kr.kpmg.com | BK26: 김익찬 | BL26: ikchankim@kr.kpmg.com | BU26: 이윤아 | BV26: yoonahlee@kr.kpmg.com | CG26: 이형철 | CH26: hyeongcheollee@kr.kpmg.com | CK26: 김상현 | CL26: skim257@kr.kpmg.com | CM26: 이민석 | CN26: mlee96@kr.kpmg.com | CZ26: FY25 넷마블 외부감사 | DA26: 5. 작업 완료 | DD26: =IF(AF26="제외요청", "V","") | DF26: V
C27: 1669412 | D27: 21 | E27: IM1 | F27: 1000953186 | G27: 에이치디현대중공업 주식회사 | H27: 1669412 | I27: FY2025 HD현대중공업 주식회사 외부감사 | J27: 유가증권 | L27: 선박건조업 | AD27: N | AE27: 45873 | AF27: 제외요청 | AG27: 대부분이 진행기준으로 매출과 원가 90% 이상이 SR | BA27: 김미희 | BB27: mkim181@kr.kpmg.com | BE27: 이현강 | BF27: hyeonganglee@kr.kpmg.com | BG27: 김신 | BH27: skim137@kr.kpmg.com | BI27: 노상호 | BJ27: sanghoroh@kr.kpmg.com | BK27: 전원표 | BL27: wjeon@kr.kpmg.com | BU27: 김성일 | BV27: seongilkim@kr.kpmg.com | BW27: 송기백 | BX27: gibaeksong@kr.kpmg.com | CG27: 탁현우 | CH27: hyunwootak@kr.kpmg.com | CZ27: #N/A | DA27: #N/A | DD27: =IF(AF27="제외요청", "V","") -> V
C28: 1668586 | D28: 22 | E28: CM2 | F28: 1000810814 | G28: 롯데웰푸드㈜ | H28: 1668586 | I28: FY2025 롯데웰푸드 외부감사 | J28: 유가증권 | L28: 기타 식품 제조업 | AB28: KR_KPMG Dashboards - IFRS v3.1 - Base Industry: UpdateMay2025 | AC28: Manufacturing | AD28: N | AE28: 45874 | AF28: 제외요청 | AG28: 1. 수익 : GL이 아닌 유통채널별 매출전표로 위험평가 및 실증절차를 수행하여 AITS 적용이 어려움. 2. 매출원가 : 재고자산으로 포함되는 원가로 적용 불가 3. 비용 : 실익이 낮아 미적용 | BA28: 김미희 | BB28: mkim181@kr.kpmg.com | BE28: 이현강 | BF28: hyeonganglee@kr.kpmg.com | BG28: 이승훈 | BH28: seunghoonlee@kr.kpmg.com | BI28: 현윤호 | BJ28: yhyun@kr.kpmg.com | BK28: 정현진 | BL28: hchung@kr.kpmg.com | BU28: 이치백 | BV28: clee60@kr.kpmg.com | CG28: 이재근 | CH28: jaekeunlee@kr.kpmg.com | CZ28: #N/A | DA28: #N/A | DD28: =IF(AF28="제외요청", "V","") -> V
C29: 1660660 | D29: 23 | E29: IM4 | F29: 1000326094 | G29: 팬오션 주식회사 | H29: 1660660 | I29: [팬오션] FY25 외부감사 (주기적 지정) | J29: 유가증권 | L29: 외항 화물 운송업 | M29: Services | N29: Oracle | O29: 5158962 | P29: 115.2.02 | Q29: O | R29: N/A | S29: N/A | T29: N/A | U29: N/A | V29: N/A | W29: N/A | X29: N/A | Y29: N/A | Z29: N/A | AA29: N/A | AB29: KR_KPMG Dashboards - IFRS v3.1 - Base Industry: UpdateMay2025 | AC29: Transportation and Warehousing | AD29: N | AL29: V | AM29: V | AN29: V | AO29: V | AP29: V | AQ29: V | AR29: V | BA29: 김미희 | BB29: mkim181@kr.kpmg.com | BE29: 이현강 | BF29: hyeonganglee@kr.kpmg.com | BG29: 지가현 | BH29: gahyunji@kr.kpmg.com | BI29: 최연석 | BJ29: ychoi@kr.kpmg.com | BK29: 김성배 | BL29: sungbaekim@kr.kpmg.com | BU29: 남종수 | BV29: jongsunam@kr.kpmg.com | CG29: 이요셉 | CH29: jlee176@kr.kpmg.com | CK29: 이정훈 | CL29: jlee520@kr.kpmg.com | CZ29: [팬오션] FY25 외부감사 (주기적 지정) | DA29: 5. 작업 완료 | DD29: =IF(AF29="제외요청", "V","") | DF29: V
C30: 1682164 | D30: 24 | E30: IM3 | F30: 1000314559 | G30: 에스케이지오센트릭 주식회사 | H30: 1682164 | I30: 에스케이지오센트릭 주식회사 FY2025 외부감사 | J30: 일반 | L30: 석유화학계 기초 화학물질 제조업 | M30: Energy and Natural Resources | N30: SAP | O30: 3311595 | P30: 115.2.13 | Q30: O | R30: N/A | S30: N/A | T30: N/A | U30: N/A | V30: N/A | W30: N/A | X30: N/A | Y30: N/A | Z30: N/A | AA30: N/A | AB30: KR_KPMG Dashboards - IFRS v3.1 - Oil & Gas Industry | AC30: Manufacturing | AD30: N | AE30: 45965 | AF30: 제외요청 | AG30: 위험하지 않은 전표들이 위험전표로 식별된 경우가 많음 | AL30: V | AM30: V | AN30: V | AO30: V | AP30: V | AQ30: V | AR30: V | AS30: V | BA30: 황인영 | BB30: ihwang7@kr.kpmg.com | BG30: 신재혁 | BH30: chaehyokshin@kr.kpmg.com | BI30: 차용재 | BJ30: ycha@kr.kpmg.com | BK30: 이종상 | BL30: jongsanglee@kr.kpmg.com | BU30: 정준영 | BV30: junyoungjung@kr.kpmg.com | CG30: 황서연 | CH30: seoyeonhwang@kr.kpmg.com | CK30: 이병관 | CL30: byeonggwalee@kr.kpmg.com | CZ30: 에스케이지오센트릭 주식회사 FY2025 외부감사 | DA30: 5. 작업 완료 | DD30: =IF(AF30="제외요청", "V","") -> V
A31: 박정빈 | B31: 완료 | C31: 1659929 | D31: 25 | E31: CM1 | F31: 1000326018 | G31: 하이트진로 ㈜ | H31: 1659929 | I31: FY2025 하이트진로 주식회사 외부감사 | J31: 유가증권 | L31: 소비재 | M31: Consumer Products | N31: Oracle | O31: 15703604 | P31: 115.2.02 115.2.13 | Q31: O | R31: N/A | S31: N/A | T31: N/A | U31: N/A | V31: N/A | W31: N/A | X31: N/A | Y31: N/A | Z31: N/A | AA31: N/A | AB31: KR_KPMG Dashboards - IFRS v3.1 - Retail Industry | AC31: Manufacturing | AD31: Y | AL31: V | AM31: V | AN31: V | AO31: V | AP31: V | AQ31: V | AR31: V | AT31: V | AU31: V | AW31: V | AX31: V | AY31: V | AZ31: V | BA31: 홍민정 | BB31: minjunghong@kr.kpmg.com | BE31: 이현강 | BF31: hyeonganglee@kr.kpmg.com | BG31: 현승임 | BH31: shyun@kr.kpmg.com | BI31: 정현진 | BJ31: hchung@kr.kpmg.com | BK31: 김중규 | BL31: joongkyukim@kr.kpmg.com | BU31: 김예현 | BV31: yaehyeonkim@kr.kpmg.com | CG31: 강건국 | CH31: konkukkang@kr.kpmg.com | CK31: 김정 | CL31: jkim444@kr.kpmg.com | CM31: 김준회 | CN31: junhoekim@kr.kpmg.com | CZ31: FY2025 하이트진로 주식회사 외부감사 | DA31: 5. 작업 완료 | DD31: =IF(AF31="제외요청", "V","") | DF31: V
C32: 1684186 | D32: 26 | E32: IM2 | F32: 1000315539 | G32: GS칼텍스㈜ | H32: 1684186 | I32: GSC FY25 회계감사 | J32: 일반 | L32: 원유 정제처리업 | M32: Energy and Natural Resources | N32: SAP ERP 6.0용 EHP6 | O32: 25626995 | P32: 115.2.02 115.2.13 | Q32: O | R32: N/A | S32: N/A | T32: 100.2.02 | U32: O | V32: N/A | W32: N/A | X32: N/A | Y32: N/A | Z32: N/A | AA32: N/A | AB32: KR_KPMG Dashboards - IFRS v3.1 - Oil & Gas Industry | AC32: Manufacturing | AD32: N | AI32: V | AL32: V | AM32: V | AN32: V | AO32: V | AP32: V | AQ32: V | AR32: V | AS32: V | BA32: 홍민정 | BB32: minjunghong@kr.kpmg.com | BE32: 이현강 | BF32: hyeonganglee@kr.kpmg.com | BG32: 현승임 | BH32: shyun@kr.kpmg.com | BI32: 나재광 | BJ32: jra@kr.kpmg.com | BK32: 정재욱 | BL32: jjoung@kr.kpmg.com | BU32: 주예솔 | BV32: yeasolju@kr.kpmg.com | CG32: 김찬양 | CH32: ckim12@kr.kpmg.com | CK32: 민정식 | CL32: jungsikmin@kr.kpmg.com | CM32: 정윤호 | CN32: yunhojeong@kr.kpmg.com | CZ32: GSC FY25 회계감사 | DA32: 5. 작업 완료 | DD32: =IF(AF32="제외요청", "V","") | DF32: V
C33: 1657107 | D33: 27 | E33: ICE2 | F33: 1000998259 | G33: 크래프톤 | H33: 1657107 | I33: 크래프톤 FY25 외부감사 | J33: 유가증권 | L33: 게임 소프트웨어 개발 및 공급업 | M33: Services | N33: SAP | O33: 675766 | P33: N/A | Q33: N/A | R33: N/A | S33: N/A | T33: 100.2.02 | U33: O | V33: N/A | W33: N/A | X33: N/A | Y33: N/A | Z33: N/A | AA33: N/A | AB33: KR_KPMG Dashboards - IFRS v3.1 - Media & Telecoms Industry | AC33: Information | AD33: N | AL33: V | AM33: V | AN33: V | AO33: V | AP33: V | AQ33: V | AR33: V | AW33: V | AX33: V | AY33: V | AZ33: V | BA33: 홍민정 | BB33: minjunghong@kr.kpmg.com | BG33: 김신 | BH33: skim137@kr.kpmg.com | BI33: 박성배 | BJ33: sungbaepark@kr.kpmg.com | BK33: 최연택 | BL33: yeontaekchoi@kr.kpmg.com | BU33: 정지훈 | BV33: jjung32@kr.kpmg.com | CG33: 최성환 | CH33: seonghwanchoi@kr.kpmg.com | CK33: 이다은 | CL33: dlee134@kr.kpmg.com | CZ33: 크래프톤 FY25 외부감사 | DA33: 5. 작업 완료 | DD33: =IF(AF33="제외요청", "V","") | DF33: V
C34: 1660170 | D34: 28 | E34: IGH | F34: 1000315188 | G34: (주) 제일기획 | H34: 1660170 | I34: [제일기획] FY2025 지정감사 | J34: 유가증권 | L34: 광고 대행업 | M34: Media | N34: SAP | O34: 1099438 | P34: 115.2.02 115.2.12b 115.2.13 115.3.01 | Q34: O | R34: 100.2.02 | S34: O | T34: N/A | U34: N/A | V34: N/A | W34: N/A | X34: N/A | Y34: N/A | Z34: N/A | AA34: N/A | AB34: KR_KPMG Dashboards - IFRS v3.1 - Media & Telecoms Industry | AC34: Information | AD34: Y | AI34: V | AL34: V | AM34: V | AN34: V | AO34: V | AP34: V | AQ34: V | AR34: V | AS34: V | AW34: V | AX34: V | AY34: V | AZ34: V | BA34: 노민경 | BB34: minkyungro@kr.kpmg.com | BE34: 이현강 | BF34: hyeonganglee@kr.kpmg.com | BG34: 김신 | BH34: skim137@kr.kpmg.com | BI34: 조일상 | BJ34: ijo@kr.kpmg.com | BK34: 이덕영 | BL34: deokyeonglee@kr.kpmg.com | BU34: 박종근 | BV34: jongkeunpark@kr.kpmg.com | CG34: 박태선 | CH34: taesunpark@kr.kpmg.com | CK34: 정진우 | CL34: jjung28@kr.kpmg.com | CM34: 최진환 | CN34: jinhwanchoi@kr.kpmg.com | CZ34: [제일기획] FY2025 지정감사 | DA34: 5. 작업 완료 | DD34: =IF(AF34="제외요청", "V","") | DF34: V
A35: 박정빈 | B35: 완료 | C35: 1660760 | D35: 29 | E35: IM2 | F35: 1000325863 | G35: 주식회사 E1 | H35: 1660760 | I35: E1 2025 회계감사(주기적지정) | J35: 유가증권 | L35: 기체연료 및 관련제품 도매업 | M35: Energy and Natural Resources | N35: SAP | O35: 5795399 | P35: 115.2.02 115.2.13 | Q35: O | R35: N/A | S35: N/A | T35: 100.2.02 | U35: O | V35: N/A | W35: N/A | X35: N/A | Y35: N/A | Z35: N/A | AA35: N/A | AB35: KR_KPMG Dashboards - IFRS v3.1 - Retail Industry | AC35: Wholesale Trade | AD35: Y | AI35: V | AL35: V | AM35: V | AN35: V | AO35: V | AP35: V | AQ35: V | AR35: V | AS35: V | AW35: V | AX35: V | AY35: V | AZ35: V | BA35: 노민경 | BB35: minkyungro@kr.kpmg.com | BE35: 이현강 | BF35: hyeonganglee@kr.kpmg.com | BG35: 신재혁 | BH35: chaehyokshin@kr.kpmg.com | BI35: 지동현 | BJ35: dchi@kr.kpmg.com | BK35: 조화수 | BL35: hwasoocho@kr.kpmg.com | BU35: 주예솔 | BV35: yeasolju@kr.kpmg.com | CG35: 김영일 | CH35: ykim47@kr.kpmg.com | CK35: 이승윤 | CL35: slee309@kr.kpmg.com | CZ35: E1 2025 회계감사(주기적지정) | DA35: 5. 작업 완료 | DD35: =IF(AF35="제외요청", "V","") | DF35: V
A36: 박정빈 | B36: 완료 | C36: 1669115 | D36: 30 | E36: CM1 | F36: 1000317405 | G36: 주식회사 현대백화점 | H36: 1669115 | I36: 현대백화점 2025년 외부감사 | J36: 유가증권 | L36: 유통업 | M36: Consumer Products | N36: HIFI (Legacy) | O36: 6016089 | P36: 115.2.13 | Q36: O | R36: N/A | S36: N/A | T36: 100.2.02 | U36: O | V36: N/A | W36: N/A | X36: N/A | Y36: N/A | Z36: N/A | AA36: N/A | AB36: KR_KPMG Dashboards - IFRS v3.1 - Retail Industry | AC36: Retail Trade | AD36: Y | AI36: V | AL36: V | AM36: V | AN36: V | AO36: V | AP36: V | AQ36: V | AR36: V | AW36: V | AX36: V | AY36: V | AZ36: V | BA36: 이채영 | BB36: clee46@kr.kpmg.com | BG36: 지가현 | BH36: gahyunji@kr.kpmg.com | BI36: 장현민 | BJ36: hyunminjang@kr.kpmg.com | BK36: 이상기 | BL36: sangkilee@kr.kpmg.com | BU36: 이세현 | BV36: sehyunlee@kr.kpmg.com | CG36: 김윤 | CH36: ykim85@kr.kpmg.com | CK36: 유현석 | CL36: hyunsukyoo@kr.kpmg.com | CM36: 박정주 | CN36: jungjoopark@kr.kpmg.com | CZ36: 현대백화점 2025년 외부감사 | DA36: 5. 작업 완료 | DD36: =IF(AF36="제외요청", "V","") | DF36: V
C37: 1664821 | D37: 31 | E37: IM2 | F37: 1000325221 | G37: 엘에스일렉트릭㈜ | H37: 1664821 | I37: 2025년 LS일렉트릭 지정감사 | J37: 유가증권 | L37: 전기회로 개폐, 보호장치 제조업 | AB37: KR_KPMG Dashboards - IFRS v3.1 - Base Industry: UpdateMay2025 | AC37: Manufacturing | AD37: N | AE37: 45958 | AF37: 제외요청 | AG37: 하나의 계정으로 진행매출과 일반매출 같이 분개. 비용은 금액적으로 유의하지 않아 절차 필요하지 않음 | AL37: V | AM37: V | AN37: V | AO37: V | AP37: V | BA37: 김수연 | BB37: sooyeonkim@kr.kpmg.com | BE37: 이현강 | BF37: hyeonganglee@kr.kpmg.com | BG37: 이승훈 | BH37: seunghoonlee@kr.kpmg.com | BI37: 이경석 | BJ37: kyungsuklee@kr.kpmg.com | BK37: 노상호 | BL37: sanghoroh@kr.kpmg.com | BU37: 한정희 | BV37: jeongheehan@kr.kpmg.com | CG37: 이창우 | CH37: clee45@kr.kpmg.com | CZ37: 2025년 LS일렉트릭 지정감사 | DA37: 9. 서비스 취소 | DD37: =IF(AF37="제외요청", "V","") -> V
C38: 1670498 | D38: 32 | E38: IM1 | F38: 1000316274 | G38: 에스케이씨 (주) | H38: 1670498 | I38: 2025년 SKC 법정감사 | J38: 유가증권 | L38: 기타 화학제품 제조업 | AD38: N | AE38: 45874 | AF38: 제외요청 | AG38: 순수 지주사임에 따라 MUS 불필요 | BA38: 엄정복 | BB38: juhm@kr.kpmg.com | BE38: 이현강 | BF38: hyeonganglee@kr.kpmg.com | BG38: 한상현 | BH38: sanghyunhan@kr.kpmg.com | BI38: 최연석 | BJ38: ychoi@kr.kpmg.com | BK38: 변상현 | BL38: sanghyunbyun@kr.kpmg.com | BU38: 원영인 | BV38: younginwon@kr.kpmg.com | CG38: 차순석 | CH38: sunseokcha@kr.kpmg.com | CZ38: #N/A | DA38: #N/A | DD38: =IF(AF38="제외요청", "V","") -> V
C39: 1668840 | D39: 33 | E39: IM3 | F39: 1000317452 | G39: 케이지모빌리티㈜ | H39: 1668840 | I39: FY25 KG 모빌리티_지정감사 | J39: 유가증권 | L39: 자동차용 엔진 및 자동차 제조업 | M39: Automotive | N39: SAP | O39: 96686944 | P39: 115.3.01 115.2.02 115.2.13 | Q39: O | R39: N/A | S39: N/A | T39: N/A | U39: N/A | V39: N/A | W39: N/A | X39: N/A | Y39: N/A | Z39: N/A | AA39: N/A | AB39: KR_KPMG Dashboards - IFRS v3.1 - Base Industry: UpdateMay2025 | AC39: Manufacturing | AD39: N | AI39: V | AL39: V | AM39: V | AN39: V | AO39: V | AP39: V | AQ39: V | AR39: V | AS39: V | AW39: V | AX39: V | AY39: V | AZ39: V | BA39: 이채영 | BB39: clee46@kr.kpmg.com | BE39: 이현강 | BF39: hyeonganglee@kr.kpmg.com | BG39: 김신 | BH39: skim137@kr.kpmg.com | BI39: 나재광 | BJ39: jra@kr.kpmg.com | BK39: 이종상 | BL39: jongsanglee@kr.kpmg.com | BU39: 정준영 | BV39: junyoungjung@kr.kpmg.com | CG39: 박승현 | CH39: seunghyunpark@kr.kpmg.com | CK39: 김휘재 | CL39: hweejaekim@kr.kpmg.com | CM39: 김재원 | CN39: jkim442@kr.kpmg.com | CO39: 최재영 | CP39: jchoi103@kr.kpmg.com | CQ39: 이성민 | CR39: slee424@kr.kpmg.com | CZ39: FY25 KG 모빌리티_지정감사 | DA39: 5. 작업 완료 | DD39: =IF(AF39="제외요청", "V","") | DF39: V
A40: 김찬영 | B40: 완료 | C40: 1667049 | D40: 34 | E40: ICE3 | F40: 1000317380 | G40: (주)엘앤에프 | H40: 1667049 | I40: 엘앤에프 FY25 지정감사 | J40: 유가증권 | L40: 운송장비용 이차전지 제조업 | M40: Industrial Products | N40: SAP | O40: 1338782 | P40: 115.3.01 115.2.02 115.2.13 | Q40: O | R40: N/A | S40: N/A | T40: 100.2.02 | U40: O | V40: N/A | W40: N/A | X40: N/A | Y40: N/A | Z40: N/A | AA40: N/A | AB40: KR_KPMG Dashboards - IFRS v3.1 - Base Industry: UpdateMay2025 | AC40: Manufacturing | AD40: N | AL40: V | AM40: V | AN40: V | AO40: V | AP40: V | AQ40: V | AR40: V | AS40: V | AW40: V | AX40: V | AY40: V | AZ40: V | BA40: 전혜지 | BB40: hjeon6@kr.kpmg.com | BE40: 이현강 | BF40: hyeonganglee@kr.kpmg.com | BG40: 김신 | BH40: skim137@kr.kpmg.com | BI40: 최세홍 | BJ40: sehongchoi@kr.kpmg.com | BK40: 강인혜 | BL40: ikang@kr.kpmg.com | BU40: 이동규 | BV40: donggyulee@kr.kpmg.com | CG40: 최민기 | CH40: minkichoi@kr.kpmg.com | CK40: 김다정 | CL40: dajungkim@kr.kpmg.com | CM40: 김아정 | CN40: ajungkim@kr.kpmg.com | CZ40: 엘앤에프 FY25 지정감사 | DA40: 5. 작업 완료 | DD40: =IF(AF40="제외요청", "V","") | DF40: V
C41: 1669145 | D41: 35 | E41: ICE1 | F41: 1001210610 | G41: 에스케이스퀘어 주식회사 | H41: 1669145 | I41: SK스퀘어 FY25 외부감사 | J41: 유가증권 | L41: 지주회사 | AB41: KR_KPMG Dashboards - IFRS v3.1 - Banking Industry | AC41: Management of Companies and Enterprises | AD41: N | AE41: 45960 | AF41: 제외요청 | AG41: 지주회사로 AITS 적용할만한 RMM 없음 | BA41: 이현경 | BB41: hyunkyunglee@kr.kpmg.com | BE41: 이현강 | BF41: hyeonganglee@kr.kpmg.com | BG41: 오헌창 | BH41: heonchangoh@kr.kpmg.com | BI41: 신문철 | BJ41: moonchulshin@kr.kpmg.com | BK41: 박성배 | BL41: sungbaepark@kr.kpmg.com | BU41: 양호철 | BV41: hocheolyang@kr.kpmg.com | CG41: 양호철 | CH41: hocheolyang@kr.kpmg.com | CZ41: #N/A | DA41: #N/A | DD41: =IF(AF41="제외요청", "V","") -> V
C42: 1661219 | D42: 36 | E42: IM1 | F42: 1000315889 | G42: 에이치디현대미포 주식회사 | H42: 1661219 | I42: FY2025_HD현대미포_지정감사 | J42: 유가증권 | L42: 선박 및 수상 부유 구조물 건조업 | AD42: N | AE42: 45874 | AF42: 제외요청 | AG42: 매출은 모든 CAR이 Base보다 위험하다고 평가하여 적용 불가. 비용은 샘플수가 적음(30건 미만) | BA42: 노민경 | BB42: minkyungro@kr.kpmg.com | BE42: 서은아 | BF42: eseo@kr.kpmg.com | BG42: 오헌창 | BH42: heonchangoh@kr.kpmg.com | BI42: 이채능 | BJ42: chaeneunglee@kr.kpmg.com | BK42: 차용재 | BL42: ycha@kr.kpmg.com | BU42: 김성일 | BV42: seongilkim@kr.kpmg.com | CG42: 황기명 | CH42: gimyeonghwang@kr.kpmg.com | CZ42: #N/A | DA42: #N/A | DD42: =IF(AF42="제외요청", "V","") -> V
C43: 1669178 | D43: 37 | E43: ICE1 | F43: 1000316385 | G43: (주)엔씨소프트 | H43: 1669178 | I43: 엔씨소프트_FY25_외부감사 | J43: 유가증권 | L43: 소프트웨어 개발 및 공급업 | O43: 502608 | P43: 115.2.02 115.2.12b 115.2.13 115.3.01 | Q43: O | R43: N/A | S43: N/A | T43: 100.2.02 | U43: O | V43: N/A | W43: N/A | X43: N/A | Y43: N/A | Z43: N/A | AA43: N/A | AB43: KR_KPMG Dashboards - IFRS v3.1 - Media & Telecoms Industry | AC43: Information | AD43: N | AL43: V | AM43: V | AN43: V | AO43: V | AP43: V | AQ43: V | AR43: V | BA43: 정주희 | BB43: jchung3@kr.kpmg.com | BG43: 오헌창 | BH43: heonchangoh@kr.kpmg.com | BI43: 한상현 | BJ43: sanghyunhan@kr.kpmg.com | BK43: 박성배 | BL43: sungbaepark@kr.kpmg.com | BU43: 안재영 | BV43: jahn6@kr.kpmg.com | CG43: 강민구 | CH43: mkang8@kr.kpmg.com | CK43: 한석화 | CL43: shan44@kr.kpmg.com | CZ43: 엔씨소프트_FY25_외부감사 | DA43: 5. 작업 완료 | DD43: =IF(AF43="제외요청", "V","") | DF43: V
C44: 1666343 | D44: 38 | E44: IM2 | F44: 1000850087 | G44: 송원산업㈜ | H44: 1666343 | I44: 25년 송원산업 지정감사 | J44: 유가증권 | L44: 기타 화학제품 제조업 | M44: 제품산업 | N44: D365 | O44: 1255732 | P44: 115.2.02 | Q44: O | R44: N/A | S44: N/A | T44: N/A | U44: N/A | V44: N/A | W44: N/A | X44: N/A | Y44: N/A | Z44: N/A | AA44: N/A | AB44: KR_KPMG Dashboards - IFRS v3.1 - Base Industry: UpdateMay2025 | AC44: Manufacturing | AD44: N | AL44: V | AM44: V | AN44: V | AO44: V | AP44: V | AQ44: V | AR44: V | BA44: 김미희 | BB44: mkim181@kr.kpmg.com | BE44: 서은아 | BF44: eseo@kr.kpmg.com | BG44: 이승훈 | BH44: seunghoonlee@kr.kpmg.com | BI44: 김현석 | BJ44: hyunsukkim@kr.kpmg.com | BK44: 황현동 | BL44: hyundonghwang@kr.kpmg.com | BU44: 서창원 | BV44: changwonseo@kr.kpmg.com | CG44: 문형준 | CH44: hmoon2@kr.kpmg.com | CK44: 정선우 | CL44: sunwoojung@kr.kpmg.com | CM44: 이정우 | CN44: jlee445@kr.kpmg.com | CZ44: 25년 송원산업 지정감사 | DA44: 5. 작업 완료 | DD44: =IF(AF44="제외요청", "V","") | DF44: V
C45: 1660527 | D45: 39 | E45: IM4 | F45: 1000882638 | G45: 주식회사 하림지주 | H45: 1660527 | I45: 하림지주 - FY25 외부감사 | J45: 코스닥 | L45: 지주회사 | AB45: KR_KPMG Dashboards - IFRS v3.1 - Banking Industry | AC45: Management of Companies and Enterprises | AD45: N | AE45: 46059 | AF45: 제외요청 | AG45: 지주회사로 AITS 적용할만한 RMM 없음 | BA45: 김미희 | BB45: mkim181@kr.kpmg.com | BE45: 서은아 | BF45: eseo@kr.kpmg.com | BG45: 지가현 | BH45: gahyunji@kr.kpmg.com | BI45: 김태준 | BJ45: tkim@kr.kpmg.com | BK45: 김도현 | BL45: dohyunkim@kr.kpmg.com | BU45: 남종수 | BV45: jongsunam@kr.kpmg.com | CG45: 이태섭 | CH45: taeseoblee@kr.kpmg.com | CZ45: #N/A | DA45: #N/A | DC45: V | DD45: =IF(AF45="제외요청", "V","") -> V
C46: 1669416 | D46: 40 | E46: IM1 | F46: 1000314823 | G46: 에이치디한국조선해양 (주) | H46: 1669416 | I46: FY2025 에이치디한국조선해양 주식회사 외부감사 | J46: 유가증권 | L46: 지주회사 | AD46: N | AE46: 45873 | AF46: 제외요청 | AG46: 별도재무제표에서 중요성금액 대비 손익 규모가 작은 상태. 실증절차 수행 시 기존의 샘플링 방식을 적용해도 표본 개수가 10개 미만. | BA46: 김미희 | BB46: mkim181@kr.kpmg.com | BG46: 지가현 | BH46: gahyunji@kr.kpmg.com | BI46: 이상근 | BJ46: sangkeunlee@kr.kpmg.com | BK46: 전원표 | BL46: wjeon@kr.kpmg.com | BU46: 황인찬 | BV46: inchanhwang@kr.kpmg.com | CG46: 윤호원 | CH46: howonyoon@kr.kpmg.com | CZ46: #N/A | DA46: #N/A | DD46: =IF(AF46="제외요청", "V","") -> V
C47: 1661221 | D47: 41 | E47: ICE1 | F47: 1000314612 | G47: (주)엘지헬로비전 | H47: 1661221 | I47: FY2025 엘지헬로비전 외부감사 | J47: 유가증권 | L47: 유선 방송업 | O47: 16653342 | P47: 115.2.02 115.2.12b 115.2.13 115.3.01 | Q47: O | R47: N/A | S47: N/A | T47: 100.2.02 | U47: O | V47: N/A | W47: N/A | X47: N/A | Y47: N/A | Z47: N/A | AA47: N/A | AB47: KR_KPMG Dashboards - IFRS v3.1 - Media & Telecoms Industry | AC47: Information | AD47: N | AL47: V | AM47: V | AN47: V | AO47: V | AP47: V | AQ47: V | AR47: V | BA47: 이영롱 | BB47: younglonglee@kr.kpmg.com | BE47: 서은아 | BF47: eseo@kr.kpmg.com | BG47: 이승훈 | BH47: seunghoonlee@kr.kpmg.com | BI47: 노정한 | BJ47: jroh@kr.kpmg.com | BK47: 설하영 | BL47: hsul@kr.kpmg.com | BU47: 이한수 | BV47: hlee42@kr.kpmg.com | CG47: 유혜경 | CH47: hyegyeongryu@kr.kpmg.com | CZ47: FY2025 엘지헬로비전 외부감사 | DA47: 5. 작업 완료 | DD47: =IF(AF47="제외요청", "V","") | DF47: V
C48: 1660759 | D48: 42 | E48: IM3 | F48: 1000322973 | G48: 주식회사 이노션 | H48: 1660759 | I48: FY25 이노션 외부감사(주기적지정) | J48: 유가증권 | L48: 광고 대행업 | M48: Media | N48: SAP | O48: 461083 | P48: N/A | Q48: N/A | R48: 100.2.02 | S48: O | T48: 100.2.02 | U48: O | V48: N/A | W48: N/A | X48: N/A | Y48: N/A | Z48: N/A | AA48: N/A | AB48: KR_KPMG Dashboards - IFRS v3.1 - Media & Telecoms Industry | AC48: Information | AD48: N | AL48: V | AM48: V | AN48: V | AO48: V | AP48: V | AQ48: V | AR48: V | AS48: V | BA48: 송은혜 | BB48: esong7@kr.kpmg.com | BC48: 홍민정 | BD48: minjunghong@kr.kpmg.com | BE48: 이현강 | BF48: hyeonganglee@kr.kpmg.com | BG48: 한상현 | BH48: sanghyunhan@kr.kpmg.com | BI48: 신문철 | BJ48: moonchulshin@kr.kpmg.com | BK48: 박경호 | BL48: kyunghopark@kr.kpmg.com | BU48: 이진호 | BV48: jinholee1@kr.kpmg.com | CG48: 임이랑 | CH48: yiranglim@kr.kpmg.com | CK48: 남태은 | CL48: tnam1@kr.kpmg.com | CM48: 석민재 | CN48: minjaeseok@kr.kpmg.com | CZ48: FY25 이노션 외부감사(주기적지정) | DA48: 5. 작업 완료 | DD48: =IF(AF48="제외요청", "V","") | DF48: V
A49: 박정빈 | B49: 완료 | C49: 1665498 | D49: 43 | E49: IGH | F49: 1000314998 | G49: 대한전선 ㈜ | H49: 1665498 | I49: [대한전선] FY2025 지정감사 | J49: 유가증권 | L49: 기타 절연선 및 케이블 제조업 | M49: Industrial Products / Construction | N49: SAP | O49: 11485002 | P49: 115.2.02 115.2.13 | Q49: X | R49: N/A | S49: N/A | T49: N/A | U49: N/A | V49: N/A | W49: N/A | X49: N/A | Y49: N/A | Z49: N/A | AA49: N/A | AB49: KR_KPMG Dashboards - IFRS v3.1 - Base Industry: UpdateMay2025 | AC49: Manufacturing | AD49: N | AK49: V | AL49: V | AM49: V | AN49: V | AO49: V | AP49: V | AQ49: V | AR49: V | AS49: V | AW49: V | AX49: V | AY49: V | AZ49: V | BA49: 전혜지 | BB49: hjeon6@kr.kpmg.com | BC49: 홍민정 | BD49: minjunghong@kr.kpmg.com | BE49: 이현강 | BF49: hyeonganglee@kr.kpmg.com | BG49: 신동명 | BH49: dongmyungshin@kr.kpmg.com | BI49: 구승회 | BJ49: seunghoikoo@kr.kpmg.com | BK49: 엄준식 | BL49: junsikuhm@kr.kpmg.com | BU49: 노영일 | BV49: yno@kr.kpmg.com | CG49: 고영기 | CH49: youngkigo@kr.kpmg.com | CK49: 한민우 | CL49: minwoohan@kr.kpmg.com | CZ49: [대한전선] FY2025 지정감사 | DA49: 5. 작업 완료 | DD49: =IF(AF49="제외요청", "V","") | DF49: V
C50: 1684040 | D50: 44 | E50: IM1 | F50: 1000325060 | G50: 주식회사 미스토홀딩스 | H50: 1684040 | I50: FY25 미스토홀딩스 법정감사 | J50: 유가증권 | L50: 생활용품 도매업 | AD50: N | AE50: 45874 | AF50: 제외요청 | AG50: 지주회사로 배당수익이 전체 매출의 99%를 차지하고 있으며, 전수로 증빙을 확인. 비용도 감가상각비와 인건비가 80%이상. 나머지는 PM미만. | BA50: 이채영 | BB50: clee46@kr.kpmg.com | BG50: 김신 | BH50: skim137@kr.kpmg.com | BI50: 강인혜 | BJ50: ikang@kr.kpmg.com | BK50: 박상훈 | BL50: sanghoonpark@kr.kpmg.com | BU50: 이민규 | BV50: mingyulee@kr.kpmg.com | CG50: 김소희 | CH50: skim106@kr.kpmg.com | CZ50: #N/A | DA50: #N/A | DD50: =IF(AF50="제외요청", "V","") -> V
C51: 1672093 | D51: 45 | E51: ICE2 | F51: 1000708387 | G51: 주식회사 카카오게임즈 | H51: 1672093 | I51: 2025년 카카오게임즈 외부감사 | J51: 코스닥 | L51: 게임 소프트웨어 개발 및 공급업 | M51: Service | N51: SAP ERP SAPLSMTR_NAVIGATION | O51: 285233 | P51: N/A | Q51: N/A | R51: N/A | S51: O | T51: 100.2.02 | U51: N/A | V51: N/A | W51: N/A | X51: N/A | Y51: N/A | Z51: N/A | AA51: N/A | AB51: KR_KPMG Dashboards - IFRS v3.1 - Media & Telecoms Industry | AC51: Information | AD51: N | AJ51: V | AL51: V | AM51: V | AN51: V | AO51: V | AP51: V | AQ51: V | AR51: V | AS51: V | AW51: V | AX51: V | AY51: V | AZ51: V | BA51: 김수영 | BB51: skim40@kr.kpmg.com | BE51: 이현강 | BF51: hyeonganglee@kr.kpmg.com | BG51: 이승훈 | BH51: seunghoonlee@kr.kpmg.com | BI51: 강승미 | BJ51: seungmikang@kr.kpmg.com | BK51: 염승훈 | BL51: syeom@kr.kpmg.com | BU51: 김세모 | BV51: semokim@kr.kpmg.com | CG51: 박준현 | CH51: jpark77@kr.kpmg.com | CK51: 이세현 | CL51: sehyeonlee@kr.kpmg.com | CM51: 김재유 | CN51: jaeyukim@kr.kpmg.com | CZ51: 2025년 카카오게임즈 외부감사 | DA51: 5. 작업 완료 | DD51: =IF(AF51="제외요청", "V","") | DF51: V
C52: 1692146 | D52: 46 | E52: IM2 | F52: 1000317436 | G52: 한국중부발전 (주) | H52: 1692146 | I52: 2025년 한국중부발전(주) 회계감사 | O52: 2262294 | AB52: KR_KPMG Dashboards - IFRS v3.1 - Base Industry: UpdateMay2025 | AC52: Utilities | AD52: N | AE52: 46043 | AF52: 제외요청 | AG52: 이미 절차를 다 수행해놓음 | AI52: V | AL52: V | BA52: 김수연 | BB52: sooyeonkim@kr.kpmg.com | BE52: 서은아 | BF52: eseo@kr.kpmg.com | BG52: Cao, Leah | BH52: leahcao@kr.kpmg.com | BI52: 한상현 | BJ52: sanghyunhan@kr.kpmg.com | BK52: 이학범 | BL52: hakbeomlee@kr.kpmg.com | BU52: 김소라 | BV52: sorakim@kr.kpmg.com | CG52: 양혁준 | CH52: hyeokjunyang@kr.kpmg.com | CZ52: 2025년 한국중부발전(주) 회계감사 | DA52: 4. 전처리 오류 처리 중 | DD52: =IF(AF52="제외요청", "V","") -> V
A53: 박정빈 | B53: 완료 | C53: 1667534 | D53: 47 | E53: ICE2 | F53: 1000712754 | G53: 주식회사펄어비스 | H53: 1667534 | I53: FY25 펄어비스 외부감사 | J53: 코스닥 | L53: 유선 온라인 게임 소프트웨어 개발 및 공급업 | M53: Services | N53: SAP | O53: 104412 | P53: N/A | Q53: N/A | R53: N/A | S53: N/A | T53: 100.2.02 | U53: O | V53: N/A | W53: N/A | X53: N/A | Y53: N/A | Z53: N/A | AA53: N/A | AB53: KR_KPMG Dashboards - IFRS v3.1 - Media & Telecoms Industry | AC53: Information | AD53: N | AI53: V | AL53: V | AM53: V | AN53: V | AO53: V | AP53: V | AQ53: V | AR53: V | BA53: 엄정복 | BB53: juhm@kr.kpmg.com | BE53: 이현강 | BF53: hyeonganglee@kr.kpmg.com | BG53: 신재혁 | BH53: chaehyokshin@kr.kpmg.com | BI53: 최이현 | BJ53: yeehyunchoi@kr.kpmg.com | BK53: 최연택 | BL53: yeontaekchoi@kr.kpmg.com | BU53: 차정웅 | BV53: jeongungcha@kr.kpmg.com | CG53: 원창일 | CH53: changilwon@kr.kpmg.com | CK53: 정여지 | CL53: yeojijeong@kr.kpmg.com | CM53: 박철완 | CN53: chulwanpark@kr.kpmg.com | CZ53: FY25 펄어비스 외부감사 | DA53: 5. 작업 완료 | DD53: =IF(AF53="제외요청", "V","") | DF53: V
C54: 1661004 | D54: 48 | E54: ICE1 | F54: 1000317098 | G54: ㈜에스엠엔터테인먼트 | H54: 1661004 | I54: 에스엠엔터테인먼트_FY2025_외부감사 | J54: 코스닥 | L54: 음악 및 기타 오디오물 출판업 | M54: Media | N54: SAP S/4 HANA | O54: 1379887 | P54: 115.2.02 115.2.13 | Q54: O | R54: N/A | S54: N/A | T54: N/A | U54: N/A | V54: N/A | W54: N/A | X54: N/A | Y54: N/A | Z54: N/A | AA54: N/A | AB54: KR_KPMG Dashboards - IFRS v3.1 - Media & Telecoms Industry | AC54: Information | AD54: N | AI54: V | AL54: V | AM54: V | AN54: V | AO54: V | AP54: V | AQ54: V | AR54: V | AS54: V | AW54: V | AX54: V | AY54: V | AZ54: V | BA54: 이영롱 | BB54: younglonglee@kr.kpmg.com | BC54: 홍민정 | BD54: minjunghong@kr.kpmg.com | BE54: 서은아 | BF54: eseo@kr.kpmg.com | BG54: 오헌창 | BH54: heonchangoh@kr.kpmg.com | BI54: 김익찬 | BJ54: ikchankim@kr.kpmg.com | BK54: 이동윤 | BL54: dongyoonlee@kr.kpmg.com | BU54: 강대웅 | BV54: daewoongkang@kr.kpmg.com | CG54: 임헌상 | CH54: heonsanglim@kr.kpmg.com | CK54: 성치훈 | CL54: chihoonsung@kr.kpmg.com | CM54: 박소윤 | CN54: soyunpark@kr.kpmg.com | CZ54: 에스엠엔터테인먼트_FY2025_외부감사 | DA54: 5. 작업 완료 | DD54: =IF(AF54="제외요청", "V","") | DF54: V
C55: 1708795 | D55: 49 | E55: CM2 | F55: 1000326360 | G55: 아이에스동서 ㈜ | H55: 1708795 | I55: [아이에스동서] FY2025 지정감사_CM2 | J55: 유가증권 | L55: 콘크리트, 레미콘 및 기타 시멘트, 플라스터 제품 제조업 | AB55: KR_KPMG Dashboards - IFRS v3.1 - Base Industry: UpdateMay2025 | AC55: Manufacturing | AD55: N | AE55: 45905 | AF55: 제외요청 | AG55: 진행기준을 적용하는 건설 및 엔지니어링 등 수주산업에 해당하며, 수익 관련 RMM을 Base 보다 높게 평가하였습니다. | BK55: 정현진 | BL55: hchung@kr.kpmg.com | BU55: 한준희 | BV55: junheehan@kr.kpmg.com | CG55: 진영주 | CH55: youngjoojin@kr.kpmg.com | CZ55: #N/A | DA55: #N/A | DD55: =IF(AF55="제외요청", "V","") -> V
C56: 1670157 | D56: 50 | E56: CM1 | F56: 1000923332 | G56: 주식회사 에스에스지닷컴 | H56: 1670157 | I56: 에스에스지닷컴_FY2025_지정감사 | J56: 일반 | L56: 무점포 소매업 | O56: 389003 | P56: 115.2.02 115.2.12.b 115.2.13 115.3.01 | Q56: O | R56: N/A | S56: N/A | T56: 100.2.02 | U56: O | V56: N/A | W56: N/A | X56: N/A | Y56: N/A | Z56: N/A | AA56: N/A | AB56: KR_KPMG Dashboards - IFRS v3.1 - Retail Industry | AC56: Retail Trade | AD56: N | AL56: V | AM56: V | AN56: V | AO56: V | AP56: V | AQ56: V | AR56: V | BA56: 이현경 | BB56: hyunkyunglee@kr.kpmg.com | BE56: 서은아 | BF56: eseo@kr.kpmg.com | BG56: 오헌창 | BH56: heonchangoh@kr.kpmg.com | BI56: 구승회 | BJ56: seunghoikoo@kr.kpmg.com | BK56: 이주형 | BL56: juhyunglee@kr.kpmg.com | BU56: 김진목 | BV56: jinmokkim@kr.kpmg.com | CG56: 홍은정 | CH56: eunjeonghong@kr.kpmg.com | CZ56: 에스에스지닷컴_FY2025_지정감사 | DA56: 5. 작업 완료 | DD56: =IF(AF56="제외요청", "V","") | DF56: V
C57: 1699032 | D57: 51 | E57: IM4 | F57: 1000316397 | G57: 한국남동발전 ㈜ | H57: 1699032 | I57: 2025년 회계감사_한국남동발전 | AB57: KR_KPMG Dashboards - IFRS v3.1 - Base Industry: UpdateMay2025 | AC57: Utilities | AD57: N | AE57: 45975 | AF57: 제외요청 | AG57: 일정상 적용 어려움 | BA57: 정주희 | BB57: jchung3@kr.kpmg.com | BE57: 서은아 | BF57: eseo@kr.kpmg.com | BG57: Cao, Leah | BH57: leahcao@kr.kpmg.com | BI57: 남상민 | BJ57: sangminnam@kr.kpmg.com | BK57: 이규홍 | BL57: kyuhonglee1@kr.kpmg.com | BU57: 박수민 | BV57: suminpark@kr.kpmg.com | CG57: 신양호 | CH57: yanghoshin@kr.kpmg.com | CZ57: #N/A | DA57: #N/A | DD57: =IF(AF57="제외요청", "V","") -> V
A58: 박정빈 | B58: 완료 | C58: 1698943 | D58: 52 | E58: IM2 | F58: 1000317231 | G58: 한국남부발전주식회사 | H58: 1698943 | I58: FY25_한국남부발전_외부감사 | J58: 채권상장 | L58: 기타 발전업 | M58: Energy and Natural Resources | N58: SAP S/4 HANA | O58: 3757092 | P58: N/A | Q58: N/A | R58: 100.2.02 | S58: O | T58: N/A | U58: N/A | V58: N/A | W58: N/A | X58: N/A | Y58: N/A | Z58: N/A | AA58: N/A | AB58: KR_KPMG Dashboards - IFRS v3.1 - Base Industry: UpdateMay2025 | AC58: Utilities | AD58: N | AL58: V | AM58: V | AN58: V | AO58: V | AP58: V | AQ58: V | AR58: V | AS58: V | AW58: V | AX58: V | AY58: V | AZ58: V | BA58: 노민경 | BB58: minkyungro@kr.kpmg.com | BE58: 이현강 | BF58: hyeonganglee@kr.kpmg.com | BG58: Cao, Leah | BH58: leahcao@kr.kpmg.com | BI58: 한상현 | BJ58: sanghyunhan@kr.kpmg.com | BK58: 정양기 | BL58: yangkijung@kr.kpmg.com | BU58: 이종록 | BV58: jongroklee@kr.kpmg.com | CG58: 이진주 | CH58: jinjulee@kr.kpmg.com | CK58: 김형진 | CL58: hkim111@kr.kpmg.com | CZ58: FY25_한국남부발전_외부감사 | DA58: 5. 작업 완료 | DD58: =IF(AF58="제외요청", "V","") | DF58: V
C59: 1684059 | D59: 53 | E59: IM4 | F59: 1000860827 | G59: SK인천석유화학㈜ | H59: 1684059 | I59: SK인천석유화학_FY2025 외부감사 | J59: 일반 | L59: 원유 정제처리업 | AB59: KR_KPMG Dashboards - IFRS v3.1 - Oil & Gas Industry | AC59: Manufacturing | AD59: N | AE59: 45903 | AF59: 제외요청 | AG59: 1. 수익 : 전수로 TOD 진행할 예정으로 AITS 미사용 2. 비용 : Usecase에 부합하지 아니함. | BA59: 이채영 | BB59: clee46@kr.kpmg.com | BG59: 이승훈 | BH59: seunghoonlee@kr.kpmg.com | BI59: 김현석 | BJ59: hyunsukkim@kr.kpmg.com | BK59: 이호철 | BL59: hochullee@kr.kpmg.com | BU59: 김현기 | BV59: hkim51@kr.kpmg.com | CG59: 정진욱 | CH59: jinukjeong@kr.kpmg.com | CZ59: #N/A | DA59: #N/A | DD59: =IF(AF59="제외요청", "V","") -> V
C60: 1683952 | D60: 54 | E60: IM4 | F60: 1000314537 | G60: 한국서부발전주식회사 | H60: 1683952 | I60: [한국서부발전] FY2025 회계감사 | AB60: KR_KPMG Dashboards - IFRS v3.1 - Base Industry: UpdateMay2025 | AC60: Utilities | AD60: N | AE60: 45903 | AF60: 제외요청 | AG60: 1. 수익 : 이미 분반기 검토 시 AITS를 사용하지 않고 TOD 수행. 2. 비용 : Usecase에 부합하지 아니함. | BA60: 전혜지 | BB60: hjeon6@kr.kpmg.com | BE60: 서은아 | BF60: eseo@kr.kpmg.com | BG60: Cao, Leah | BH60: leahcao@kr.kpmg.com | BI60: 남상민 | BJ60: sangminnam@kr.kpmg.com | BK60: 김연정 | BL60: yeonjungkim@kr.kpmg.com | BU60: 김현기 | BV60: hkim51@kr.kpmg.com | CZ60: #N/A | DA60: #N/A | DD60: =IF(AF60="제외요청", "V","") -> V
C61: 1699021 | D61: 55 | E61: IM4 | F61: 1000317365 | G61: 한국동서발전 ㈜ | H61: 1699021 | I61: 2025년 회계감사_한국동서발전 | AB61: KR_KPMG Dashboards - IFRS v3.1 - Base Industry: UpdateMay2025 | AC61: Utilities | AD61: N | AE61: 46063 | AF61: 제외요청 | AG61: 일정상 적용 어려움 | BA61: 정주희 | BB61: jchung3@kr.kpmg.com | BE61: 이현강 | BF61: hyeonganglee@kr.kpmg.com | BG61: Cao, Leah | BH61: leahcao@kr.kpmg.com | BI61: 남상민 | BJ61: sangminnam@kr.kpmg.com | BK61: 김성배 | BL61: sungbaekim@kr.kpmg.com | BU61: 김현기 | BV61: hkim51@kr.kpmg.com | CG61: 김도희 | CH61: dkim240@kr.kpmg.com | CZ61: #N/A | DA61: #N/A | DC61: V | DD61: =IF(AF61="제외요청", "V","") -> V
A62: 박정빈 | B62: 완료 | C62: 1683535 | D62: 56 | E62: ICE2 | F62: 1000326195 | G62: 씨제이프레시웨이주식회사 | H62: 1683535 | I62: FY2025 씨제이프레시웨이 외부감사 | J62: 코스닥 | L62: 가공식품 도매업 | N62: SAP | O62: 262846595 | P62: 115.2.02 115.2.12.b 115.2.13 115.3.01 | Q62: O | R62: N/A | S62: N/A | T62: 100.2.02 | U62: O | V62: N/A | W62: N/A | X62: N/A | Y62: N/A | Z62: N/A | AA62: N/A | AB62: KR_KPMG Dashboards - IFRS v3.1 - Retail Industry | AC62: Retail Trade | AD62: Y | AI62: V | AL62: V | AM62: V | AN62: V | AO62: V | AP62: V | AQ62: V | AR62: V | AS62: V | AW62: V | AX62: V | AY62: V | AZ62: V | BA62: 김수영 | BB62: skim40@kr.kpmg.com | BG62: 현승임 | BH62: shyun@kr.kpmg.com | BI62: 최진석 | BJ62: jinseokchoi@kr.kpmg.com | BK62: 김정기 | BL62: jungkikim@kr.kpmg.com | BU62: 정지훈 | BV62: jjung32@kr.kpmg.com | CG62: 강동민 | CH62: dongminkang@kr.kpmg.com | CK62: 오움남 | CL62: uoh1@kr.kpmg.com | CZ62: FY2025 씨제이프레시웨이 외부감사 | DA62: 5. 작업 완료 | DD62: =IF(AF62="제외요청", "V","") | DF62: V
C63: 1682989 | D63: 57 | E63: CM2 | F63: 1000316773 | G63: (주)코리아세븐 | H63: 1682989 | I63: FY2025 코리아세븐 법정감사 | J63: 일반 | L63: 상품 중개업 | AB63: KR_KPMG Dashboards - IFRS v3.1 - Retail Industry | AC63: Retail Trade | AD63: N | AE63: 46044 | AF63: 제외요청 | AG63: 이미 절차를 다 수행해놓음 | AL63: V | AM63: V | BA63: 전혜지 | BB63: hjeon6@kr.kpmg.com | BC63: 홍민정 | BD63: minjunghong@kr.kpmg.com | BE63: 서은아 | BF63: eseo@kr.kpmg.com | BG63: 신재혁 | BH63: chaehyokshin@kr.kpmg.com | BI63: 이용호 | BJ63: yongholee@kr.kpmg.com | BK63: 김시우 | BL63: siwookim@kr.kpmg.com | BU63: 오승재 | BV63: seungjaeoh@kr.kpmg.com | CG63: 김성동 | CH63: skim127@kr.kpmg.com | CZ63: FY2025 코리아세븐 법정감사 | DA63: 1. 서비스 요청 | DD63: =IF(AF63="제외요청", "V","") -> V
C64: 1714218 | D64: 58 | E64: IM4 | F64: 1000315949 | G64: 한국석유공사 | H64: 1714218 | I64: FY25 한국석유공사 외부감사 | AB64: KR_KPMG Dashboards - IFRS v3.1 - Oil & Gas Industry | AC64: Mining | AD64: N | AE64: 45902 | AF64: 제외요청 | AG64: 수익 및 비용의 RMM이 모두 Base 초과이거나 RM이어서 AITS 적용 Usecase에 부합하지 아니함. | BK64: 이경석 | BL64: kyungsuklee@kr.kpmg.com | BU64: 이상민 | BV64: slee14@kr.kpmg.com | CG64: 장지형 | CH64: jihyeongjang@kr.kpmg.com | CZ64: #N/A | DA64: #N/A | DD64: =IF(AF64="제외요청", "V","") -> V
C65: 1664607 | D65: 59 | E65: CM1 | F65: 1000317517 | G65: (주)동원에프앤비 | H65: 1664607 | I65: 동원F&B_외부감사_FY25 | J65: 유가증권 | L65: 기타식품제조업 | M65: Consumer Products | N65: SAP S/4 HANA | O65: 128984268 | P65: 115.2.12.b 115.2.13 | Q65: O | R65: N/A | S65: N/A | T65: N/A | U65: N/A | V65: N/A | W65: N/A | X65: N/A | Y65: N/A | Z65: N/A | AA65: N/A | AB65: KR_KPMG Dashboards - IFRS v3.1 - Base Industry: UpdateMay2025 | AC65: Manufacturing | AD65: Y | AL65: V | AM65: V | AN65: V | AO65: V | AP65: V | AQ65: V | AR65: V | AS65: V | AW65: V | AX65: V | AY65: V | AZ65: V | BA65: 유재준 | BB65: jyoo8@kr.kpmg.com | BE65: 서은아 | BF65: eseo@kr.kpmg.com | BG65: 한상현 | BH65: sanghyunhan@kr.kpmg.com | BI65: 도정욱 | BJ65: jungwookdo@kr.kpmg.com | BK65: 박정수 | BL65: jungsoopark@kr.kpmg.com | BU65: 손진영 | BV65: jinyoungson@kr.kpmg.com | CG65: 최연주 | CH65: yeonjoochoi@kr.kpmg.com | CK65: 유홍재 | CL65: hongjaeyoo@kr.kpmg.com | CM65: 이선화 | CN65: slee370@kr.kpmg.com | CO65: 김창민 | CP65: changminkim@kr.kpmg.com | CZ65: 동원F&B_외부감사_FY25 | DA65: 5. 작업 완료 | DD65: =IF(AF65="제외요청", "V","") | DF65: V
C66: 1683260 | D66: 60 | E66: ICE1 | F66: 1000502523 | G66: 주식회사 우아한형제들 | H66: 1683260 | I66: 우아한형제들_외부감사 및 Group reporting_FY25 | J66: 일반 | L66: 응용 소프트웨어 개발 및 공급업 | AB66: KR_KPMG Dashboards - IFRS v3.1 - Media & Telecoms Industry | AC66: Information | AD66: N | AE66: 46058 | AF66: 제외요청 | AG66: 이미 감사 절차 수행완료 | BA66: 이영롱 | BB66: younglonglee@kr.kpmg.com | BE66: 이현강 | BF66: hyeonganglee@kr.kpmg.com | BG66: 현승임 | BH66: shyun@kr.kpmg.com | BI66: 설유진 | BJ66: yseol@kr.kpmg.com | BK66: 박홍민 | BL66: hongminpark@kr.kpmg.com | BU66: 김신영 | BV66: shinyoungkim@kr.kpmg.com | CG66: 권내형 | CH66: naehyeongkwon@kr.kpmg.com | CZ66: #N/A | DA66: #N/A | DC66: V | DD66: =IF(AF66="제외요청", "V","") -> V
A67: 박정빈 | B67: 완료 | C67: 1657550 | D67: 61 | E67: CM2 | F67: 1001005932 | G67: 한일시멘트(주) | H67: 1657550 | I67: 한일시멘트 FY25 외부감사 | J67: 유가증권 | L67: 시멘트 제조업 | M67: Industrial Products | N67: UNI-ERP | O67: 1349103 | P67: N/A | Q67: N/A | R67: N/A | S67: N/A | T67: 100.2.02 | U67: O | V67: N/A | W67: N/A | X67: N/A | Y67: N/A | Z67: N/A | AA67: N/A | AB67: KR_KPMG Dashboards - IFRS v3.1 - Base Industry: UpdateMay2025 | AC67: Manufacturing | AD67: N | AF67: 사용 | AL67: V | AW67: V | AX67: V | AY67: V | AZ67: V | BA67: 김수영 | BB67: skim40@kr.kpmg.com | BE67: 서은아 | BF67: eseo@kr.kpmg.com | BG67: 오헌창 | BH67: heonchangoh@kr.kpmg.com | BI67: 박관종 | BJ67: kwanjongpark@kr.kpmg.com | BK67: 조한얼 | BL67: hjo@kr.kpmg.com | BU67: 안창현 | BV67: changhyunan@kr.kpmg.com | CG67: 김정현 | CH67: jkim216@kr.kpmg.com | CK67: 김선호 | CL67: skim270@kr.kpmg.com | CZ67: 한일시멘트 FY25 외부감사 | DA67: 5. 작업 완료 | DC67: V | DD67: =IF(AF67="제외요청", "V","") | DF67: V
C68: 1681493 | D68: 62 | E68: CM1 | F68: 1000676068 | G68: 대한제당(주) | H68: 1681493 | I68: FY2025_대한제당_법정감사 | J68: 유가증권 | L68: 곡물 가공품, 전분 및 전분제품 제조업 | AD68: N | AE68: 45874 | AF68: 제외요청 | AG68: 매출 4개 stream 중 2개는 Significant, 2개는 base. Base항목들은 Sample 숫자 20개 미만. 비용도 샘플 10개 미만 | BA68: 김수영 | BB68: skim40@kr.kpmg.com | BG68: 김신 | BH68: skim137@kr.kpmg.com | BI68: 정창길 | BJ68: changgiljung@kr.kpmg.com | BK68: 박정수 | BL68: jungsoopark@kr.kpmg.com | BU68: 최성운 | BV68: sungwoonchoi@kr.kpmg.com | CG68: 정혜정 | CH68: hyejungjung@kr.kpmg.com | CZ68: #N/A | DA68: #N/A | DD68: =IF(AF68="제외요청", "V","") -> V
C69: 1683305 | D69: 63 | E69: CM2 | F69: 1000751734 | G69: 롯데물산주식회사 | H69: 1683305 | I69: 롯데물산_FY2025_외부감사 | J69: 일반 | L69: 부동산 임대 및 공급업 | AD69: N | AE69: 45861 | AF69: 제외요청 | AG69: 매출전표가 월합으로 기표되어 전체 매출전표 숫자 자체가 10건 미만. AITS 사용 시 효익이 없음 | BA69: 김미희 | BB69: mkim181@kr.kpmg.com | BI69: 이주형 | BJ69: juhyunglee@kr.kpmg.com | BK69: 한상일 | BL69: sangilhan@kr.kpmg.com | BU69: 박상화 | BV69: sanghwapark@kr.kpmg.com | CG69: 이광수 | CH69: kwangsulee@kr.kpmg.com | CZ69: #N/A | DA69: #N/A | DD69: =IF(AF69="제외요청", "V","") -> V
C70: 1658674 | D70: 64 | E70: CM1 | F70: 1000315256 | G70: (주)한섬 | H70: 1658674 | I70: 한섬_2025년 외부감사 | J70: 유가증권 | L70: 여자용 겉옷 제조업 | AD70: Y | AE70: 45881 | AF70: 제외요청 | AG70: FY24 AITS 사용결과 AITS 효익 미비 | BA70: 노민경 | BB70: minkyungro@kr.kpmg.com | BE70: 이현강 | BF70: hyeonganglee@kr.kpmg.com | BG70: 현승임 | BH70: shyun@kr.kpmg.com | BI70: 도정욱 | BJ70: jungwookdo@kr.kpmg.com | BK70: 조일상 | BL70: ijo@kr.kpmg.com | BU70: 김주형 | BV70: juhyungkim@kr.kpmg.com | CG70: 오서영 | CH70: soh10@kr.kpmg.com | CZ70: #N/A | DA70: #N/A | DD70: =IF(AF70="제외요청", "V","") -> V
A71: 박정빈 | B71: 완료 | C71: 1660912 | D71: 65 | E71: ICE3 | F71: 1001227695 | G71: (주)스튜디오 산타클로스 엔터테인먼트 | H71: 1660912 | I71: FY25_산타클로스ENT_지정감사 | J71: 코스닥 | L71: 창작 및 예술관련 서비스업 | M71: Services Media | N71: 더존 | O71: 34446 | P71: N/A | Q71: N/A | R71: 100.2.02 | S71: O | T71: N/A | U71: N/A | V71: N/A | W71: N/A | X71: N/A | Y71: N/A | Z71: N/A | AA71: N/A | AB71: KR_KPMG Dashboards - IFRS v3.1 - Media & Telecoms Industry | AC71: Arts, Entertainment, and Recreation | AD71: N | AI71: V | AL71: V | AM71: V | AN71: V | AO71: V | AP71: V | AQ71: V | AR71: V | AS71: V | AW71: V | AX71: V | AY71: V | AZ71: V | BA71: 이채영 | BB71: clee46@kr.kpmg.com | BE71: 서은아 | BF71: eseo@kr.kpmg.com | BG71: 이승훈 | BH71: seunghoonlee@kr.kpmg.com | BI71: 민성진 | BJ71: smin@kr.kpmg.com | BK71: 강승미 | BL71: seungmikang@kr.kpmg.com | BU71: 최유라 | BV71: yoorachoi@kr.kpmg.com | CG71: 정병열 | CH71: byungyuljung@kr.kpmg.com | CK71: 주혜빈 | CL71: hyebinjoo@kr.kpmg.com | CZ71: FY25_산타클로스ENT_지정감사 | DA71: 5. 작업 완료 | DD71: =IF(AF71="제외요청", "V","") | DF71: V
C72: 1683705 | D72: 66 | E72: ICE3 | F72: 1000670608 | G72: 에스케이쉴더스(주) | H72: 1683705 | I72: SK쉴더스_외부감사_FY2025 | J72: 일반 | L72: 시스템 소프트웨어 개발 및 공급업 | M72: Services | N72: SAP | O72: 77104869 | P72: N/A | Q72: N/A | R72: N/A | S72: N/A | T72: 100.2.02 | U72: O | V72: N/A | W72: N/A | X72: N/A | Y72: N/A | Z72: N/A | AA72: N/A | AB72: KR_KPMG Dashboards - IFRS v3.1 - Technology Industry | AC72: Professional, Scientific, and Technical Services | AD72: N | AI72: V | AL72: V | AM72: V | AN72: V | AO72: V | AP72: V | AQ72: V | AR72: V | BA72: 이현경 | BB72: hyunkyunglee@kr.kpmg.com | BG72: 현승임 | BH72: shyun@kr.kpmg.com | BI72: 이동윤 | BJ72: dongyoonlee@kr.kpmg.com | BK72: 강인혜 | BL72: ikang@kr.kpmg.com | BU72: 박소영 | BV72: soyoungpark@kr.kpmg.com | CG72: 조민곤 | CH72: mcho5@kr.kpmg.com | CK72: 한효민 | CL72: hyominhan@kr.kpmg.com | CM72: 이재경 | CN72: jlee565@kr.kpmg.com | CZ72: SK쉴더스_외부감사_FY2025 | DA72: 5. 작업 완료 | DD72: =IF(AF72="제외요청", "V","") | DF72: V
C73: 1682283 | D73: 67 | E73: CM2 | F73: 1000751735 | G73: 롯데글로벌로지스주식회사 | H73: 1682283 | I73: FY2025_롯데글로벌로지스 외부감사 | J73: 일반 | L73: 화물운송 중개, 대리 및 관련서비스업 | AD73: N | AE73: 46058 | AF73: 제외요청 | AG73: RMM이 Base에 해당하지 않아 적용 불가 | AL73: V | BA73: 이채영 | BB73: clee46@kr.kpmg.com | BE73: 이현강 | BF73: hyeonganglee@kr.kpmg.com | BG73: 현승임 | BH73: shyun@kr.kpmg.com | BI73: 박상옥 | BJ73: sangokpark@kr.kpmg.com | BK73: 김수광 | BL73: sukwangkim@kr.kpmg.com | BU73: 이광수 | BV73: kwangsulee@kr.kpmg.com | CG73: 이영민 | CH73: yeongminlee@kr.kpmg.com | CZ73: FY2025_롯데글로벌로지스 외부감사 | DA73: 1. 서비스 요청 | DC73: V | DD73: =IF(AF73="제외요청", "V","") -> V
A74: 박정빈 | B74: 완료 | C74: 1669402 | D74: 68 | E74: IM2 | F74: 1000855664 | G74: 에스케이케미칼 | H74: 1669402 | I74: SK케미칼 2025년 지정감사 | J74: 유가증권 | L74: 합성수지 및 기타 플라스틱 물질 제조업 | O74: 8649748 | P74: 115.2.02 | Q74: O | R74: N/A | S74: N/A | T74: N/A | U74: N/A | V74: N/A | W74: N/A | X74: N/A | Y74: N/A | Z74: N/A | AA74: N/A | AB74: KR_KPMG Dashboards - IFRS v3.1 - Base Industry: UpdateMay2025 | AC74: Manufacturing | AD74: N | AI74: V | AL74: V | AM74: V | AN74: V | AO74: V | AP74: V | AQ74: V | AR74: V | AS74: V | AW74: V | AX74: V | AY74: V | AZ74: V | BA74: 전혜지 | BB74: hjeon6@kr.kpmg.com | BE74: 서은아 | BF74: eseo@kr.kpmg.com | BG74: 지가현 | BH74: gahyunji@kr.kpmg.com | BI74: 전원표 | BJ74: wjeon@kr.kpmg.com | BK74: 정양기 | BL74: yangkijung@kr.kpmg.com | BU74: 이종록 | BV74: jongroklee@kr.kpmg.com | CG74: 정승헌 | CH74: seungheonjeong@kr.kpmg.com | CK74: 양인규 | CL74: ingyuyang@kr.kpmg.com | CM74: 노은서 | CN74: eunseoroh@kr.kpmg.com | CZ74: SK케미칼 2025년 지정감사 | DA74: 5. 작업 완료 | DD74: =IF(AF74="제외요청", "V","") | DF74: V
C75: 1668837 | D75: 69 | E75: IM3 | F75: 1000575020 | G75: 에어부산㈜ | H75: 1668837 | I75: [에어부산] 2025년 지정 감사 | J75: 유가증권 | L75: 항공 여객 운송업 | M75: Aviation | N75: SAP S/4 HANA | O75: 2132339 | P75: 115.2.02 | Q75: O | R75: N/A | S75: N/A | T75: N/A | U75: N/A | V75: N/A | W75: N/A | X75: N/A | Y75: N/A | Z75: N/A | AA75: N/A | AB75: KR_KPMG Dashboards - IFRS v3.1 - Base Industry: UpdateMay2025 | AC75: Manufacturing | AD75: N | AE75: 46043 | AF75: 제외요청 | AG75: AITS interim 완료하였으나 배치전표로 분석결과가 좋지 못하여 사용불가 | AI75: V | AL75: V | AM75: V | AN75: V | AO75: V | AP75: V | AQ75: V | AR75: V | BA75: 황인영 | BB75: ihwang7@kr.kpmg.com | BC75: 홍민정 | BD75: minjunghong@kr.kpmg.com | BE75: 서은아 | BF75: eseo@kr.kpmg.com | BG75: 김신 | BH75: skim137@kr.kpmg.com | BI75: 이채능 | BJ75: chaeneunglee@kr.kpmg.com | BK75: 신동준 | BL75: dongjunshin@kr.kpmg.com | BU75: 김상우 | BV75: skim56@kr.kpmg.com | CG75: 나수정 | CH75: sujungna@kr.kpmg.com | CK75: 조하은 | CL75: hcho14@kr.kpmg.com | CZ75: [에어부산] 2025년 지정 감사 | DA75: 5. 작업 완료 | DD75: =IF(AF75="제외요청", "V","") -> V
C76: 1659927 | D76: 70 | E76: CM2 | F76: 1000326244 | G76: 남해화학㈜ | H76: 1659927 | I76: 남해화학 FY2025 외부감사 | J76: 유가증권 | L76: 복합비료 및 기타 화학비료 제조업 | O76: 8090609 | P76: 115.2.02 115.2.13 | Q76: O | R76: N/A | S76: N/A | T76: 100.2.02 | U76: O | V76: N/A | W76: N/A | X76: N/A | Y76: N/A | Z76: N/A | AA76: N/A | AB76: KR_KPMG Dashboards - IFRS v3.1 - Base Industry: UpdateMay2025 | AC76: Manufacturing | AD76: Y | AI76: V | AL76: V | AM76: V | AN76: V | AO76: V | AP76: V | AQ76: V | AR76: V | AS76: V | BA76: 이동영 | BB76: dongyounglee@kr.kpmg.com | BE76: 서은아 | BF76: eseo@kr.kpmg.com | BG76: 신동명 | BH76: dongmyungshin@kr.kpmg.com | BI76: 황구철 | BJ76: khwang@kr.kpmg.com | BK76: 이종우 | BL76: jongwoolee@kr.kpmg.com | BU76: 송규원 | BV76: kyuwonsong@kr.kpmg.com | CG76: 박재범 | CH76: jpark75@kr.kpmg.com | CK76: 곽혜진 | CL76: hyejinkwak@kr.kpmg.com | CM76: 송지환 | CN76: jsong26@kr.kpmg.com | CZ76: 남해화학 FY2025 외부감사 | DA76: 5. 작업 완료 | DD76: =IF(AF76="제외요청", "V","") | DF76: V
A77: 박정빈 | B77: 완료 | C77: 1661433 | D77: 71 | E77: IM4 | F77: 1001148872 | G77: (주)알파칩스 | H77: 1661433 | I77: [알파홀딩스] 2025년 지정감사 | J77: 코스닥 | L77: 전자집적회로 제조업 | M77: Industrial Products | N77: 더존iCube (Amaranth10) | O77: 31574 | P77: N/A | Q77: N/A | R77: N/A | S77: N/A | T77: 100.2.02 | U77: X | V77: N/A | W77: N/A | X77: N/A | Y77: N/A | Z77: N/A | AA77: N/A | AB77: KR_KPMG Dashboards - IFRS v3.1 - Base Industry: UpdateMay2025 | AC77: Manufacturing | AD77: N | AI77: V | AL77: V | AM77: V | AN77: V | AO77: V | AP77: V | AQ77: V | AR77: V | AS77: V | AW77: V | AX77: V | AY77: V | AZ77: V | BA77: 이채영 | BB77: clee46@kr.kpmg.com | BE77: 이현강 | BF77: hyeonganglee@kr.kpmg.com | BG77: 신재혁 | BH77: chaehyokshin@kr.kpmg.com | BI77: 강성채 | BJ77: sungchaekang@kr.kpmg.com | BK77: 이경석 | BL77: kyungsuklee@kr.kpmg.com | BU77: 송민규 | BV77: mingyusong@kr.kpmg.com | CG77: 강태훈 | CH77: taehoonkang@kr.kpmg.com | CK77: 김성훈 | CL77: skim197@kr.kpmg.com | CM77: 박정현 | CN77: jpark211@kr.kpmg.com | CZ77: [알파홀딩스] 2025년 지정감사 | DA77: 5. 작업 완료 | DD77: =IF(AF77="제외요청", "V","") | DF77: V
C78: 1664808 | D78: 72 | E78: IGH | F78: 1001078687 | G78: 주식회사 국보 | H78: 1664808 | I78: [국보] FY2025 지정감사 | J78: 유가증권 | L78: 일반 화물자동차 운송업 | AD78: N | AE78: 45957 | AF78: 제외요청 | AG78: 총계정원장 시산표 등 자료 수령불가 : 반기에도 DSD 외의 자료는 회사에서 제공하지 않아 입수가 어려운 상황입니다. 2024년부터 동일한 상황이 지속되고 있으며, 기말에도 DSD만 제공될 것으로 예상됩니다. 감사의견 거절 지속 : 2023년부터 감사의견 거절이 표명되었으며, 2025년 반기에도 검토의견 거절이 발생하였습니다. 현재 상황으로 볼 때, 기말에도 감사의견 거절이 예상됩니다. 감사의견 거절에 따른 RMM 영향: 감사의견 거절로 인해 RMM에 대한 CAR가 BASE를 초과하는 상황입니다. | AI78: V | BA78: 김수연 | BB78: sooyeonkim@kr.kpmg.com | BG78: 신재혁 | BH78: chaehyokshin@kr.kpmg.com | BI78: 전현호 | BJ78: hyunhojeon@kr.kpmg.com | BK78: 범승형 | BL78: sbeom@kr.kpmg.com | BU78: 허건웅 | BV78: khur@kr.kpmg.com | CZ78: #N/A | DA78: #N/A | DD78: =IF(AF78="제외요청", "V","") -> V
C79: 1661198 | D79: 73 | E79: ICE1 | F79: 1000316497 | G79: 웹젠 | H79: 1661198 | I79: 웹젠 FY2025 외부감사 | J79: 코스닥 | L79: 게임 소프트웨어 개발 및 공급업 | M79: Services | N79: 더존ERP | O79: 100142 | P79: N/A | Q79: N/A | R79: N/A | S79: N/A | T79: 100.2.02 | U79: O | V79: N/A | W79: N/A | X79: N/A | Y79: N/A | Z79: N/A | AA79: N/A | AB79: KR_KPMG Dashboards - IFRS v3.1 - Technology Industry | AC79: Information | AD79: N | AI79: V | AL79: V | AM79: V | AN79: V | AO79: V | AP79: V | AQ79: V | AR79: V | AW79: V | AX79: V | AY79: V | AZ79: V | BA79: 노민경 | BB79: minkyungro@kr.kpmg.com | BE79: 서은아 | BF79: eseo@kr.kpmg.com | BG79: 신동명 | BH79: dongmyungshin@kr.kpmg.com | BI79: 허재훈 | BJ79: jaehoonheo@kr.kpmg.com | BK79: 설원 | BL79: wonseol@kr.kpmg.com | BU79: 김의진 | BV79: euijinkim@kr.kpmg.com | CG79: 정병열 | CH79: byungyuljung@kr.kpmg.com | CK79: 김지혜 | CL79: jkim520@kr.kpmg.com | CZ79: 웹젠 FY2025 외부감사 | DA79: 5. 작업 완료 | DD79: =IF(AF79="제외요청", "V","") | DF79: V
C80: 1686129 | D80: 74 | E80: IM2 | F80: 1000741492 | G80: (주)LS네트웍스 | H80: 1686129 | I80: LS네트웍스 FY25 회계감사 | J80: 유가증권 | L80: 상품 종합 도매업 | AD80: N | AE80: 45910 | AF80: 제외요청 | AG80: 수익관련 RMM CAR 평가결과 BASE가 아닌 그 이상의 리스크로 평가. 비용은 샘플이 10개로 실익 없음 | AL80: V | AM80: V | AN80: V | AO80: V | AP80: V | BA80: 전혜지 | BB80: hjeon6@kr.kpmg.com | BE80: 이현강 | BF80: hyeonganglee@kr.kpmg.com | BG80: 현승임 | BH80: shyun@kr.kpmg.com | BI80: 지동현 | BJ80: dchi@kr.kpmg.com | BK80: 조화수 | BL80: hwasoocho@kr.kpmg.com | BU80: 양진석 | BV80: jinseokyang@kr.kpmg.com | CG80: 신정은 | CH80: jeongeunshin@kr.kpmg.com | CZ80: #N/A | DA80: #N/A | DD80: =IF(AF80="제외요청", "V","") -> V
C81: 1687118 | D81: 75 | E81: IM2 | F81: 1000325995 | G81: (주)이수화학 | H81: 1687118 | I81: 이수화학_2025년 회계감사 | J81: 유가증권 | L81: 석유화학계 기초 화학물질 제조업 | M81: Consumer Products Industrial Products Construction Government | N81: SAP S/4 HANA | O81: 602196 | P81: N/A | Q81: N/A | R81: 100.2.02 | S81: O | T81: 100.2.02 | U81: O | V81: N/A | W81: N/A | X81: N/A | Y81: N/A | Z81: N/A | AA81: N/A | AB81: KR_KPMG Dashboards - IFRS v3.1 - Base Industry: UpdateMay2025 | AC81: Manufacturing | AD81: N | AK81: V | AL81: V | AM81: V | AN81: V | AO81: V | AP81: V | AQ81: V | AR81: V | AS81: V | AW81: V | AX81: V | AY81: V | AZ81: V | BA81: 노민경 | BB81: minkyungro@kr.kpmg.com | BE81: 이현강 | BF81: hyeonganglee@kr.kpmg.com | BG81: 현승임 | BH81: shyun@kr.kpmg.com | BI81: 전원표 | BJ81: wjeon@kr.kpmg.com | BK81: 최연석 | BL81: ychoi@kr.kpmg.com | BU81: 이충기 | BV81: choongkilee@kr.kpmg.com | CG81: 김재현 | CH81: jkim508@kr.kpmg.com | CK81: 김윤석 | CL81: yunseokkim@kr.kpmg.com | CM81: 한승우 | CN81: seungwoohan@kr.kpmg.com | CZ81: 이수화학_2025년 회계감사 | DA81: 5. 작업 완료 | DD81: =IF(AF81="제외요청", "V","") | DF81: V
C82: 1682814 | D82: 76 | E82: CM2 | F82: 1000734708 | G82: 더블유씨피 주식회사 | H82: 1682814 | I82: 더블유씨피_외부감사_FY25 | J82: 코스닥 | L82: 축전지 제조업 | AD82: Y | AE82: 46058 | AF82: 제외요청 | AG82: RMM이 Base에 해당하지 않아 적용 불가 | AL82: V | BA82: 김수영 | BB82: skim40@kr.kpmg.com | BI82: 현윤호 | BJ82: yhyun@kr.kpmg.com | BK82: 정창길 | BL82: changgiljung@kr.kpmg.com | BU82: 김성욱 | BV82: sungwookkim@kr.kpmg.com | CG82: 황준석 | CH82: junseokhwang@kr.kpmg.com | CZ82: 더블유씨피_외부감사_FY25 | DA82: 1. 서비스 요청 | DC82: V | DD82: =IF(AF82="제외요청", "V","") -> V
A83: 박정빈 | B83: 완료 | C83: 1671288 | D83: 77 | E83: IM1 | F83: 1000326239 | G83: 무림페이퍼(주) | H83: 1671288 | I83: 2025년 무림페이퍼 법정감사 | J83: 유가증권 | L83: 펄프, 종이 및 판지 제조업 | M83: Industrial Products | N83: SAP | O83: 5829700 | P83: 115.2.02 | Q83: O | R83: N/A | S83: N/A | T83: N/A | U83: N/A | V83: N/A | W83: N/A | X83: N/A | Y83: N/A | Z83: N/A | AA83: N/A | AB83: KR_KPMG Dashboards - IFRS v3.1 - Base Industry: UpdateMay2025 | AC83: Manufacturing | AD83: N | AI83: V | AL83: V | AM83: V | AN83: V | AO83: V | AP83: V | AQ83: V | AR83: V | AS83: V | AW83: V | AX83: V | AY83: V | AZ83: V | BA83: 김수연 | BB83: sooyeonkim@kr.kpmg.com | BE83: 서은아 | BF83: eseo@kr.kpmg.com | BG83: 지가현 | BH83: gahyunji@kr.kpmg.com | BI83: 이종상 | BJ83: jongsanglee@kr.kpmg.com | BK83: 황재남 | BL83: jaenamhwang@kr.kpmg.com | BU83: 원영인 | BV83: younginwon@kr.kpmg.com | BW83: 이주화 | BX83: jlee92@kr.kpmg.com | CG83: 윤보현 | CH83: bohyunyoon@kr.kpmg.com | CK83: 신재성 | CL83: jaeseongshin@kr.kpmg.com | CM83: 장현옥 | CN83: hyeonokjang@kr.kpmg.com | CZ83: 2025년 무림페이퍼 법정감사 | DA83: 5. 작업 완료 | DD83: =IF(AF83="제외요청", "V","") | DF83: V
C84: 1707140 | D84: 78 | E84: CM1 | F84: 1000953430 | G84: 주식회사 컬리 | H84: 1707140 | I84: 컬리 FY2025.12 IPO지정감사 | J84: 일반 | L84: 통신 판매업 | AD84: N | AE84: 46058 | AF84: 제외요청 | AG84: 매출은 비경상적이며 비용은 AITS미적용(감가상각비, 인건비)가 대다수 | AI84: V | AL84: V | BA84: 이채영 | BB84: clee46@kr.kpmg.com | BG84: 오헌창 | BH84: heonchangoh@kr.kpmg.com | BI84: 김태준 | BJ84: tkim@kr.kpmg.com | BK84: 황구철 | BL84: khwang@kr.kpmg.com | BU84: 강지헌 | BV84: jiheonkang@kr.kpmg.com | CG84: 이상은 | CH84: sangunlee@kr.kpmg.com | CZ84: 컬리 FY2025.12 IPO지정감사 | DA84: 1. 서비스 요청 | DC84: V | DD84: =IF(AF84="제외요청", "V","") -> V
C85: 1658486 | D85: 79 | E85: CM1 | F85: 1000326117 | G85: 율촌화학 | H85: 1658486 | I85: 율촌화학_지정감사_FY25 | J85: 유가증권 | L85: 제조업 | AD85: N | AE85: 45995 | AF85: 제외요청 | AG85: 이미 절차를 다 수행해놓음. 초도감사 | AL85: V | BA85: 김문영 | BB85: moonyoungkim@kr.kpmg.com | BE85: 서은아 | BF85: eseo@kr.kpmg.com | BG85: 신동명 | BH85: dongmyungshin@kr.kpmg.com | BI85: 박상훈 | BJ85: sanghoonpark@kr.kpmg.com | BK85: 황구철 | BL85: khwang@kr.kpmg.com | BU85: 김수연 | BV85: skim125@kr.kpmg.com | CG85: 박광량 | CH85: gbak@kr.kpmg.com | CZ85: 율촌화학_지정감사_FY25 | DA85: 9. 서비스 취소 | DD85: =IF(AF85="제외요청", "V","") -> V
A86: 박정빈 | B86: 완료 | C86: 1670502 | D86: 80 | E86: IM1 | F86: 1001438239 | G86: 무림피앤피㈜ | H86: 1670502 | I86: 2025년 무림피앤피 법정감사 | J86: 유가증권 | L86: 펄프, 종이 및 판지 제조업 | M86: Industrial Products | N86: SAP | O86: 8973476 | P86: 115.2.02 | Q86: O | R86: N/A | S86: N/A | T86: N/A | U86: N/A | V86: N/A | W86: N/A | X86: N/A | Y86: N/A | Z86: N/A | AA86: N/A | AB86: KR_KPMG Dashboards - IFRS v3.1 - Base Industry: UpdateMay2025 | AC86: Manufacturing | AD86: N | AL86: V | AM86: V | AN86: V | AO86: V | AP86: V | AQ86: V | AR86: V | AW86: V | AX86: V | AY86: V | AZ86: V | BA86: 송은혜 | BB86: esong7@kr.kpmg.com | BE86: 이현강 | BF86: hyeonganglee@kr.kpmg.com | BG86: 신동명 | BH86: dongmyungshin@kr.kpmg.com | BI86: 이종상 | BJ86: jongsanglee@kr.kpmg.com | BK86: 변상현 | BL86: sanghyunbyun@kr.kpmg.com | BU86: 원영인 | BV86: younginwon@kr.kpmg.com | CG86: 이용범 | CH86: yongbeomlee@kr.kpmg.com | CK86: 김영빈 | CL86: ykim184@kr.kpmg.com | CM86: 유준수 | CN86: junsuyoo@kr.kpmg.com | CZ86: 2025년 무림피앤피 법정감사 | DA86: 5. 작업 완료 | DD86: =IF(AF86="제외요청", "V","") | DF86: V
C87: 1683651 | D87: 81 | E87: IM1 | F87: 1000704681 | G87: 에스케이렌터카(주) | H87: 1683651 | I87: FY2025_SK렌터카_법정감사 | J87: 일반 | L87: 자동차 임대업 | AD87: N | AE87: 45873 | AF87: 제외요청 | AG87: 보조부 원장과 총계정원장이 매핑되어 있지 않아 추가 작업 필요 | BA87: 김수영 | BB87: skim40@kr.kpmg.com | BG87: 오헌창 | BH87: heonchangoh@kr.kpmg.com | BI87: 강정구 | BJ87: jeonggukang@kr.kpmg.com | BK87: 이주영 | BL87: jooyounglee@kr.kpmg.com | BU87: 유성희 | BV87: sungheeyoo@kr.kpmg.com | CG87: 신민경 | CH87: minkyungshin@kr.kpmg.com | CZ87: #N/A | DA87: #N/A | DD87: =IF(AF87="제외요청", "V","") -> V
C88: 1679121 | D88: 82 | E88: CM2 | F88: 1000317012 | G88: (주)우리홈쇼핑 | H88: 1679121 | I88: 우리홈쇼핑_FY2025_법정감사 | J88: 일반 | L88: 기타통신판매업 | M88: Retail, Consumer Products | O88: 8090609 | P88: 115.2.02 115.2.13 115.3.01 | Q88: O | R88: N/A | S88: N/A | T88: 100.2.02 | U88: O | V88: N/A | W88: N/A | X88: N/A | Y88: N/A | Z88: N/A | AA88: N/A | AB88: KR_KPMG Dashboards - IFRS v3.1 - Retail Industry | AC88: Retail Trade | AD88: N | AI88: V | AL88: V | AM88: V | AN88: V | AO88: V | AP88: V | AQ88: V | AR88: V | AS88: V | AW88: V | AX88: V | AY88: V | AZ88: V | BI88: 이용호 | BJ88: yongholee@kr.kpmg.com | BK88: 김재민 | BL88: jaeminkim@kr.kpmg.com | BU88: 정민주 | BV88: minjujeong@kr.kpmg.com | CG88: 강남현 | CH88: namhyunkang@kr.kpmg.com | CK88: 고세훈 | CL88: saehoonkoh@kr.kpmg.com | CZ88: 우리홈쇼핑_FY2025_법정감사 | DA88: 5. 작업 완료 | DD88: =IF(AF88="제외요청", "V","") | DF88: V
C89: 1688777 | D89: 83 | E89: IGH | F89: 1001330099 | G89: 한화갤러리아 (주) | H89: 1688777 | I89: [한화갤러리아] FY2025 외부감사 | J89: 유가증권 | L89: 백화점 | M89: Retail | N89: SAP | O89: 3320172 | P89: 115.2.02 115.2.12b | Q89: O | R89: N/A | S89: N/A | T89: N/A | U89: N/A | V89: N/A | W89: N/A | X89: N/A | Y89: N/A | Z89: N/A | AA89: N/A | AB89: KR_KPMG Dashboards - IFRS v3.1 - Retail Industry | AC89: Retail Trade | AD89: Y | AL89: V | AM89: V | AN89: V | AO89: V | AP89: V | AQ89: V | AR89: V | BA89: 송은혜 | BB89: esong7@kr.kpmg.com | BE89: 이현강 | BF89: hyeonganglee@kr.kpmg.com | BG89: 한상현 | BH89: sanghyunhan@kr.kpmg.com | BI89: 조일상 | BJ89: ijo@kr.kpmg.com | BK89: 엄준식 | BL89: junsikuhm@kr.kpmg.com | BU89: 노영일 | BV89: yno@kr.kpmg.com | CG89: 김민경 | CH89: mkim64@kr.kpmg.com | CK89: 추상민 | CL89: sangminchoo@kr.kpmg.com | CZ89: [한화갤러리아] FY2025 외부감사 | DA89: 5. 작업 완료 | DD89: =IF(AF89="제외요청", "V","") | DF89: V
C90: 1685837 | D90: 84 | E90: ICE3 | F90: 1001261445 | G90: 주식회사 놀유니버스 | H90: 1685837 | I90: FY25 놀유니버스(구.인터파크트리플) 외부감사 | J90: 일반 | L90: 상품 종합 도매업 | AD90: N | AE90: 46058 | AF90: 제외요청 | AG90: PCAOB이며, ERP에서 자료가 나오지 않음 | AL90: V | BI90: 강인혜 | BJ90: ikang@kr.kpmg.com | BK90: 최진석 | BL90: jinseokchoi@kr.kpmg.com | BU90: 이준혁 | BV90: junhyeoklee@kr.kpmg.com | CG90: 정대륙 | CH90: daeryukjeong@kr.kpmg.com | CZ90: FY25 놀유니버스(구.인터파크트리플) 외부감사 | DA90: 1. 서비스 요청 | DC90: V | DD90: =IF(AF90="제외요청", "V","") -> V
C91: 1687853 | D91: 85 | E91: IGH | F91: 1000682279 | G91: 주식회사 지누스 | H91: 1687853 | I91: [지누스] FY2025 외부감사 | J91: 유가증권 | L91: 상품 종합 도매업 | AD91: Y | AE91: 45992 | AF91: 제외요청 | AG91: 보조부 원장과 총계정원장이 매핑되어 있지 않아 추가 작업 필요 | AL91: V | BA91: 이동영 | BB91: dongyounglee@kr.kpmg.com | BE91: 이현강 | BF91: hyeonganglee@kr.kpmg.com | BG91: 한상현 | BH91: sanghyunhan@kr.kpmg.com | BI91: 김태준 | BJ91: tkim@kr.kpmg.com | BK91: 박상옥 | BL91: sangokpark@kr.kpmg.com | BU91: 서상석 | BV91: sangseokseo@kr.kpmg.com | CG91: 신호영 | CH91: hoyoungshin@kr.kpmg.com | CZ91: [지누스] FY2025 외부감사 | DA91: 9. 서비스 취소 | DD91: =IF(AF91="제외요청", "V","") -> V
C92: 1668814 | D92: 86 | E92: CM2 | F92: 1001098619 | G92: (주)티와이홀딩스 | H92: 1668814 | I92: TY홀딩스 지정감사 FY2025 | J92: 유가증권 | L92: 지주회사 | AD92: N | AE92: 45866 | AF92: 제외요청 | AG92: 지주회사 임에 따라 적용범위 RMM이 해당되는 Journal entry가 별도재무제표 상 거의 없어, 적용이 어려움 | BA92: 노민경 | BB92: minkyungro@kr.kpmg.com | BE92: 이현강 | BF92: hyeonganglee@kr.kpmg.com | BG92: 신재혁 | BH92: chaehyokshin@kr.kpmg.com | BI92: 박상훈 | BJ92: sanghoonpark@kr.kpmg.com | BK92: 도정욱 | BL92: jungwookdo@kr.kpmg.com | BU92: 김혜진 | BV92: hkim23@kr.kpmg.com | CG92: 최지함 | CH92: jihamchoi@kr.kpmg.com | CZ92: #N/A | DA92: #N/A | DD92: =IF(AF92="제외요청", "V","") -> V
C93: 1658417 | D93: 87 | E93: IM4 | F93: 1000326224 | G93: 주식회사 아이센스 | H93: 1658417 | I93: FY25 아이센스 지정감사 | J93: 코스닥 | L93: 전기식 진단 및 요법 기기 제조업 | AD93: N | AE93: 46062 | AF93: 제외요청 | AG93: RMM이 Base에 해당하지 않아 적용 불가 | AI93: V | AL93: V | BA93: 정주희 | BB93: jchung3@kr.kpmg.com | BG93: 이승훈 | BH93: seunghoonlee@kr.kpmg.com | BI93: 이종상 | BJ93: jongsanglee@kr.kpmg.com | BK93: 강정구 | BL93: jeonggukang@kr.kpmg.com | BU93: 윤광현 | BV93: kwanghyunyun@kr.kpmg.com | CG93: 서제국 | CH93: jegukseo@kr.kpmg.com | CZ93: FY25 아이센스 지정감사 | DA93: 1. 서비스 요청 | DC93: V | DD93: =IF(AF93="제외요청", "V","") -> V
C94: 1683936 | D94: 88 | E94: IM4 | F94: 1000636221 | G94: 비에이치아이 주식회사 | H94: 1683936 | I94: 비에이치아이_Audit_FY2025 | J94: 코스닥 | L94: 증류기, 열 교환기 및 가스 발생기 제조업 | AD94: N | AE94: 45861 | AF94: 제외요청 | AG94: 수익이 모두 진행기준이고 SR | BA94: 김미희 | BB94: mkim181@kr.kpmg.com | BG94: 현승임 | BH94: shyun@kr.kpmg.com | BI94: 강성채 | BJ94: sungchaekang@kr.kpmg.com | BK94: 이정수 | BL94: jungsoolee@kr.kpmg.com | BU94: 김성욱 | BV94: sunguckkim@kr.kpmg.com | CG94: 부성호 | CH94: sunghobu@kr.kpmg.com | CZ94: #N/A | DA94: #N/A | DD94: =IF(AF94="제외요청", "V","") -> V
C95: 1667966 | D95: 89 | E95: IM3 | F95: 1000317119 | G95: 오텍 | H95: 1667966 | I95: 오텍 2025년 외부감사 | J95: 코스닥 | L95: 자동차 재제조 부품 제조업 | AD95: N | AE95: 45867 | AF95: 제외요청 | AG95: 모집단 크기가 100개 미만으로 AITS를 적용하는데 비효율 | BA95: 이영롱 | BB95: younglonglee@kr.kpmg.com | BE95: 이현강 | BF95: hyeonganglee@kr.kpmg.com | BG95: 지가현 | BH95: gahyunji@kr.kpmg.com | BI95: 최세홍 | BJ95: sehongchoi@kr.kpmg.com | BK95: 백명종 | BL95: mbaek@kr.kpmg.com | BU95: 박상진 | BV95: spark20@kr.kpmg.com | CG95: 박상언 | CH95: sangeonpark@kr.kpmg.com | CZ95: #N/A | DA95: #N/A | DD95: =IF(AF95="제외요청", "V","") -> V
C96: 1671940 | D96: 90 | E96: IGH | F96: 1000326253 | G96: 에이치디씨현대이피 주식회사 | H96: 1671940 | I96: [HDC현대EP] FY2025 지정감사 | J96: 유가증권 | L96: 기타 화학제품 제조업 | M96: Industrial Products | N96: UniERP | O96: 626329 | P96: N/A | Q96: N/A | R96: 100.2.02 | S96: O | T96: 100.2.02 | U96: O | V96: N/A | W96: N/A | X96: N/A | Y96: N/A | Z96: N/A | AA96: N/A | AB96: KR_KPMG Dashboards - IFRS v3.1 - Base Industry: UpdateMay2025 | AC96: Manufacturing | AD96: N | AL96: V | AM96: V | AN96: V | AO96: V | AP96: V | AQ96: V | AR96: V | AW96: V | AX96: V | AY96: V | AZ96: V | BA96: 노민경 | BB96: minkyungro@kr.kpmg.com | BE96: 이현강 | BF96: hyeonganglee@kr.kpmg.com | BG96: 한상현 | BH96: sanghyunhan@kr.kpmg.com | BI96: 노상호 | BJ96: sanghoroh@kr.kpmg.com | BK96: 이덕영 | BL96: deokyeonglee@kr.kpmg.com | BU96: 박정훈 | BV96: jeonghoonpark@kr.kpmg.com | CG96: 정형석 | CH96: hyeongseokjeong@kr.kpmg.com | CK96: 김찬우 | CL96: ckim21@kr.kpmg.com | CM96: 허영환 | CN96: younghwanheo@kr.kpmg.com | CZ96: [HDC현대EP] FY2025 지정감사 | DA96: 5. 작업 완료 | DD96: =IF(AF96="제외요청", "V","") | DF96: V
C97: 1689086 | D97: 91 | E97: IM4 | F97: 1000314686 | G97: STX | H97: 1689086 | I97: FY25 STX외부회계감사 | J97: 유가증권 | L97: 상품종합도매 | AD97: Y | AE97: 46058 | AF97: 제외요청 | AG97: 법정감사로 AITS 적용 부담 | BA97: 김수영 | BB97: skim40@kr.kpmg.com | BE97: 서은아 | BF97: eseo@kr.kpmg.com | BG97: 한상현 | BH97: sanghyunhan@kr.kpmg.com | BI97: 조승희 | BJ97: seungheecho@kr.kpmg.com | BK97: 이경석 | BL97: kyungsuklee@kr.kpmg.com | BU97: 이상민 | BV97: slee14@kr.kpmg.com | CG97: 박주원 | CH97: juwonpark@kr.kpmg.com | CZ97: #N/A | DA97: #N/A | DC97: V | DD97: =IF(AF97="제외요청", "V","") -> V
C98: 1681503 | D98: 92 | E98: CM1 | F98: 1000316828 | G98: 주식회사 지마켓 | H98: 1681503 | I98: 지마켓 FY25 외부감사 | J98: 일반 | L98: 통신 판매업 | AD98: N | AE98: 46058 | AF98: 제외요청 | AG98: 이미 감사 절차 수행완료 | AL98: V | BI98: 정현진 | BJ98: hchung@kr.kpmg.com | BK98: 이용호 | BL98: yongholee@kr.kpmg.com | BU98: 김보람 | BV98: bkim13@kr.kpmg.com | CG98: 김용욱 | CH98: yongwookkim@kr.kpmg.com | CZ98: 지마켓 FY25 외부감사 | DA98: 1. 서비스 요청 | DC98: V | DD98: =IF(AF98="제외요청", "V","") -> V
A99: 박정빈 | B99: 완료 | C99: 1657536 | D99: 93 | E99: CM2 | F99: 1000584416 | G99: 한일홀딩스(주) | H99: 1657536 | I99: 한일홀딩스 2025년 지정감사(주기적) | J99: 유가증권 | L99: 시멘트 제조업 (지주회사) | M99: Industrial Products | N99: 이카운트ERP | O99: 17917 | P99: N/A | Q99: N/A | R99: N/A | S99: N/A | T99: 100.2.02 | U99: X | V99: N/A | W99: N/A | X99: N/A | Y99: N/A | Z99: N/A | AA99: N/A | AB99: KR_KPMG Dashboards - IFRS v3.1 - Base Industry: UpdateMay2025 | AC99: Manufacturing | AD99: N | AF99: 사용 | AL99: V | AW99: V | AX99: V | AY99: V | AZ99: V | BA99: 김미희 | BB99: mkim181@kr.kpmg.com | BE99: 서은아 | BF99: eseo@kr.kpmg.com | BG99: 오헌창 | BH99: heonchangoh@kr.kpmg.com | BI99: 박관종 | BJ99: kwanjongpark@kr.kpmg.com | BK99: 조한얼 | BL99: hjo@kr.kpmg.com | BU99: 안창현 | BV99: changhyunan@kr.kpmg.com | CG99: 박재현 | CH99: jpark106@kr.kpmg.com | CK99: 김영준 | CL99: ykim186@kr.kpmg.com | CZ99: 한일홀딩스 2025년 지정감사(주기적) | DA99: 5. 작업 완료 | DC99: V | DD99: =IF(AF99="제외요청", "V","") | DF99: V
C100: 1689472 | D100: 94 | E100: IM1 | F100: 1000314936 | G100: 삼성바이오에피스 주식회사 | H100: 1689472 | I100: 삼성바이오에피스 25년 외부감사 | J100: 일반 | L100: 바이오 의약품 개발 및 상업화 | M100: Life Science | N100: SAP S/4 HANA | O100: 257934 | P100: 115.2.02 | Q100: O | R100: N/A | S100: N/A | T100: N/A | U100: N/A | V100: N/A | W100: N/A | X100: N/A | Y100: N/A | Z100: N/A | AA100: N/A | AB100: KR_KPMG Dashboards - IFRS v3.1 - Base Industry: UpdateMay2025 | AC100: Manufacturing | AD100: N | AL100: V | AM100: V | AN100: V | AO100: V | AP100: V | AQ100: V | AR100: V | BI100: 이덕영 | BJ100: deokyeonglee@kr.kpmg.com | BK100: 지동현 | BL100: dchi@kr.kpmg.com | BU100: 천의성 | BV100: euiseongcheon@kr.kpmg.com | CG100: 김현우 | CH100: hkim154@kr.kpmg.com | CK100: 이준엽 | CL100: junyeoblee@kr.kpmg.com | CM100: 이지은 | CN100: jlee532@kr.kpmg.com | CZ100: 삼성바이오에피스 25년 외부감사 | DA100: 5. 작업 완료 | DD100: =IF(AF100="제외요청", "V","") | DF100: V
C101: 1684212 | D101: 95 | E101: CM1 | F101: 1000563922 | G101: 풀무원식품 (주) | H101: 1684212 | I101: 풀무원식품_FY2025_외부감사 | J101: 일반 | L101: 도매 및 상품 중개업 | AD101: N | AE101: 46063 | AF101: 제외요청 | AG101: 이미 감사 절차 수행완료 | BA101: 김미희 | BB101: mkim181@kr.kpmg.com | BC101: 홍민정 | BD101: minjunghong@kr.kpmg.com | BE101: 이현강 | BF101: hyeonganglee@kr.kpmg.com | BG101: 지가현 | BH101: gahyunji@kr.kpmg.com | BK101: 조일상 | BL101: ijo@kr.kpmg.com | BU101: 양순재 | BV101: soonjaeyang@kr.kpmg.com | CG101: 권경진 | CH101: kyungjinkwon@kr.kpmg.com | CZ101: #N/A | DA101: #N/A | DC101: V | DD101: =IF(AF101="제외요청", "V","") -> V
C102: 1681431 | D102: 96 | E102: IGH | F102: 1000317554 | G102: 케이엔솔 주식회사 | H102: 1681431 | I102: [케이엔솔] FY2025 회계감사 | J102: 코스닥 | L102: (지주회사) | AD102: N | AE102: 45958 | AF102: 제외요청 | AG102: 건설업. 진행기준 매출. 선급금으로 비용 배분 발생 | BA102: 유재준 | BB102: jyoo8@kr.kpmg.com | BE102: 서은아 | BF102: eseo@kr.kpmg.com | BG102: 현승임 | BH102: shyun@kr.kpmg.com | BI102: 이주영 | BJ102: jooyounglee@kr.kpmg.com | BK102: 박상옥 | BL102: sangokpark@kr.kpmg.com | BU102: 박종근 | BV102: jongkeunpark@kr.kpmg.com | CG102: 현예슬 | CH102: yhyeon@kr.kpmg.com | CZ102: #N/A | DA102: #N/A | DD102: =IF(AF102="제외요청", "V","") -> V
...

Sheet 이메일 주소(전체)
B2: jaenamhwang@kr.kpmg.com, sehongchoi@kr.kpmg.com, sangkeunlee@kr.kpmg.com, hwanukjung@kr.kpmg.com, choongkilee@kr.kpmg.com, dayeongahn@kr.kpmg.com | S2: jaenamhwang@kr.kpmg.com, sehongchoi@kr.kpmg.com, sangkeunlee@kr.kpmg.com, hwanukjung@kr.kpmg.com, choongkilee@kr.kpmg.com, dayeongahn@kr.kpmg.com | T2: =SUBSTITUTE(S2,", ","; ") -> jaenamhwang@kr.kpmg.com; sehongchoi@kr.kpmg.com; sangkeunlee@kr.kpmg.com; hwanukjung@kr.kpmg.com; choongkilee@kr.kpmg.com; dayeongahn@kr.kpmg.com | U2: {=_xlfn.LET(_xlpm.r,T2:T192,_xlpm.repl,SUBSTITUTE(_xlpm.r,",","; "),_xlpm.all,_xlfn.TEXTSPLIT(_xlfn.TEXTJOIN(";",TRUE,_xlpm.repl),";"),_xlpm.clean,TRIM(_xlpm.all),_xlpm.noempty,_xlfn._xlws.FILTER(_xlpm.clean,_xlpm.clean<>""),_xlpm.dedup,_xlfn.UNIQUE(_xlpm.noempty),_xlfn.TEXTJOIN("; ",TRUE,_xlpm.dedup))} -> jaenamhwang@kr.kpmg.com; sehongchoi@kr.kpmg.com; sangkeunlee@kr.kpmg.com; hwanukjung@kr.kpmg.com; choongkilee@kr.kpmg.com; dayeongahn@kr.kpmg.com; seungmikang@kr.kpmg.com; jeewonlee@kr.kpmg.com; jinboshim@kr.kpmg.com; jlee79@kr.kpmg.com; semokim@kr.kpmg.com; jjung9@kr.kpmg.com; jungkikim@kr.kpmg.com; yeehyunchoi@kr.kpmg.com; euijinkim@kr.kpmg.com; yangkijung@kr.kpmg.com; sungchaekang@kr.kpmg.com; juneheeshin@kr.kpmg.com; djung4@kr.kpmg.com; jaenamhwang@kr.kpmg.com; dongjunshin@kr.kpmg.com; skim56@kr.kpmg.com; yosupgo@kr.kpmg.com; chaeneunglee@kr.kpmg.com; mbaek@kr.kpmg.com; yungicho@kr.kpmg.com; hsul@kr.kpmg.com; yseol@kr.kpmg.com; jinjang@kr.kpmg.com; jongseokyoun@kr.kpmg.com; cahn@kr.kpmg.com; yeontaekchoi@kr.kpmg.com; hkim108@kr.kpmg.com; mingyuhan@kr.kpmg.com; yhyun@kr.kpmg.com; siwookim@kr.kpmg.com; seungjaeoh@kr.kpmg.com; kwangsulee@kr.kpmg.com; joohunyoon@kr.kpmg.com; ikchankim@kr.kpmg.com; yoonahlee@kr.kpmg.com; hyeongcheollee@kr.kpmg.com; sanghoroh@kr.kpmg.com; wjeon@kr.kpmg.com; seongilkim@kr.kpmg.com; gibaeksong@kr.kpmg.com; hyunwootak@kr.kpmg.com; yhyun@kr.kpmg.com; hchung@kr.kpmg.com; clee60@kr.kpmg.com; ychoi@kr.kpmg.com; sungbaekim@kr.kpmg.com; jongsunam@kr.kpmg.com; hchung@kr.kpmg.com; joongkyukim@kr.kpmg.com; yaehyeonkim@kr.kpmg.com; konkukkang@kr.kpmg.com; jra@kr.kpmg.com; jjoung@kr.kpmg.com; yeasolju@kr.kpmg.com; ckim12@kr.kpmg.com; sungbaepark@kr.kpmg.com; yeontaekchoi@kr.kpmg.com; jjung32@kr.kpmg.com; dchi@kr.kpmg.com; hwasoocho@kr.kpmg.com; yeasolju@kr.kpmg.com; ykim47@kr.kpmg.com; hyunminjang@kr.kpmg.com; sangkilee@kr.kpmg.com; sehyunlee@kr.kpmg.com; ykim85@kr.kpmg.com; kyungsuklee@kr.kpmg.com; sanghoroh@kr.kpmg.com; jeongheehan@kr.kpmg.com; ychoi@kr.kpmg.com; sanghyunbyun@kr.kpmg.com; younginwon@kr.kpmg.com; sunseokcha@kr.kpmg.com; jra@kr.kpmg.com; jongsanglee@kr.kpmg.com; jchoi13@kr.kpmg.com; moonchulshin@kr.kpmg.com; sungbaepark@kr.kpmg.com; jaejoongkim@kr.kpmg.com; hocheolyang@kr.kpmg.com; chaeneunglee@kr.kpmg.com; ycha@kr.kpmg.com; seongilkim@kr.kpmg.com; gimyeonghwang@kr.kpmg.com; sanghyunhan@kr.kpmg.com; sungbaepark@kr.kpmg.com; jahn6@kr.kpmg.com; mkang8@kr.kpmg.com; hyunsukkim@kr.kpmg.com; hyundonghwang@kr.kpmg.com; changwonseo@kr.kpmg.com; gyeongokim@kr.kpmg.com; tkim@kr.kpmg.com; dohyunkim@kr.kpmg.com; jongsunam@kr.kpmg.com; taeseoblee@kr.kpmg.com; sangkeunlee@kr.kpmg.com; wjeon@kr.kpmg.com; inchanhwang@kr.kpmg.com; howonyoon@kr.kpmg.com; jroh@kr.kpmg.com; hsul@kr.kpmg.com; hlee42@kr.kpmg.com; hyegyeongryu@kr.kpmg.com; moonchulshin@kr.kpmg.com; kyunghopark@kr.kpmg.com; jinholee1@kr.kpmg.com; ikang@kr.kpmg.com; sanghoonpark@kr.kpmg.com; mingyulee@kr.kpmg.com; skim106@kr.kpmg.com; seungmikang@kr.kpmg.com; syeom@kr.kpmg.com; semokim@kr.kpmg.com; sanghyunhan@kr.kpmg.com; hakbeomlee@kr.kpmg.com; sorakim@kr.kpmg.com; yeehyunchoi@kr.kpmg.com; yeontaekchoi@kr.kpmg.com; jeongungcha@kr.kpmg.com; changilwon@kr.kpmg.com; hchung@kr.kpmg.com; junheehan@kr.kpmg.com; seunghoikoo@kr.kpmg.com; juhyunglee@kr.kpmg.com; jinmokkim@kr.kpmg.com; eunjeonghong@kr.kpmg.com; sangminnam@kr.kpmg.com; kyuhonglee1@kr.kpmg.com; suminpark@kr.kpmg.com; yanghoshin@kr.kpmg.com; sanghyunhan@kr.kpmg.com; yangkijung@kr.kpmg.com; jongroklee@kr.kpmg.com; hyunsukkim@kr.kpmg.com; hochullee@kr.kpmg.com; hkim51@kr.kpmg.com; sangminnam@kr.kpmg.com; yeonjungkim@kr.kpmg.com; sunguckkim@kr.kpmg.com; hkim51@kr.kpmg.com; sangminnam@kr.kpmg.com; sungbaekim@kr.kpmg.com; suminpark@kr.kpmg.com; myoungjaejeon@kr.kpmg.com; yongholee@kr.kpmg.com; siwookim@kr.kpmg.com; seungjaeoh@kr.kpmg.com; skim127@kr.kpmg.com; kyungsuklee@kr.kpmg.com; slee14@kr.kpmg.com; jungwookdo@kr.kpmg.com; jungsoopark@kr.kpmg.com; jinyoungson@kr.kpmg.com; yeonjoochoi@kr.kpmg.com; yseol@kr.kpmg.com; hongminpark@kr.kpmg.com; shinyoungkim@kr.kpmg.com; naehyeongkwon@kr.kpmg.com; kwanjongpark@kr.kpmg.com; hjo@kr.kpmg.com; changhyunan@kr.kpmg.com; jkim216@kr.kpmg.com; changgiljung@kr.kpmg.com; jungsoopark@kr.kpmg.com; sungwoonchoi@kr.kpmg.com; juhyunglee@kr.kpmg.com; sangilhan@kr.kpmg.com; sanghwapark@kr.kpmg.com; jungwookdo@kr.kpmg.com; ijo@kr.kpmg.com; juhyungkim@kr.kpmg.com; soh10@kr.kpmg.com; smin@kr.kpmg.com; seungmikang@kr.kpmg.com; yoorachoi@kr.kpmg.com; dongyoonlee@kr.kpmg.com; ikang@kr.kpmg.com; soyoungpark@kr.kpmg.com; mcho5@kr.kpmg.com; sangokpark@kr.kpmg.com; sukwangkim@kr.kpmg.com; mjang3@kr.kpmg.com; wjeon@kr.kpmg.com; yangkijung@kr.kpmg.com; eunseokkim@kr.kpmg.com; chaeneunglee@kr.kpmg.com; dongjunshin@kr.kpmg.com; skim56@kr.kpmg.com; sujungna@kr.kpmg.com; hyunhojeon@kr.kpmg.com; sbeom@kr.kpmg.com; khur@kr.kpmg.com; jaehoonheo@kr.kpmg.com; wonseol@kr.kpmg.com; euijinkim@kr.kpmg.com; byungyuljung@kr.kpmg.com; dchi@kr.kpmg.com; hwasoocho@kr.kpmg.com; jinseokyang@kr.kpmg.com; jeongeunshin@kr.kpmg.com; wjeon@kr.kpmg.com; ychoi@kr.kpmg.com; kyu3@kr.kpmg.com; yhyun@kr.kpmg.com; changgiljung@kr.kpmg.com; sungwookkim@kr.kpmg.com; jongsanglee@kr.kpmg.com; jaenamhwang@kr.kpmg.com; younginwon@kr.kpmg.com; jlee92@kr.kpmg.com; bohyunyoon@kr.kpmg.com; tkim@kr.kpmg.com; khwang@kr.kpmg.com; jiheonkang@kr.kpmg.com; sanghoonpark@kr.kpmg.com; khwang@kr.kpmg.com; skim125@kr.kpmg.com; gbak@kr.kpmg.com; jongsanglee@kr.kpmg.com; sanghyunbyun@kr.kpmg.com; younginwon@kr.kpmg.com; yongbeomlee@kr.kpmg.com; jeonggukang@kr.kpmg.com; jooyounglee@kr.kpmg.com; sungheeyoo@kr.kpmg.com; minkyungshin@kr.kpmg.com; ikang@kr.kpmg.com; jinseokchoi@kr.kpmg.com; junhyeoklee@kr.kpmg.com; daeryukjeong@kr.kpmg.com; tkim@kr.kpmg.com; sangokpark@kr.kpmg.com; sangseokseo@kr.kpmg.com; hoyoungshin@kr.kpmg.com; sanghoonpark@kr.kpmg.com; jungwookdo@kr.kpmg.com; hkim23@kr.kpmg.com; jihamchoi@kr.kpmg.com; jongsanglee@kr.kpmg.com; jeonggukang@kr.kpmg.com; kwanghyunyun@kr.kpmg.com; sungchaekang@kr.kpmg.com; jungsoolee@kr.kpmg.com; sunguckkim@kr.kpmg.com; sunghobu@kr.kpmg.com; sehongchoi@kr.kpmg.com; mbaek@kr.kpmg.com; spark20@kr.kpmg.com; sanghoroh@kr.kpmg.com; deokyeonglee@kr.kpmg.com; jeonghoonpark@kr.kpmg.com; seungheecho@kr.kpmg.com; kyungsuklee@kr.kpmg.com; slee14@kr.kpmg.com; hchung@kr.kpmg.com; yongholee@kr.kpmg.com; bkim13@kr.kpmg.com; yongwookkim@kr.kpmg.com; kwanjongpark@kr.kpmg.com; hjo@kr.kpmg.com; changhyunan@kr.kpmg.com; jbak@kr.kpmg.com; ijo@kr.kpmg.com; soonjaeyang@kr.kpmg.com; wooseokheo@kr.kpmg.com; jooyounglee@kr.kpmg.com; sangokpark@kr.kpmg.com; jongkeunpark@kr.kpmg.com; hyunhojeon@kr.kpmg.com; taeungjeon@kr.kpmg.com; hkim51@kr.kpmg.com; kwanjongpark@kr.kpmg.com; hakbeomlee@kr.kpmg.com; changwonseo@kr.kpmg.com; yeonjuchu@kr.kpmg.com; heeseokkang@kr.kpmg.com; jooyounglee@kr.kpmg.com; sungheeyoo@kr.kpmg.com; dlee89@kr.kpmg.com; jeewonlee@kr.kpmg.com; jaehoonheo@kr.kpmg.com; jinjang@kr.kpmg.com; jaehyunjeon@kr.kpmg.com; khwang@kr.kpmg.com; sukwangkim@kr.kpmg.com; hkim23@kr.kpmg.com; dongjoonchi@kr.kpmg.com; junsikuhm@kr.kpmg.com; yangkijung@kr.kpmg.com; jaewanlim@kr.kpmg.com; kyunghopark@kr.kpmg.com; dohyunkim@kr.kpmg.com; mingyusong@kr.kpmg.com; jkim258@kr.kpmg.com; hchung@kr.kpmg.com; yongholee@kr.kpmg.com; soonjaeyang@kr.kpmg.com; ihwang7@kr.kpmg.com; hyunminjang@kr.kpmg.com; kwanjongpark@kr.kpmg.com; jaehyoungan@kr.kpmg.com; wonjaekang@kr.kpmg.com; ikang@kr.kpmg.com; jaehoonheo@kr.kpmg.com; yoonahlee@kr.kpmg.com; junhyeoklee@kr.kpmg.com; hyucksoonchoi@kr.kpmg.com; hyunhojeon@kr.kpmg.com; yeonjungkim@kr.kpmg.com; kwanghyunyun@kr.kpmg.com; sangokpark@kr.kpmg.com; yeounchoi@kr.kpmg.com; suyeonkim@kr.kpmg.com; dchi@kr.kpmg.com; sangminnam@kr.kpmg.com; pjeong@kr.kpmg.com; dongjunshin@kr.kpmg.com; sukwangkim@kr.kpmg.com; jkim143@kr.kpmg.com; jhwang4@kr.kpmg.com; daejinkim@kr.kpmg.com; hochullee@kr.kpmg.com; sunguckkim@kr.kpmg.com; junhyunghong@kr.kpmg.com; smin@kr.kpmg.com; jaehoonheo@kr.kpmg.com; donggyulee@kr.kpmg.com; sangokpark@kr.kpmg.com; daejinkim@kr.kpmg.com; yulcheolpark@kr.kpmg.com; ylee67@kr.kpmg.com; jaenamhwang@kr.kpmg.com; kyunghopark@kr.kpmg.com; jlee123@kr.kpmg.com; sungchaekang@kr.kpmg.com; yongholee@kr.kpmg.com; jinyoungson@kr.kpmg.com; chulyoungkim@kr.kpmg.com; hwasoocho@kr.kpmg.com; jinseokyang@kr.kpmg.com; yeonjuchu@kr.kpmg.com; khwang@kr.kpmg.com; dohyunkim@kr.kpmg.com; mkim175@kr.kpmg.com; dkim240@kr.kpmg.com; sangkeunlee@kr.kpmg.com; hyunminjang@kr.kpmg.com; woohyunyi@kr.kpmg.com; changgiljung@kr.kpmg.com; dchi@kr.kpmg.com; inchanhwang@kr.kpmg.com; syoo7@kr.kpmg.com; hchung@kr.kpmg.com; yongholee@kr.kpmg.com; yaehyeonkim@kr.kpmg.com; konkukkang@kr.kpmg.com; chulyoungkim@kr.kpmg.com; kyungsuklee@kr.kpmg.com; slee14@kr.kpmg.com; hyunminjang@kr.kpmg.com; jungwookdo@kr.kpmg.com; minjujeong@kr.kpmg.com; kyunghopark@kr.kpmg.com; gleem@kr.kpmg.com; jeonghoonpark@kr.kpmg.com; jungkikim@kr.kpmg.com; moonchulshin@kr.kpmg.com; edo@kr.kpmg.com; seungohwoo@kr.kpmg.com; sangilhan@kr.kpmg.com; jlee79@kr.kpmg.com; sungwoonchoi@kr.kpmg.com; sangilhan@kr.kpmg.com; jlee79@kr.kpmg.com; bkim13@kr.kpmg.com; yongwookkim@kr.kpmg.com; jungsoolee@kr.kpmg.com; jjoung@kr.kpmg.com; jaeyeonleem@kr.kpmg.com; jlee177@kr.kpmg.com; cahn@kr.kpmg.com; yseol@kr.kpmg.com; yoorachoi@kr.kpmg.com; seungheecho@kr.kpmg.com; sanghoonpark@kr.kpmg.com; jlee92@kr.kpmg.com; hyim@kr.kpmg.com; jooyounglee@kr.kpmg.com; chaeneunglee@kr.kpmg.com; jongroklee@kr.kpmg.com; jungkikim@kr.kpmg.com; sanghyunkang@kr.kpmg.com; euijinkim@kr.kpmg.com; jooyounglee@kr.kpmg.com; seunghoikoo@kr.kpmg.com; jeonghoonlee@kr.kpmg.com; siwookim@kr.kpmg.com; ijo@kr.kpmg.com; gyeon@kr.kpmg.com; sungchaekang@kr.kpmg.com; seungmikang@kr.kpmg.com; woohyunyi@kr.kpmg.com; sukheehan@kr.kpmg.com; chaeneunglee@kr.kpmg.com; daejinkim@kr.kpmg.com; jaehyukjang@kr.kpmg.com; hcho12@kr.kpmg.com; seungmikang@kr.kpmg.com; moonchulshin@kr.kpmg.com; scho3@kr.kpmg.com; jroh@kr.kpmg.com; hsul@kr.kpmg.com; seongbeomlee@kr.kpmg.com; sungbaekim@kr.kpmg.com; hyundonghwang@kr.kpmg.com; giwoongbae@kr.kpmg.com; junsikuhm@kr.kpmg.com; taeungjeon@kr.kpmg.com; hkim51@kr.kpmg.com; ijo@kr.kpmg.com; tkim@kr.kpmg.com; jkim143@kr.kpmg.com; seungmikang@kr.kpmg.com; yeontaekchoi@kr.kpmg.com; ykang4@kr.kpmg.com; hakbeomlee@kr.kpmg.com; daejinkim@kr.kpmg.com; jaehyukjang@kr.kpmg.com; jungohyoon@kr.kpmg.com; jungkikim@kr.kpmg.com; yeehyunchoi@kr.kpmg.com; sangkilee@kr.kpmg.com; seungmikang@kr.kpmg.com; woohyunyi@kr.kpmg.com; yeonjungkim@kr.kpmg.com; heeseokkang@kr.kpmg.com; jchoi13@kr.kpmg.com; hyunminjang@kr.kpmg.com; kwanjongpark@kr.kpmg.com; jaehyoungan@kr.kpmg.com; wonjaekang@kr.kpmg.com; jaeyeonkim@kr.kpmg.com; jra@kr.kpmg.com; yulcheolpark@kr.kpmg.com; kwonjaelee@kr.kpmg.com; sukwangkim@kr.kpmg.com; yhyun@kr.kpmg.com; yaehyeonkim@kr.kpmg.com; sehongchoi@kr.kpmg.com; kyuhonglee1@kr.kpmg.com; mkim175@kr.kpmg.com; daejinkim@kr.kpmg.com; jjoung@kr.kpmg.com; giwoongbae@kr.kpmg.com; dongyoonlee@kr.kpmg.com; ikang@kr.kpmg.com; taehyunglee@kr.kpmg.com; doheunkim@kr.kpmg.com; heeseokkang@kr.kpmg.com; yeounchoi@kr.kpmg.com; jaehyukjang@kr.kpmg.com; dokyunglee@kr.kpmg.com; hakbeomlee@kr.kpmg.com; jeonghwancha@kr.kpmg.com; sungkyujung@kr.kpmg.com; jinhyeokwoo@kr.kpmg.com; kyunghopark@kr.kpmg.com; yeounchoi@kr.kpmg.com; jlee92@kr.kpmg.com; gyucheoloh@kr.kpmg.com; jaeyeonkim@kr.kpmg.com; wjeon@kr.kpmg.com; sungheeyoo@kr.kpmg.com; hyunwootak@kr.kpmg.com; ycha@kr.kpmg.com; heeseokkang@kr.kpmg.com; jlee123@kr.kpmg.com; changgiljung@kr.kpmg.com; yongholee@kr.kpmg.com; jaehyoungan@kr.kpmg.com; wonjaekang@kr.kpmg.com; dongjunshin@kr.kpmg.com; hochullee@kr.kpmg.com; sunguckkim@kr.kpmg.com; tkim50@kr.kpmg.com; jjoung@kr.kpmg.com; sbeom@kr.kpmg.com; hyoungtakhan@kr.kpmg.com; ychoi@kr.kpmg.com; dchi@kr.kpmg.com; yeongminlee@kr.kpmg.com; spark72@kr.kpmg.com; junsikuhm@kr.kpmg.com; yeounchoi@kr.kpmg.com; suyeonkim@kr.kpmg.com; sanghyunkang@kr.kpmg.com; jeewonlee@kr.kpmg.com; jboo@kr.kpmg.com; ychoi@kr.kpmg.com; ycha@kr.kpmg.com; jlee92@kr.kpmg.com; kyungsunkwon@kr.kpmg.com; daejinkim@kr.kpmg.com; sungchaekang@kr.kpmg.com; spark20@kr.kpmg.com; yeehyunchoi@kr.kpmg.com; yeontaekchoi@kr.kpmg.com; ykang4@kr.kpmg.com; smin@kr.kpmg.com; yeehyunchoi@kr.kpmg.com; jaeyoungpark@kr.kpmg.com; joohunyoon@kr.kpmg.com; daejinkim@kr.kpmg.com; jlee92@kr.kpmg.com; jungohyoon@kr.kpmg.com; yangkijung@kr.kpmg.com; hochullee@kr.kpmg.com; sseo@kr.kpmg.com; dohyunkim@kr.kpmg.com; daejinkim@kr.kpmg.com; suyeonkim@kr.kpmg.com; chulyoungkim@kr.kpmg.com; sangminnam@kr.kpmg.com; eunseokkim@kr.kpmg.com; khwang@kr.kpmg.com; jungwookdo@kr.kpmg.com; jkim143@kr.kpmg.com; jihoonchoo@kr.kpmg.com; seunghoikoo@kr.kpmg.com; seungmikang@kr.kpmg.com; woohyunyi@kr.kpmg.com; sukheehan@kr.kpmg.com; jongwoolee@kr.kpmg.com; joongkyukim@kr.kpmg.com; yaehyeonkim@kr.kpmg.com; cbae1@kr.kpmg.com; hyunsukkim@kr.kpmg.com; seungmikang@kr.kpmg.com; jaeyoungpark@kr.kpmg.com; hyeongcheollee@kr.kpmg.com; jongsanglee@kr.kpmg.com; jungwoohan@kr.kpmg.com; yno@kr.kpmg.com; dohyunkim@kr.kpmg.com; jra@kr.kpmg.com; younakim@kr.kpmg.com; jungsoopark@kr.kpmg.com; siwookim@kr.kpmg.com; sanghwapark@kr.kpmg.com; youngjoojin@kr.kpmg.com; kiwoongkim@kr.kpmg.com; ikchankim@kr.kpmg.com; seunghoikoo@kr.kpmg.com; scho3@kr.kpmg.com; sehongchoi@kr.kpmg.com; kyuhonglee1@kr.kpmg.com; jongsunam@kr.kpmg.com; jeonghwancha@kr.kpmg.com; dongyoonlee@kr.kpmg.com; hyejujang@kr.kpmg.com; yeonjungkim@kr.kpmg.com; hongminpark@kr.kpmg.com; edo@kr.kpmg.com; seungheecho@kr.kpmg.com; ycha@kr.kpmg.com; mingyulee@kr.kpmg.com; dasanyoun@kr.kpmg.com; dongyoonlee@kr.kpmg.com; hyunminjang@kr.kpmg.com; hyeonggilwi@kr.kpmg.com; cahn@kr.kpmg.com; sehongchoi@kr.kpmg.com; sorakim@kr.kpmg.com; smin@kr.kpmg.com; cahn@kr.kpmg.com; seoyoungnam@kr.kpmg.com; joonggimin@kr.kpmg.com; daejinkim@kr.kpmg.com; joongkyukim@kr.kpmg.com; jiheonkang@kr.kpmg.com; chulyoungkim@kr.kpmg.com; hwasoocho@kr.kpmg.com; jinseokyang@kr.kpmg.com; hyunjaeim@kr.kpmg.com; hyundonghwang@kr.kpmg.com; heeseokkang@kr.kpmg.com; dlee34@kr.kpmg.com; jaehoonheo@kr.kpmg.com; tkim@kr.kpmg.com; seunghyeonpark@kr.kpmg.com; jungkikim@kr.kpmg.com; hyundonghwang@kr.kpmg.com; jaeyeonleem@kr.kpmg.com; jkim508@kr.kpmg.com; sangilhan@kr.kpmg.com; kwanjongpark@kr.kpmg.com; jinyoungson@kr.kpmg.com; yeonjoochoi@kr.kpmg.com; sbeom@kr.kpmg.com; hchung@kr.kpmg.com; junheehan@kr.kpmg.com; jungsoopark@kr.kpmg.com; sanghoonpark@kr.kpmg.com; sungheeyoo@kr.kpmg.com; dkim77@kr.kpmg.com; jungwoohan@kr.kpmg.com; khwang@kr.kpmg.com; jiheonkang@kr.kpmg.com; sbeom@kr.kpmg.com; wjeon@kr.kpmg.com; skim66@kr.kpmg.com; kyungsuklee@kr.kpmg.com; sanghoroh@kr.kpmg.com; sorakim@kr.kpmg.com; yangkijung@kr.kpmg.com; smin@kr.kpmg.com; hlee42@kr.kpmg.com; jeonghwancha@kr.kpmg.com; yoongeunoh@kr.kpmg.com; yungicho@kr.kpmg.com; seungmikang@kr.kpmg.com; sukwangkim@kr.kpmg.com; clee60@kr.kpmg.com; sangilhan@kr.kpmg.com; minjujeong@kr.kpmg.com; jooyounglee@kr.kpmg.com; seunghoikoo@kr.kpmg.com; jahn6@kr.kpmg.com; naehyeongkwon@kr.kpmg.com; hyunminjang@kr.kpmg.com; seunghoikoo@kr.kpmg.com; jeonghoonlee@kr.kpmg.com; wonseol@kr.kpmg.com; jeonghwancha@kr.kpmg.com; seoyoungnam@kr.kpmg.com; mincheolyun@kr.kpmg.com; hyunhojeon@kr.kpmg.com; kyuhonglee1@kr.kpmg.com; mkim175@kr.kpmg.com; joongkyukim@kr.kpmg.com; hjo@kr.kpmg.com; clee60@kr.kpmg.com; jkim181@kr.kpmg.com; jungsoolee@kr.kpmg.com; jjoung@kr.kpmg.com; changwonseo@kr.kpmg.com; jlee177@kr.kpmg.com; jongwoolee@kr.kpmg.com; seunghyeonpark@kr.kpmg.com; yoongeunoh@kr.kpmg.com; yungicho@kr.kpmg.com; hochullee@kr.kpmg.com; mkim175@kr.kpmg.com; tkim@kr.kpmg.com; mjang3@kr.kpmg.com; seungheecho@kr.kpmg.com; tkim@kr.kpmg.com; jkim143@kr.kpmg.com; youngmokoo@kr.kpmg.com; yeehyunchoi@kr.kpmg.com; yeontaekchoi@kr.kpmg.com; sungkyujung@kr.kpmg.com; jinhyeokwoo@kr.kpmg.com
B3: seungmikang@kr.kpmg.com, jeewonlee@kr.kpmg.com, jinboshim@kr.kpmg.com, jlee79@kr.kpmg.com, semokim@kr.kpmg.com, jjung9@kr.kpmg.com | S3: seungmikang@kr.kpmg.com, jeewonlee@kr.kpmg.com, jinboshim@kr.kpmg.com, jlee79@kr.kpmg.com, semokim@kr.kpmg.com, jjung9@kr.kpmg.com | T3: =SUBSTITUTE(S3,", ","; ") -> seungmikang@kr.kpmg.com; jeewonlee@kr.kpmg.com; jinboshim@kr.kpmg.com; jlee79@kr.kpmg.com; semokim@kr.kpmg.com; jjung9@kr.kpmg.com
B4: jungkikim@kr.kpmg.com, yeehyunchoi@kr.kpmg.com, euijinkim@kr.kpmg.com | S4: jungkikim@kr.kpmg.com, yeehyunchoi@kr.kpmg.com, euijinkim@kr.kpmg.com | T4: =SUBSTITUTE(S4,", ","; ") -> jungkikim@kr.kpmg.com; yeehyunchoi@kr.kpmg.com; euijinkim@kr.kpmg.com
B5: yangkijung@kr.kpmg.com, sungchaekang@kr.kpmg.com, juneheeshin@kr.kpmg.com, djung4@kr.kpmg.com | S5: yangkijung@kr.kpmg.com, sungchaekang@kr.kpmg.com, juneheeshin@kr.kpmg.com, djung4@kr.kpmg.com | T5: =SUBSTITUTE(S5,", ","; ") -> yangkijung@kr.kpmg.com; sungchaekang@kr.kpmg.com; juneheeshin@kr.kpmg.com; djung4@kr.kpmg.com
B6: jaenamhwang@kr.kpmg.com, dongjunshin@kr.kpmg.com, skim56@kr.kpmg.com, yosupgo@kr.kpmg.com | S6: jaenamhwang@kr.kpmg.com, dongjunshin@kr.kpmg.com, skim56@kr.kpmg.com, yosupgo@kr.kpmg.com | T6: =SUBSTITUTE(S6,", ","; ") -> jaenamhwang@kr.kpmg.com; dongjunshin@kr.kpmg.com; skim56@kr.kpmg.com; yosupgo@kr.kpmg.com
B7: chaeneunglee@kr.kpmg.com, mbaek@kr.kpmg.com, yungicho@kr.kpmg.com | S7: chaeneunglee@kr.kpmg.com, mbaek@kr.kpmg.com, yungicho@kr.kpmg.com | T7: =SUBSTITUTE(S7,", ","; ") -> chaeneunglee@kr.kpmg.com; mbaek@kr.kpmg.com; yungicho@kr.kpmg.com
B8: hsul@kr.kpmg.com, yseol@kr.kpmg.com, jinjang@kr.kpmg.com, jongseokyoun@kr.kpmg.com | S8: hsul@kr.kpmg.com, yseol@kr.kpmg.com, jinjang@kr.kpmg.com, jongseokyoun@kr.kpmg.com | T8: =SUBSTITUTE(S8,", ","; ") -> hsul@kr.kpmg.com; yseol@kr.kpmg.com; jinjang@kr.kpmg.com; jongseokyoun@kr.kpmg.com
B9: cahn@kr.kpmg.com, yeontaekchoi@kr.kpmg.com, hkim108@kr.kpmg.com, mingyuhan@kr.kpmg.com | S9: cahn@kr.kpmg.com, yeontaekchoi@kr.kpmg.com, hkim108@kr.kpmg.com, mingyuhan@kr.kpmg.com | T9: =SUBSTITUTE(S9,", ","; ") -> cahn@kr.kpmg.com; yeontaekchoi@kr.kpmg.com; hkim108@kr.kpmg.com; mingyuhan@kr.kpmg.com
B10: yhyun@kr.kpmg.com, siwookim@kr.kpmg.com, seungjaeoh@kr.kpmg.com, kwangsulee@kr.kpmg.com | S10: yhyun@kr.kpmg.com, siwookim@kr.kpmg.com, seungjaeoh@kr.kpmg.com, kwangsulee@kr.kpmg.com | T10: =SUBSTITUTE(S10,", ","; ") -> yhyun@kr.kpmg.com; siwookim@kr.kpmg.com; seungjaeoh@kr.kpmg.com; kwangsulee@kr.kpmg.com
B11: joohunyoon@kr.kpmg.com, ikchankim@kr.kpmg.com, yoonahlee@kr.kpmg.com, hyeongcheollee@kr.kpmg.com | S11: joohunyoon@kr.kpmg.com, ikchankim@kr.kpmg.com, yoonahlee@kr.kpmg.com, hyeongcheollee@kr.kpmg.com | T11: =SUBSTITUTE(S11,", ","; ") -> joohunyoon@kr.kpmg.com; ikchankim@kr.kpmg.com; yoonahlee@kr.kpmg.com; hyeongcheollee@kr.kpmg.com
B12: sanghoroh@kr.kpmg.com, wjeon@kr.kpmg.com, seongilkim@kr.kpmg.com, gibaeksong@kr.kpmg.com, hyunwootak@kr.kpmg.com | S12: sanghoroh@kr.kpmg.com, wjeon@kr.kpmg.com, seongilkim@kr.kpmg.com, gibaeksong@kr.kpmg.com, hyunwootak@kr.kpmg.com | T12: =SUBSTITUTE(S12,", ","; ") -> sanghoroh@kr.kpmg.com; wjeon@kr.kpmg.com; seongilkim@kr.kpmg.com; gibaeksong@kr.kpmg.com; hyunwootak@kr.kpmg.com
B13: yhyun@kr.kpmg.com, hchung@kr.kpmg.com, clee60@kr.kpmg.com | S13: yhyun@kr.kpmg.com, hchung@kr.kpmg.com, clee60@kr.kpmg.com | T13: =SUBSTITUTE(S13,", ","; ") -> yhyun@kr.kpmg.com; hchung@kr.kpmg.com; clee60@kr.kpmg.com
B14: ychoi@kr.kpmg.com, sungbaekim@kr.kpmg.com, jongsunam@kr.kpmg.com | S14: ychoi@kr.kpmg.com, sungbaekim@kr.kpmg.com, jongsunam@kr.kpmg.com | T14: =SUBSTITUTE(S14,", ","; ") -> ychoi@kr.kpmg.com; sungbaekim@kr.kpmg.com; jongsunam@kr.kpmg.com
... B192: yeehyunchoi@kr.kpmg.com, yeontaekchoi@kr.kpmg.com, sungkyujung@kr.kpmg.com, jinhyeokwoo@kr.kpmg.com | S192: yeehyunchoi@kr.kpmg.com, yeontaekchoi@kr.kpmg.com, sungkyujung@kr.kpmg.com, jinhyeokwoo@kr.kpmg.com | T192: =SUBSTITUTE(S192,", ","; ") -> yeehyunchoi@kr.kpmg.com; yeontaekchoi@kr.kpmg.com; sungkyujung@kr.kpmg.com; jinhyeokwoo@kr.kpmg.com

Sheet 이메일 주소(ICA)
B2: 정진우(jjung9@kr.kpmg.com) | F2: 정진우 | G2: jjung9@kr.kpmg.com | J2: =_xlfn.XLOOKUP(K2,G:G,F:F) -> 정진우 | K2: jjung9@kr.kpmg.com | N2: =_xlfn.TEXTJOIN("; ",TRUE,$K$2:$K$123) -> jjung9@kr.kpmg.com; seongbeomlee@kr.kpmg.com; djung4@kr.kpmg.com; yosupgo@kr.kpmg.com; yeongkyunkim@kr.kpmg.com; jongseokyoun@kr.kpmg.com; kwangsulee@kr.kpmg.com; hyeongcheollee@kr.kpmg.com; jaekeunlee@kr.kpmg.com; jlee176@kr.kpmg.com; konkukkang@kr.kpmg.com; ckim12@kr.kpmg.com; seonghwanchoi@kr.kpmg.com; ykim47@kr.kpmg.com; ykim85@kr.kpmg.com; clee45@kr.kpmg.com; sboo@kr.kpmg.com; hocheolyang@kr.kpmg.com; mkang8@kr.kpmg.com; gyeongokim@kr.kpmg.com; taeseoblee@kr.kpmg.com; hyegyeongryu@kr.kpmg.com; yiranglim@kr.kpmg.com; slee89@kr.kpmg.com; ghyun@kr.kpmg.com; changilwon@kr.kpmg.com; youngjoojin@kr.kpmg.com; eunjeonghong@kr.kpmg.com; yanghoshin@kr.kpmg.com; kwangheecho@kr.kpmg.com; jinukjeong@kr.kpmg.com; hkim51@kr.kpmg.com; myoungjaejeon@kr.kpmg.com; skim127@kr.kpmg.com; jihyeongjang@kr.kpmg.com; yeonjoochoi@kr.kpmg.com; naehyeongkwon@kr.kpmg.com; jkim216@kr.kpmg.com; hyejungjung@kr.kpmg.com; byungyuljung@kr.kpmg.com; mcho5@kr.kpmg.com; yeongminlee@kr.kpmg.com; seungheonjeong@kr.kpmg.com; sujungna@kr.kpmg.com; jeongeunshin@kr.kpmg.com; jkim508@kr.kpmg.com; jongsukim@kr.kpmg.com; bohyunyoon@kr.kpmg.com; sangunlee@kr.kpmg.com; gbak@kr.kpmg.com; yongbeomlee@kr.kpmg.com; daeryukjeong@kr.kpmg.com; hoyoungshin@kr.kpmg.com; hyeongseokjeong@kr.kpmg.com; juwonpark@kr.kpmg.com; yongwookkim@kr.kpmg.com; jbak@kr.kpmg.com; wooseokheo@kr.kpmg.com; yhyeon@kr.kpmg.com; rbaek@kr.kpmg.com; yeonjuchu@kr.kpmg.com; jaehyunjeon@kr.kpmg.com; mkim63@kr.kpmg.com; wonjaekang@kr.kpmg.com; hyucksoonchoi@kr.kpmg.com; doyoungpark@kr.kpmg.com; hkim154@kr.kpmg.com; kichansung@kr.kpmg.com; jhwang4@kr.kpmg.com; heeseokseo@kr.kpmg.com; ylee67@kr.kpmg.com; jlee273@kr.kpmg.com; dkim240@kr.kpmg.com; mjeon1@kr.kpmg.com; jkim176@kr.kpmg.com; hkim131@kr.kpmg.com; jlee177@kr.kpmg.com; kwangsoocho@kr.kpmg.com; hyim@kr.kpmg.com; jaeminsim@kr.kpmg.com; dongyeokkim@kr.kpmg.com; slee336@kr.kpmg.com; gyeon@kr.kpmg.com; sukheehan@kr.kpmg.com; seungkikim@kr.kpmg.com; gahyunjang@kr.kpmg.com; kichankang@kr.kpmg.com; kwonjaelee@kr.kpmg.com; tkim50@kr.kpmg.com; doheunkim@kr.kpmg.com; dokyunglee@kr.kpmg.com; jinhyeokwoo@kr.kpmg.com; gyucheoloh@kr.kpmg.com; beomjinpark@kr.kpmg.com; spark72@kr.kpmg.com; seungjunkwak@kr.kpmg.com; jungohyoon@kr.kpmg.com; yooyounglee@kr.kpmg.com; jihoonchoo@kr.kpmg.com; cbae1@kr.kpmg.com; jchoi38@kr.kpmg.com; kiwoongkim@kr.kpmg.com; inwoohong@kr.kpmg.com; junhyunghong@kr.kpmg.com; jkim502@kr.kpmg.com; seulgibae@kr.kpmg.com; dasanyoun@kr.kpmg.com; ajungkim@kr.kpmg.com; jinjulee@kr.kpmg.com; joonggimin@kr.kpmg.com; minhyuckyoo@kr.kpmg.com; hyunjaeim@kr.kpmg.com; sangeonpark@kr.kpmg.com; taeyoonlee@kr.kpmg.com; gkwak@kr.kpmg.com; hkim238@kr.kpmg.com; mincheolyun@kr.kpmg.com; jkim181@kr.kpmg.com; jkim252@kr.kpmg.com; youngmokoo@kr.kpmg.com; mkim175@kr.kpmg.com; hkim51@kr.kpmg.com
B3: 이성범(seongbeomlee@kr.kpmg.com) | F3: 이성범 | G3: seongbeomlee@kr.kpmg.com | J3: =_xlfn.XLOOKUP(K3,G:G,F:F) -> 이성범 | K3: seongbeomlee@kr.kpmg.com
B4: 정대주(djung4@kr.kpmg.com) | F4: 정대주 | G4: djung4@kr.kpmg.com | J4: =_xlfn.XLOOKUP(K4,G:G,F:F) -> 정대주 | K4: djung4@kr.kpmg.com
B5: 고요섭(yosupgo@kr.kpmg.com) | F5: 고요섭 | G5: yosupgo@kr.kpmg.com | J5: =_xlfn.XLOOKUP(K5,G:G,F:F) -> 고요섭 | K5: yosupgo@kr.kpmg.com
B6: 김영균(yeongjyunkim@kr.kpmg.com) | F6: 김영균 | G6: yeongkyunkim@kr.kpmg.com | J6: =_xlfn.XLOOKUP(K6,G:G,F:F) -> 김영균 | K6: yeongkyunkim@kr.kpmg.com
B7: 윤종석(jongseokyoun@kr.kpmg.com) | F7: 윤종석 | G7: jongseokyoun@kr.kpmg.com | J7: =_xlfn.XLOOKUP(K7,G:G,F:F) -> 윤종석 | K7: jongseokyoun@kr.kpmg.com
B8: 이광수(kwangsulee@kr.kpmg.com) | F8: 이광수 | G8: kwangsulee@kr.kpmg.com | J8: =_xlfn.XLOOKUP(K8,G:G,F:F) -> 이광수 | K8: kwangsulee@kr.kpmg.com
B9: 이형철(hyeongcheollee@kr.kpmg.com) | F9: 이형철 | G9: hyeongcheollee@kr.kpmg.com | J9: =_xlfn.XLOOKUP(K9,G:G,F:F) -> 이형철 | K9: hyeongcheollee@kr.kpmg.com
B10: 이재근(jaekeunlee@kr.kpmg.com) | F10: 이재근 | G10: jaekeunlee@kr.kpmg.com | J10: =_xlfn.XLOOKUP(K10,G:G,F:F) -> 이재근 | K10: jaekeunlee@kr.kpmg.com
B11: 이요셉(jlee176@kr.kpmg.com) | F11: 이요셉 | G11: jlee176@kr.kpmg.com | J11: =_xlfn.XLOOKUP(K11,G:G,F:F) -> 이요셉 | K11: jlee176@kr.kpmg.com
B12: 강건국(konkukkang@kr.kpmg.com) | F12: 강건국 | G12: konkukkang@kr.kpmg.com | J12: =_xlfn.XLOOKUP(K12,G:G,F:F) -> 강건국 | K12: konkukkang@kr.kpmg.com
B13: 김찬양(ckim12@kr.kpmg.com) | F13: 김찬양 | G13: ckim12@kr.kpmg.com | J13: =_xlfn.XLOOKUP(K13,G:G,F:F) -> 김찬양 | K13: ckim12@kr.kpmg.com
B14: 최성환(seonghwanchoi@kr.kpmg.com) | F14: 최성환 | G14: seonghwanchoi@kr.kpmg.com | J14: =_xlfn.XLOOKUP(K14,G:G,F:F) -> 최성환 | K14: seonghwanchoi@kr.kpmg.com
... B121: 김기웅(kiwoongkim@kr.kpmg.com) | F121: 김기웅 | G121: kiwoongkim@kr.kpmg.com | J121: =_xlfn.XLOOKUP(K121,G:G,F:F) -> 구영모 | K121: youngmokoo@kr.kpmg.com
B122: 홍인우(inwoohong@kr.kpmg.com) | F122: 홍인우 | G122: inwoohong@kr.kpmg.com | K122: mkim175@kr.kpmg.com
B123: 홍준형(junhyunghong@kr.kpmg.com) | F123: 홍준형 | G123: junhyunghong@kr.kpmg.com | K123: hkim51@kr.kpmg.com
B124: 김정우(jkim502@kr.kpmg.com) | F124: 김정우 | G124: jkim502@kr.kpmg.com
B125: 배슬기(seulgibae@kr.kpmg.com) | F125: 배슬기 | G125: seulgibae@kr.kpmg.com
B126: 윤다산(dasanyoun@kr.kpmg.com) | F126: 윤다산 | G126: dasanyoun@kr.kpmg.com
B127: 김아정(ajungkim@kr.kpmg.com) | F127: 김아정 | G127: ajungkim@kr.kpmg.com
B128: 이진주(jinjulee@kr.kpmg.com) | F128: 이진주 | G128: jinjulee@kr.kpmg.com
B129: 민중기(joonggimin@kr.kpmg.com) | F129: 민중기 | G129: joonggimin@kr.kpmg.com
B130: 유민혁(minhyuckyoo@kr.kpmg.com) | F130: 유민혁 | G130: minhyuckyoo@kr.kpmg.com
B131: 임현재(hyunjaeim@kr.kpmg.com) | F131: 임현재 | G131: hyunjaeim@kr.kpmg.com
B132: 박상언(sangeonpark@kr.kpmg.com) | F132: 박상언 | G132: sangeonpark@kr.kpmg.com
B133: 이태윤(taeyoonlee@kr.kpmg.com) | F133: 이태윤 | G133: taeyoonlee@kr.kpmg.com
B134: 김재현(jkim508@kr.kpmg.com) | F134: 김재현 | G134: jkim508@kr.kpmg.com
B135: 최연주(yeonjoochoi@kr.kpmg.com) | F135: 최연주 | G135: yeonjoochoi@kr.kpmg.com
... B150: 우진혁(jinhyeokwoo@kr.kpmg.com) | F150: 우진혁 | G150: jinhyeokwoo@kr.kpmg.com

Sheet FY25_결과
N1: =SUBTOTAL(1,N3:N1297) -> 0.033183195 | O1: =SUBTOTAL(1,O3:O1297) -> 0.10093588 | P1: =SUBTOTAL(1,P3:P1297) -> 0.86588093 | Q1: =SUBTOTAL(1,Q3:Q1425) -> 175.08524
A2: No | B2: Timing | C2: Org Code | D2: Organizatin Name | E2: Eng Code | F2: Engagement Name | G2: Analysis Name | H2: 대상기간 | I2: GL/SL | J2: Usecase | K2: In-scope | L2: Gross activity(ABS) | M2: Total entries | N2: H % | O2: M % | P2: L % | Q2: High risk entries | R2: ₩ value in high | S2: Medium risk entries | T2: ₩ value in medium | U2: Low risk entries | V2: ₩ value in low
A3: 1 | B3: 1Q | C3: 1000316445 | D3: 에스케이하이닉스 | E3: 1668793 | F3: SK하이닉스 FY2025 외부감사 | G3: SK하이닉스 FY2025.1Q | H3: 2025-01-01 ~ 2025-03-31 | I3: General Ledger | J3: Revenue | K3: X | L3: =ABS(R3)+ABS(T3)+ABS(V3) -> 18731898038976 | M3: =Q3+S3+U3 -> 42454 | N3: =ABS(R3)/$L3 -> 0.058455673 | O3: =ABS(T3)/$L3 -> 0.07259674 | P3: =ABS(V3)/$L3 -> 0.86894759 | Q3: 16 | R3: -1094985705459 | S3: 1188 | T3: 1359874730911 | U3: 41250 | V3: 16277037602606
A4: 1 | B4: 1Q | C4: 1000316445 | D4: 에스케이하이닉스 | E4: 1668793 | F4: SK하이닉스 FY2025 외부감사 | G4: SK하이닉스 FY2025.1Q | H4: 2025-01-01 ~ 2025-03-31 | I4: General Ledger | J4: High Risk Journal Entry | K4: X | L4: =ABS(R4)+ABS(T4)+ABS(V4) -> 735541056678472 | M4: =Q4+S4+U4 -> 6821774 | N4: =ABS(R4)/$L4 -> 0.00070418678 | O4: =ABS(T4)/$L4 -> 0 | P4: =ABS(V4)/$L4 -> 0.99929581 | Q4: 8 | R4: -517958285326 | S4: 0 | T4: 0 | U4: 6821766 | V4: 735023098393146
A5: 1 | B5: 3Q | C5: 1000316445 | D5: 에스케이하이닉스 | E5: 1668793 | F5: SK하이닉스 FY2025 외부감사 | G5: FY25_SK하이닉스_3Q | H5: 2025-01-01 ~ 2025-09-30 | I5: General Ledger | J5: Revenue | K5: O | L5: =ABS(R5)+ABS(T5)+ABS(V5) -> 58928558788679 | M5: =Q5+S5+U5 -> 136054 | N5: =ABS(R5)/$L5 -> 0.0070191901 | O5: =ABS(T5)/$L5 -> 0.0052752335 | P5: =ABS(V5)/$L5 -> 0.98770558 | Q5: 59 | R5: 413630755230 | S5: 3005 | T5: 310861906784 | U5: 132990 | V5: 58204066126665
A6: 1 | B6: 3Q | C6: 1000316445 | D6: 에스케이하이닉스 | E6: 1668793 | F6: SK하이닉스 FY2025 외부감사 | G6: FY25_SK하이닉스_3Q | H6: 2025-01-01 ~ 2025-09-30 | I6: General Ledger | J6: High Risk Journal Entry | K6: X | L6: =ABS(R6)+ABS(T6)+ABS(V6) -> 2.4201226e+15 | M6: =Q6+S6+U6 -> 22060675 | N6: =ABS(R6)/$L6 -> 0.00070525664 | O6: =ABS(T6)/$L6 -> 0 | P6: =ABS(V6)/$L6 -> 0.99929474 | Q6: 61 | R6: 1706807540903 | S6: 0 | T6: 0 | U6: 22060614 | V6: 2.4184158e+15
A7: 1 | B7: 4Q | C7: 1000316445 | D7: 에스케이하이닉스 | E7: 1668793 | F7: SK하이닉스 FY2025 외부감사 | G7: 4Q_SK하이닉스 FY2025 외부감사 | H7: 2025-10-01 ~ 2025-12-31 | I7: General Ledger | J7: Revenue | K7: O | L7: =ABS(R7)+ABS(T7)+ABS(V7) -> 30523064712165 | M7: =Q7+S7+U7 -> 47376 | N7: =ABS(R7)/$L7 -> 0.00050212086 | O7: =ABS(T7)/$L7 -> 0.012238207 | P7: =ABS(V7)/$L7 -> 0.98725967 | Q7: 24 | R7: 15326267632 | S7: 1606 | T7: 373547575212 | U7: 45746 | V7: 30134190869321
A8: 1 | B8: 4Q | C8: 1000316445 | D8: 에스케이하이닉스 | E8: 1668793 | F8: SK하이닉스 FY2025 외부감사 | G8: 4Q_SK하이닉스 FY2025 외부감사 | H8: 2025-10-01 ~ 2025-12-31 | I8: General Ledger | J8: High Risk Journal Entry | K8: X | L8: =ABS(R8)+ABS(T8)+ABS(V8) -> 1.1413329e+15 | M8: =Q8+S8+U8 -> 8022593 | N8: =ABS(R8)/$L8 -> 0.017930538 | O8: =ABS(T8)/$L8 -> 0 | P8: =ABS(V8)/$L8 -> 0.98206946 | Q8: 53 | R8: 20464712708952 | S8: 0 | T8: 0 | U8: 8022540 | V8: 1.1208682e+15
A9: 2 | B9: 1Q | C9: 1000317342 | D9: Korea Electric Power Corporation | E9: 1698103 | F9: FY25_한국전력공사_외부회계감사 | G9: [DRY-RUN]KEPCO_FY2025_Q1 | H9: 2025-01-01 ~ 2025-03-31 | I9: General Ledger | J9: High Risk Journal Entry | K9: X | L9: =ABS(R9)+ABS(T9)+ABS(V9) -> 6.0741513e+15 | M9: =Q9+S9+U9 -> 32890267 | N9: =ABS(R9)/$L9 -> 0.0026727374 | O9: =ABS(T9)/$L9 -> 0 | P9: =ABS(V9)/$L9 -> 0.99732726 | Q9: 58 | R9: 16234611602693 | S9: 0 | T9: 0 | U9: 32890209 | V9: 6.0579167e+15
A10: 2 | B10: 1Q | C10: 1000317342 | D10: Korea Electric Power Corporation | E10: 1698103 | F10: FY25_한국전력공사_외부회계감사 | G10: [DRY-RUN]KEPCO_FY2025_Q1 | H10: 2025-01-01 ~ 2025-03-31 | I10: General Ledger | J10: Operating Expense | K10: X | L10: =ABS(R10)+ABS(T10)+ABS(V10) -> 63507912518644 | M10: =Q10+S10+U10 -> 40664 | N10: =ABS(R10)/$L10 -> 0.0082462063 | O10: =ABS(T10)/$L10 -> 0.96057518 | P10: =ABS(V10)/$L10 -> 0.031178611 | Q10: 361 | R10: 523699350172 | S10: 12236 | T10: 61004124673722 | U10: 28067 | V10: 1980088494750
A11: 2 | B11: 1Q | C11: 1000317342 | D11: Korea Electric Power Corporation | E11: 1698103 | F11: FY25_한국전력공사_외부회계감사 | G11: [DRY-RUN]KEPCO_FY2025_Q1 | H11: 2025-01-01 ~ 2025-03-31 | I11: General Ledger | J11: Revenue | K11: X | L11: =ABS(R11)+ABS(T11)+ABS(V11) -> 6.8886035e+15 | M11: =Q11+S11+U11 -> 34598701 | N11: =ABS(R11)/$L11 -> 0.0034901864 | O11: =ABS(T11)/$L11 -> 0 | P11: =ABS(V11)/$L11 -> 0.99650981 | Q11: 141 | R11: 24042510091003 | S11: 0 | T11: 0 | U11: 34598560 | V11: 6.864561e+15
A12: 2 | B12: 2Q | C12: 1000317342 | D12: Korea Electric Power Corporation | E12: 1698103 | F12: FY25_한국전력공사_외부회계감사 | G12: 2Q_FY25_한국전력공사_외부회계감사 | H12: 2025-01-01 ~ 2025-06-30 | I12: General Ledger | J12: High Risk Journal Entry | K12: X | L12: =ABS(R12)+ABS(T12)+ABS(V12) -> 2.9857257e+15 | M12: =Q12+S12+U12 -> 47726117 | N12: =ABS(R12)/$L12 -> 0.0030172289 | O12: =ABS(T12)/$L12 -> 0 | P12: =ABS(V12)/$L12 -> 0.99698277 | Q12: 437 | R12: 9008617940863 | S12: 0 | T12: 0 | U12: 47725680 | V12: 2.9767171e+15
A13: 2 | B13: 2Q | C13: 1000317342 | D13: Korea Electric Power Corporation | E13: 1698103 | F13: FY25_한국전력공사_외부회계감사 | G13: 2Q_FY25_한국전력공사_외부회계감사 | H13: 2025-01-01 ~ 2025-06-30 | I13: General Ledger | J13: Operating Expense | K13: O | L13: =ABS(R13)+ABS(T13)+ABS(V13) -> 3337611750987 | M13: =Q13+S13+U13 -> 4698274 | N13: =ABS(R13)/$L13 -> 0.014813582 | O13: =ABS(T13)/$L13 -> 0.18812722 | P13: =ABS(V13)/$L13 -> 0.7970592 | Q13: 98 | R13: 49441984269 | S13: 15455 | T13: 627895627295 | U13: 4682721 | V13: 2660274139423
A14: 2 | B14: 4Q | C14: 1000317342 | D14: Korea Electric Power Corporation | E14: 1698103 | F14: FY25_한국전력공사_외부회계감사 | G14: 하반기_FY25_한국전력공사_외부회계감사 | H14: 2025-07-01 ~ 2025-12-31 | I14: General Ledger | J14: High Risk Journal Entry | K14: X | L14: =ABS(R14)+ABS(T14)+ABS(V14) -> 2.5590393e+15 | M14: =Q14+S14+U14 -> 192850079 | N14: =ABS(R14)/$L14 -> 0.0033234225 | O14: =ABS(T14)/$L14 -> 0 | P14: =ABS(V14)/$L14 -> 0.99667658 | Q14: 937 | R14: 8504768925552 | S14: 0 | T14: 0 | U14: 192849142 | V14: 2.5505346e+15
A15: 2 | B15: 4Q | C15: 1000317342 | D15: Korea Electric Power Corporation | E15: 1698103 | F15: FY25_한국전력공사_외부회계감사 | G15: 하반기_FY25_한국전력공사_외부회계감사 | H15: 2025-07-01 ~ 2025-12-31 | I15: General Ledger | J15: Operating Expense | K15: O | L15: =ABS(R15)+ABS(T15)+ABS(V15) -> 9544149429634 | M15: =Q15+S15+U15 -> 7035569 | N15: =ABS(R15)/$L15 -> 0.014585842 | O15: =ABS(T15)/$L15 -> 0.065755315 | P15: =ABS(V15)/$L15 -> 0.91965884 | Q15: 261 | R15: 139209451285 | S15: 17735 | T15: 627578555159 | U15: 7017573 | V15: 8777361423190
A16: 3 | B16: 1Q | C16: 1000314674 | D16: 한국수력원자력 ㈜ | E16: 1698595 | F16: [한국수력원자력] FY2025 회계감사 | G16: [한국수력원자력] FY2025 회계감사_Q1 | H16: 2025-01-01 ~ 2025-03-31 | I16: General Ledger | J16: High Risk Journal Entry | K16: X | L16: =ABS(R16)+ABS(T16)+ABS(V16) -> 153672662547410 | M16: =Q16+S16+U16 -> 1669400 | N16: =ABS(R16)/$L16 -> 0.0024107168 | O16: =ABS(T16)/$L16 -> 0 | P16: =ABS(V16)/$L16 -> 0.99758928 | Q16: 9 | R16: 370461270058 | S16: 0 | U16: 1669391 | V16: 153302201277352
A17: 3 | B17: 1Q | C17: 1000314674 | D17: 한국수력원자력 ㈜ | E17: 1698595 | F17: [한국수력원자력] FY2025 회계감사 | G17: [한국수력원자력] FY2025 회계감사_Q1 | H17: 2025-01-01 ~ 2025-03-31 | I17: General Ledger | J17: Operating Expense | K17: X | L17: =ABS(R17)+ABS(T17)+ABS(V17) -> 2249231665688 | M17: =Q17+S17+U17 -> 183893 | N17: =ABS(R17)/$L17 -> 0.010126582 | O17: =ABS(T17)/$L17 -> 0.097811273 | P17: =ABS(V17)/$L17 -> 0.89206215 | Q17: 72 | R17: 22777028791 | S17: 2246 | T17: 220000211908 | U17: 181575 | V17: 2006454424989
A18: 3 | B18: 1Q | C18: 1000314674 | D18: 한국수력원자력 ㈜ | E18: 1698595 | F18: [한국수력원자력] FY2025 회계감사 | G18: [한국수력원자력] FY2025 회계감사_Q1 | H18: 2025-01-01 ~ 2025-03-31 | I18: General Ledger | J18: Revenue | K18: X | L18: =ABS(R18)+ABS(T18)+ABS(V18) -> 6639171315356 | M18: =Q18+S18+U18 -> 2876 | N18: =ABS(R18)/$L18 -> 0 | O18: =ABS(T18)/$L18 -> 0.1811116 | P18: =ABS(V18)/$L18 -> 0.8188884 | Q18: 0 | R18: 0 | S18: 147 | T18: -1202430949707 | U18: 2729 | V18: 5436740365649
A19: 3 | B19: 1Q | C19: 1000314674 | D19: 한국수력원자력 ㈜ | E19: 1698595 | F19: [한국수력원자력] FY2025 회계감사 | G19: [한국수력원자력] FY2025 회계감사_Q1 | H19: 2025-01-01 ~ 2025-03-31 | I19: General Ledger | J19: Revenue | K19: X | L19: =ABS(R19)+ABS(T19)+ABS(V19) -> 12377368465 | M19: =Q19+S19+U19 -> 48 | N19: =ABS(R19)/$L19 -> 0 | O19: =ABS(T19)/$L19 -> 0 | P19: =ABS(V19)/$L19 -> 1 | Q19: 0 | R19: 0 | S19: 0 | T19: 0 | U19: 48 | V19: 12377368465
A20: 4 | B20: 1Q | C20: 1000315445 | D20: 에스케이브로드밴드 주식회사 | E20: 1683891 | F20: SK브로드밴드 2025년 외부감사 | G20: SK브로드밴드 2025년 외부감사 1Q | H20: 2025-01-01 ~ 2025-03-31 | I20: General Ledger | J20: High Risk Journal Entry | K20: X | L20: =ABS(R20)+ABS(T20)+ABS(V20) -> 99682530838788 | M20: =Q20+S20+U20 -> 2259811 | N20: =ABS(R20)/$L20 -> 0.0041064263 | O20: =ABS(T20)/$L20 -> 0 | P20: =ABS(V20)/$L20 -> 0.99589357 | Q20: 28 | R20: 409338965336 | S20: 0 | T20: 0 | U20: 2259783 | V20: 99273191873452
A21: 4 | B21: 1Q | C21: 1000315445 | D21: 에스케이브로드밴드 주식회사 | E21: 1683891 | F21: SK브로드밴드 2025년 외부감사 | G21: SK브로드밴드 2025년 외부감사 1Q | H21: 2025-01-01 ~ 2025-03-31 | I21: General Ledger | J21: Operating Expense | K21: O | L21: =ABS(R21)+ABS(T21)+ABS(V21) -> 2267910146825 | M21: =Q21+S21+U21 -> 726077 | N21: =ABS(R21)/$L21 -> 0.0098967916 | O21: =ABS(T21)/$L21 -> 0.35059467 | P21: =ABS(V21)/$L21 -> 0.63950854 | Q21: 43 | R21: 22445034119 | S21: 19936 | T21: 795117209064 | U21: 706098 | V21: 1450347903642
A22: 4 | B22: 1Q | C22: 1000315445 | D22: 에스케이브로드밴드 주식회사 | E22: 1683891 | F22: SK브로드밴드 2025년 외부감사 | G22: SK브로드밴드 2025년 외부감사 1Q | H22: 2025-01-01 ~ 2025-03-31 | I22: General Ledger | J22: Revenue | K22: O | L22: =ABS(R22)+ABS(T22)+ABS(V22) -> 3690460683183 | M22: =Q22+S22+U22 -> 36739 | N22: =ABS(R22)/$L22 -> 0.40074258 | O22: =ABS(T22)/$L22 -> 0.33956858 | P22: =ABS(V22)/$L22 -> 0.25968885 | Q22: 204 | R22: 1478924719133 | S22: 5777 | T22: 1253164488980 | U22: 30758 | V22: 958371475070
A23: 4 | B23: 1Q | C23: 1000315445 | D23: 에스케이브로드밴드 주식회사 | E23: 1683891 | F23: SK브로드밴드 2025년 외부감사 | G23: SK브로드밴드 2025년 외부감사 1Q | H23: 2025-01-01 ~ 2025-03-31 | I23: General Ledger | J23: Revenue | K23: O | L23: =ABS(R23)+ABS(T23)+ABS(V23) -> 3594691519182 | M23: =Q23+S23+U23 -> 32283 | N23: =ABS(R23)/$L23 -> 0.41038111 | O23: =ABS(T23)/$L23 -> 0.33195366 | P23: =ABS(V23)/$L23 -> 0.25766523 | Q23: 195 | R23: 1475193491409 | S23: 5339 | T23: 1193271013367 | U23: 26749 | V23: 926227014406
A24: 4 | B24: 1Q | C24: 1000315445 | D24: 에스케이브로드밴드 주식회사 | E24: 1683891 | F24: SK브로드밴드 2025년 외부감사 | G24: SK브로드밴드 2025년 외부감사 1Q | H24: 2025-01-01 ~ 2025-03-31 | I24: General Ledger | J24: Revenue | K24: O | L24: =ABS(R24)+ABS(T24)+ABS(V24) -> 95769164001 | M24: =Q24+S24+U24 -> 4456 | N24: =ABS(R24)/$L24 -> 0.038960638 | O24: =ABS(T24)/$L24 -> 0.62539416 | P24: =ABS(V24)/$L24 -> 0.3356452 | Q24: 9 | R24: 3731227724 | S24: 438 | T24: 59893475613 | U24: 4009 | V24: 32144460664
A25: 4 | B25: 2Q | C25: 1000315445 | D25: 에스케이브로드밴드 주식회사 | E25: 1683891 | F25: SK브로드밴드 2025년 외부감사 | G25: SK브로드밴드 2025년 외부감사 2Q | H25: 2025-01-01 ~ 2025-06-30 | I25: General Ledger | J25: High Risk Journal Entry | K25: X | L25: =ABS(R25)+ABS(T25)+ABS(V25) -> 258715357033820 | M25: =Q25+S25+U25 -> 4410298 | N25: =ABS(R25)/$L25 -> 0.0035122348 | O25: =ABS(T25)/$L25 -> 0 | P25: =ABS(V25)/$L25 -> 0.99648777 | Q25: 59 | R25: 908669068770 | S25: 0 | T25: 0 | U25: 4410239 | V25: 257806687965050
A26: 4 | B26: 2Q | C26: 1000315445 | D26: 에스케이브로드밴드 주식회사 | E26: 1683891 | F26: SK브로드밴드 2025년 외부감사 | G26: SK브로드밴드 2025년 외부감사 2Q | H26: 2025-01-01 ~ 2025-06-30 | I26: General Ledger | J26: Revenue | K26: O | L26: =ABS(R26)+ABS(T26)+ABS(V26) -> 2418697305303 | M26: =Q26+S26+U26 -> 17951 | N26: =ABS(R26)/$L26 -> 0.0035796286 | O26: =ABS(T26)/$L26 -> 0.11739267 | P26: =ABS(V26)/$L26 -> 0.87902771 | Q26: 191 | R26: 8658038131 | S26: 903 | T26: 283937323695 | U26: 16857 | V26: 2126101943477
A27: 4 | B27: 2Q | C27: 1000315445 | D27: 에스케이브로드밴드 주식회사 | E27: 1683891 | F27: SK브로드밴드 2025년 외부감사 | G27: SK브로드밴드 2025년 외부감사 2Q | H27: 2025-01-01 ~ 2025-06-30 | I27: General Ledger | J27: Revenue | K27: O | L27: =ABS(R27)+ABS(T27)+ABS(V27) -> 255677330673 | M27: =Q27+S27+U27 -> 8611 | N27: =ABS(R27)/$L27 -> 0.031087014 | O27: =ABS(T27)/$L27 -> 0.28439033 | P27: =ABS(V27)/$L27 -> 0.68452265 | Q27: 187 | R27: 7948244758 | S27: 575 | T27: 72712160911 | U27: 7849 | V27: 175016925004
A28: 4 | B28: 4Q | C28: 1000315445 | D28: 에스케이브로드밴드 주식회사 | E28: 1683891 | F28: SK브로드밴드 2025년 외부감사 | G28: SK브로드밴드 2025년 외부감사 2Q | H28: 2025-07-01 ~ 2025-12-31 | I28: General Ledger | J28: High Risk Journal Entry | K28: X | L28: =ABS(R28)+ABS(T28)+ABS(V28) -> 245095979529562 | M28: =Q28+S28+U28 -> 4504496 | N28: =ABS(R28)/$L28 -> 0.0094325741 | O28: =ABS(T28)/$L28 -> 0 | P28: =ABS(V28)/$L28 -> 0.99056743 | Q28: 201 | R28: 2311885989641 | S28: 0 | T28: 0 | U28: 4504295 | V28: 242784093539921
... A483: 235 | B483: 4Q | C483: 1001044635 | D483: (주)비와이씨 | E483: 1683391 | F483: 주식회사 BYC FY2025 외부감사 | G483: 4Q_주식회사 BYC FY2025 외부감사 | H483: 2025-01-01 ~ 2025-12-31 | I483: General Ledger | J483: Revenue | K483: O | L483: =ABS(R483)+ABS(T483)+ABS(V483) -> 45138827854 | M483: =Q483+S483+U483 -> 44515 | N483: =ABS(R483)/$L483 -> 0 | O483: =ABS(T483)/$L483 -> 0.11081038 | P483: =ABS(V483)/$L483 -> 0.88918962 | Q483: 0 | R483: 0 | S483: 288 | T483: 5001850592 | U483: 44227 | V483: 40136977262

Sheet FY25_비용
G1: =SUM(G3:G111) -> 199500.52 | H1: =SUM(H3:H111) -> 281227170 | I1: =H1/G1 -> 1409.6563
A2: No | B2: 본부명 | C2: 계약코드 | D2: 계약명 | E2: EP | F2: EM | G2: Eng당 비용($) | H2: Eng당 비용(\)
A3: 1 | B3: ICE1 | C3: 1683199 | D3: FY2025 네이버파이낸셜 외부감사 | E3: 강상현 | F3: 김의진 | G3: 1830.28 | H3: 2580066
A4: 2 | B4: ICE1 | C4: 1683595 | D4: FY2025 스노우 외부감사 | E4: 강상현 | F4: 김부성 | G4: 1830.28 | H4: 2580066
A5: 3 | B5: IM3 | C5: 1668904 | D5: FY25 현대모비스 외부감사 | E5: 강성채 | F5: 신준희 | G5: 1830.28 | H5: 2580066
A6: 4 | B6: ICE3 | C6: 1660912 | D6: FY25_산타클로스ENT_지정감사 | E6: 강승미 | F6: 최유라 | G6: 1830.28 | H6: 2580065
A7: 5 | B7: ICE3 | C7: 1666297 | D7: KEC FY25 지정감사 | E7: 강승미 | F7: 이우현 | G7: 1830.28 | H7: 2580065
A8: 6 | B8: ICE3 | C8: 1684314 | D8: 십일번가_FY2025_외부감사 및 Group reporting | E8: 강승미 | F8: 이우현 | G8: 1830.28 | H8: 2580065
A9: 7 | B9: ICE3 | C9: 1683461 | D9: 위메이드플레이 FY25 외부감사 | E9: 강승미 | F9: 이우현 | G9: 1830.28 | H9: 2580065
A10: 8 | B10: ICE3 | C10: 1684341 | D10: FY2025 시노펙스 외부감사 | E10: 강승미 | F10: 박재영 | G10: 1830.28 | H10: 2580065
A11: 9 | B11: ICE3 | C11: 1667049 | D11: 엘앤에프 FY25 지정감사 | E11: 강인혜 | F11: 이동규 | G11: 1830.28 | H11: 2580065
A12: 10 | B12: ICE3 | C12: 1683705 | D12: SK쉴더스_외부감사_FY2025 | E12: 강인혜 | F12: 박소영 | G12: 1830.28 | H12: 2580065
A13: 11 | B13: ICE3 | C13: 1669150 | D13: SK Telecom FY25 integrated audit | E13: 강인혜 | F13: 강진제 | G13: 1830.28 | H13: 2580065
A14: 12 | B14: IM3 | C14: 1660186 | D14: FY25_앤에스(구,뉴로스)_지정감사 | E14: 강희석 | F14: 이다니엘 | G14: 1830.28 | H14: 2580066
... A111: 109 | B111: IM2 | C111: 1659469 | D111: 이수앱지스 2025년 외부감사(주기적 지정) | E111: 황현동 | F111: 임재연 | G111: 1830.28 | H111: 2580066

Sheet FY24>>>

Sheet FY24_현황
T2: =COUNTA(T6:T213) -> 9 | W2: =COUNTA(W6:W100) -> 52 | X2: =COUNTA(X6:X100) -> 50 | Y2: =COUNTA(Y6:Y100) -> 43 | Z2: =COUNTA(Z6:Z100) -> 40 | AA2: =COUNTA(AA6:AA100) -> 36 | AB2: =COUNTA(AB6:AB100) -> 31 | AC2: =COUNTA(AC6:AC100) -> 27 | AD2: =COUNTA(AD6:AD100) -> 27 | ... AF2: =COUNTA(AF6:AF100) -> 27 | AG2: =COUNTIF(AG6:AG70,"V") -> 44 | AH2: =COUNTIF(AH6:AH70,"V") -> 44 | AI2: =COUNTIF(AI6:AI70,"V") -> 39 | AJ2: =COUNTIF(AJ6:AJ70,"V") -> 40
A3: Eng 정보 | M3: Eng 인원 현황 | T3: Scoping | W3: Interim | AB3: Year-end | AG3: Cost | AJ3: 설문
AC4: 감사팀 | AE4: ITA | AF4: IAC
A5: NO | B5: 본부명 | C5: 계약코드 | D5: 계약명 | E5: 고객코드 | F5: 회사명 | G5: 법인구분 | I5: 업종-대분류 | J5: 업종-세분류 | K5: KCw Industry | L5: ERP | M5: DPP | N5: EQCR | O5: EP | P5: EM | Q5: ICA | R5: Staff | S5: Staff | T5: 전년도 참여 | U5: 변동사항 | V5: 변동사유 | W5: ORG생성여부 | X5: 최초 Interim 대상 2024-07-04 | Y5: Interim 대상(진행) 2024-09-02 | Z5: Interim 분석 수행 | AA5: Interim 대상(최종) 2025-01-15 | AB5: 기말대상여부 | AC5: STS Ticket 생성 | AD5: 데이터업로드 | AE5: 전처리/업로드 | AF5: 분석 결과 제공 | AG5: 최종비용청구 | AH5: Global 집계 | AI5: 청구단위 | AJ5: 발송 | AK5: 회신
A6: 1 | B6: ICE2 | C6: 1529846 | D6: FY24 삼성전자 외부감사 | E6: 1000314822 | F6: 삼성전자 (주) | G6: 유가증권 | H6: Enhanced | I6: 제조업 | J6: 통신 및 방송장비 제조업 | K6: Industrial Products | L6: SAP S4 HANA | M6: 김수영/손지연 | N6: 남상민 | O6: 한상현 | P6: 김지만 | Q6: 박승환 | R6: 김민석 | S6: 위현준 | T6: Y | W6: V | X6: V | Y6: V | Z6: V | AA6: V | AB6: V | AC6: V | AD6: V | AE6: V | AF6: V | AG6: =IF(OR(Z6="V",AB6="V"),"V","") -> V | AH6: V | AI6: V | AJ6: V
A7: 2 | B7: ICE1 | C7: 1527608 | D7: SK하이닉스 FY2024 외부감사 | E7: 1000316445 | F7: 에스케이하이닉스 | G7: 유가증권 | H7: Enhanced | I7: 제조업 | J7: 다이오드, 트랜지스터 및 유사 반도체소자 제조업 | K7: Industrial Products | L7: SAP S4 HANA | M7: 이현경 | N7: 변재준 | O7: 윤주헌 | P7: 김병민 | Q7: 송성화 | R7: 이하린 | S7: 강동건 | T7: Y | W7: V | X7: V | Y7: V | Z7: V | AA7: V | AB7: V | AC7: V | AD7: V | AE7: V | AF7: V | AG7: =IF(OR(Z7="V",AB7="V"),"V","") -> V | AH7: V | AI7: V | AJ7: V
A8: 3 | B8: CM2 | C8: 1528382 | D8: FY2024 롯데쇼핑 외부감사 | E8: 1000316329 | F8: 롯데쇼핑 | G8: 유가증권 | I8: 유통업 | J8: 백화점 | U8: 적용제외 | V8: 1. Bulk전표 구성 2. 마지막 감사 3. 연중에 data 입수 불가 | X8: V | AG8: =IF(OR(Z8="V",AB8="V"),"V","")
A9: 4 | B9: IM4 | C9: 1531176 | D9: 두산에너빌리티_FY2024 외부감사 | E9: 1000316406 | F9: 두산에너빌리티 | G9: 유가증권 | H9: Enhanced | I9: 제조업 | J9: 기타 기관 및 터빈 제조업 | K9: Industrial Products | L9: Oracle | M9: 노민경 | N9: 변재준 | O9: 강정구 | P9: 지현수 | Q9: 신양호 | U9: 기말 제외 요청 | V9: 효율성이 높지 않다고 판단함 | W9: V | X9: V | Y9: V | Z9: V | AA9: V | AG9: =IF(OR(Z9="V",AB9="V"),"V","") -> V | AH9: V | AI9: V | AJ9: V
A10: 5 | B10: IM3 | C10: 1526468 | D10: 기아 주식회사 2024년 외부감사 | E10: 1000317467 | F10: 기아 주식회사 | G10: 유가증권 | H10: Enhanced | I10: 제조업 | J10: 자동차제조업 | K10: Automotive | M10: 이채영 | N10: 이경석 | O10: 전현호 | P10: 최준성 | Q10: 정대주 | R10: 남태은 | S10: 이지환 | U10: 기말 제외 요청 | V10: 기중매출실재성 위험평가를 Base로 한 것에 대한 후속적인 확인 목적으로 1~9월 AITS를 활용하였으며, 1~12월 전체에 대하여 MUS 실증절차로 마무리하였다 라는 방향으로 감사계획 수립 | W10: V | X10: V | Y10: V | Z10: V | AA10: V | AG10: =IF(OR(Z10="V",AB10="V"),"V","") -> V | AH10: V | AI10: V | AJ10: V
A11: 6 | B11: IM1 | C11: 1516473 | D11: FY2024_SK네트웍스_법정감사 | E11: 1000325538 | F11: SK 네트웍스 (주) | G11: 유가증권 | H11: Enhanced | I11: 도소매업 | J11: 기타 전문 도매업 | K11: Retail | L11: SAP S4 HANA | M11: 황인영 | N11: 도정욱 | O11: 이주영 | P11: 문상웅 | Q11: 천의성 | W11: V | X11: V | Y11: V | Z11: V | AA11: V | AB11: V | AC11: V | AD11: V | AE11: V | AF11: V | AG11: =IF(OR(Z11="V",AB11="V"),"V","") -> V | AH11: V | AI11: V | AJ11: V
A12: 7 | B12: ICE1 | C12: 1511883 | D12: LG이노텍 2024년 외부감사 | E12: 1000326122 | F12: 엘지이노텍 주식회사 | G12: 유가증권 | H12: Enhanced | I12: 제조업 | J12: 전자부품 제조업 | K12: Industrial Products | L12: Oracle | M12: 김수연 | N12: 전철희 | O12: 민성진 | P12: 이한수 | Q12: 김현준 | R12: 고동우 | S12: 이희정 | U12: 제외 요청_20241211 | V12: 기말감사 일정 상의 문제 | W12: V | X12: V | Y12: V | Z12: V | AG12: =IF(OR(Z12="V",AB12="V"),"V","") -> V | AH12: V | AI12: V | AJ12: V
A13: 8 | B13: ICE2 | C13: 1517865 | D13: ENM 24년 법정감사 | E13: 1000605595 | F13: (주) 씨제이이엔엠 | G13: 코스닥 | I13: 서비스업 | J13: 텔레비전 방송업 | U13: 적용제외 | V13: 1. 담당EM이 당사보다 더 적합 eng로 교체를 희망 | X13: V | AG13: =IF(OR(Z13="V",AB13="V"),"V","")
A14: 9 | B14: IM1 | C14: 1531800 | D14: FY24 외부감사_ 한화솔루션 | E14: 1000317447 | F14: 한화솔루션(주) | G14: 유가증권 | I14: 제조업 | J14: 석유화학계 기초 화학물질 제조업 | U14: 적용제외 | V14: 1. 마지막 감사 2. 별도내 부문별 ERP가 상이 3. 연결 ICFR으로 인한 공수 증가로 부담 | X14: V | AG14: =IF(OR(Z14="V",AB14="V"),"V","")
A15: 10 | B15: CM1 | C15: 1517937 | D15: 이마트 FY24 외부감사 | E15: 1000315311 | F15: (주) 이마트 | G15: 유가증권 | I15: 도소매업 | J15: 종합 소매업 | U15: 적용제외 | V15: 1. cash to revenue SAP로 감사절차를 계획 | X15: V | AG15: =IF(OR(Z15="V",AB15="V"),"V","")
A16: 11 | B16: IM3 | C16: 1519379 | D16: 한온시스템 FY2024 외부감사 | E16: 1000325981 | F16: 한온시스템㈜ | G16: 유가증권 | I16: 제조업 | J16: 공기 조화장치 제조업 | U16: 적용제외 | V16: 1. 매출 실재성 Elevated | X16: V | AG16: =IF(OR(Z16="V",AB16="V"),"V","")
A17: 12 | B17: IGH | C17: 1527322 | D17: [SK가스] FY24 외부감사 | E17: 1000316262 | F17: 에스케이가스㈜ | G17: 유가증권 | H17: Enhanced | I17: 에너지 공급업 | J17: 기체 연료 및 관련제품 도매업 | K17: Energy and Natural Resources | L17: SAP S4 HANA | M17: 노민경 | N17: 노상호 | O17: 조승희 | P17: 최지선 | Q17: 박지선 | R17: 고영기 | S17: 한민우 | U17: 기말 제외 요청_20250212 | V17: 기말감사 일정 상의 문제 | W17: V | X17: V | Y17: V | Z17: V | AA17: V | AG17: =IF(OR(Z17="V",AB17="V"),"V","") -> V | AH17: V | AI17: V | AJ17: V
A18: 13 | B18: CM1 | C18: 1515048 | D18: FY2024 하이트진로 주식회사 외부감사 | E18: 1000326018 | F18: 하이트진로 (주) | G18: 유가증권 | H18: Enhanced | I18: 제조업 | J18: 주류제조업 | K18: Consumer Products | M18: 김수연 | N18: 정현진 | O18: 김중규 | P18: 김예현 | Q18: 강건국 | R18: 김정 | T18: Y | W18: V | X18: V | Y18: V | Z18: V | AA18: V | AB18: V | AC18: V | AD18: V | AE18: V | AF18: V | AG18: =IF(OR(Z18="V",AB18="V"),"V","") -> V | AH18: V | AI18: V | AJ18: V
A19: 14 | B19: IGH | C19: 1523946 | D19: [제일기획] FY2024 지정감사 | E19: 1000315188 | F19: (주) 제일기획 | G19: 유가증권 | H19: Enhanced | I19: 서비스업 | J19: 광고 대행업 | K19: Media | L19: SAP ECC | M19: 전혜지 | N19: 조일상 | O19: 이덕영 | P19: 박종근 | Q19: 박태선 | R19: 임영범 | S19: 정진우 | W19: V | X19: V | Y19: V | Z19: V | AA19: V | AB19: V | AC19: V | AD19: V | AE19: V | AF19: V | AG19: =IF(OR(Z19="V",AB19="V"),"V","") -> V | AH19: V | AI19: V | AJ19: V
A20: 15 | B20: IM2 | C20: 1512425 | D20: 2024년 SK이노베이션 지정감사 | E20: 1000316943 | F20: SK이노베이션(주) | G20: 유가증권 | H20: Enhanced | I20: 제조업 | J20: 석유 정제품 제조업 | K20: Energy and Natural Resources | L20: SAP S4 HANA | M20: 이동영 | N20: 노원 | O20: 이채능 | P20: 정필재 | Q20: 김준수 | R20: 최현지 | S20: 김윤 | T20: Y | W20: V | X20: V | Y20: V | Z20: V | AA20: V | AB20: V | AC20: V | AD20: V | AE20: V | AF20: V | AG20: =IF(OR(Z20="V",AB20="V"),"V","") -> V | AH20: V | AJ20: V
A21: 16 | B21: IM3 | C21: 1531294 | D21: FY24 현대로템 외부감사 | E21: 1000317454 | F21: 현대로템 주식회사 | G21: 유가증권 | I21: 제조업 | J21: 기관차 및 기타 철도차량 제조업 | U21: 적용제외 | V21: 1. 매출 진행기준 2. 비용 실재성 : Significant | X21: V | AG21: =IF(OR(Z21="V",AB21="V"),"V","")
A22: 17 | B22: ICE2 | C22: 1529567 | D22: 2024년 에스디바이오센서 외부감사 | E22: 1001143819 | F22: 에스디바이오센서(주) | G22: 유가증권 | I22: 제조업 | J22: 의료기기개발,제조 외 | K22: Healthcare | M22: 송은혜 | N22: 박성배 | O22: 김익찬 | P22: 이상현 | Q22: 정효민 | U22: 제외 요청_20241002 | V22: 코로나 이후로 기업 규모 감소 | X22: V | Y22: V | AG22: =IF(OR(Z22="V",AB22="V"),"V","")
A23: 18 | B23: IM1 | C23: 1530311 | D23: OCI주식회사 FY24 법정감사 | E23: 1001345756 | F23: 오씨아이 주식회사 | G23: 유가증권 | H23: Enhanced | I23: 제조업 | J23: 기타 기초 무기화학 물질 제조업 | K23: Industrial Products | L23: Legacy | M23: 김수영 | N23: 이채능 | O23: 나재광 | P23: 박정희 | Q23: 김도영 | R23: 이수재 | S23: 장현옥 | W23: V | X23: V | Y23: V | Z23: V | AA23: V | AB23: V | AC23: V | AD23: V | AE23: V | AF23: V | AG23: =IF(OR(Z23="V",AB23="V"),"V","") -> V | AH23: V | AI23: V | AJ23: V
A24: 19 | B24: CM1 | C24: 1528166 | D24: 현대백화점 2024년 외부감사 | E24: 1000317405 | F24: 주식회사 현대백화점 | G24: 유가증권 | H24: Enhanced | I24: 유통업 | J24: 백화점 | K24: Retail | M24: 이채영 | N24: 장현민 | O24: 신장훈 | P24: 이세현 | Q24: 김윤 | R24: 양소영 | S24: 유현석 | W24: V | X24: V | Y24: V | Z24: V | AA24: V | AB24: V | AC24: V | AD24: V | AE24: V | AF24: V | AG24: =IF(OR(Z24="V",AB24="V"),"V","") -> V | AH24: V | AI24: V | AJ24: V
A25: 20 | B25: IM2 | C25: 1527025 | D25: 2024년 KG스틸 회계감사 | E25: 1000317103 | F25: KG스틸(주) | G25: 유가증권 | I25: 제조업 | J25: 냉간 압연 및 압출 제품 제조업 | U25: 적용제외 | V25: 1. 매출 실재성 Elevated | X25: V | AG25: =IF(OR(Z25="V",AB25="V"),"V","")
A26: 21 | B26: CM2 | C26: 1519955 | D26: BGF리테일_2024외부감사 | E26: 1000811746 | F26: 비지에프리테일 | G26: 유가증권 | I26: 유통업 | J26: 체인화 편의점 | U26: 적용제외 | V26: 1. 매출 샘플수 300개로 감당가능 | X26: V | AG26: =IF(OR(Z26="V",AB26="V"),"V","")
A27: 22 | B27: IM2 | C27: 1514244 | D27: 아세아시멘트 2024년 회계감사 | E27: 1000953509 | F27: 아세아시멘트(주) | G27: 유가증권 | H27: Enhanced | I27: 제조업 | J27: 시멘트 제조업 | K27: Industrial Products | L27: Legacy | M27: 황인영 | N27: 김연정 | O27: 정양기 | P27: 배기웅 | Q27: 이창우 | R27: 황준현 | S27: 이수정(slee307) | W27: V | X27: V | Y27: V | Z27: V | AA27: V | AB27: V | AC27: V | AD27: V | AE27: V | AF27: V | AG27: =IF(OR(Z27="V",AB27="V"),"V","") -> V | AH27: V | AI27: V | AJ27: V
A28: 23 | B28: ICE2 | C28: 1546791 | D28: FY2024 씨제이프레시웨이 외부감사 | E28: 1000326195 | F28: 씨제이프레시웨이 주식회사 | G28: 코스닥 | H28: Enhanced | I28: 도소매업 | J28: 가공식품 도매업 | K28: Retail | M28: 김수영 | N28: 최진석 | O28: 김정기 | P28: 정지훈 | Q28: 강동민 | R28: 오움남 | S28: 이은영 | T28: Y | W28: V | X28: V | Y28: V | Z28: V | AA28: V | AB28: V | AC28: V | AD28: V | AE28: V | AF28: V | AG28: =IF(OR(Z28="V",AB28="V"),"V","") -> V | AH28: V | AI28: V | AJ28: V
A29: 24 | B29: IM1 | C29: 1522493 | D29: FY24_보령 법정감사 | E29: 1000326228 | F29: 보령 | G29: 유가증권 | H29: Enhanced | I29: 제조업 | J29: 의약품 제조업 | K29: Healthcare | M29: 전혜지 | N29: 조승희 | O29: 박상훈 | P29: 성준희 | Q29: 임혁순 | W29: V | X29: V | Y29: V | Z29: V | AA29: V | AB29: V | AG29: =IF(OR(Z29="V",AB29="V"),"V","") -> V | AH29: V | AI29: V | AJ29: V
A30: 25 | B30: IM2 | C30: 1514071 | D30: E1 FY24 외부감사(주기적지정) | E30: 1000325863 | F30: 주식회사 E1 | G30: 유가증권 | H30: Enhanced | I30: 도소매업 | J30: 기체 연료 및 관련제품 도매업 | K30: Energy and Natural Resources | L30: SAP S4 HANA | M30: 노민경 | N30: 지동현 | O30: 조화수 | P30: 주예솔 | Q30: 김영일 | W30: V | X30: V | Y30: V | Z30: V | AA30: V | AB30: V | AC30: V | AD30: V | AE30: V | AF30: V | AG30: =IF(OR(Z30="V",AB30="V"),"V","") -> V | AH30: V | AI30: V | AJ30: V
A31: 26 | B31: IM4 | C31: 1547353 | D31: [대성산업] FY2024 외부감사 | E31: 1000314474 | F31: 대성산업 | G31: 유가증권 | I31: 도소매업 | J31: 연료 소매업 | K31: Energy and Natural Resources | M31: 전혜지 | N31: 임근구 | O31: 이경석 | P31: 서세훈 | Q31: 장혁준 | U31: 제외 요청_20241002 | V31: 1. 샘플수 많지 않음(30건) | X31: V | Y31: V | AG31: =IF(OR(Z31="V",AB31="V"),"V","")
A32: 27 | B32: IM4 | C32: 1513980 | D32: 팜스코 - FY24 외부감사 | E32: 1000317490 | F32: (주) 팜스코 | G32: 유가증권 | H32: Enhanced | I32: 제조업 | J32: 곡물가공품, 전분 및 전분제품 제조업 | K32: Consumer Products | L32: Oracle | M32: 전혜지 | N32: 박정수 | O32: 김도현 | P32: 박재훈 | Q32: 이태섭 | R32: 박태규 | S32: 류동수 | U32: 제외 요청_20241217 | V32: 매출 실재성 Elevated | W32: V | X32: V | Y32: V | Z32: V | AG32: =IF(OR(Z32="V",AB32="V"),"V","") -> V | AH32: V | AI32: V | AJ32: V
A33: 28 | B33: IGH | C33: 1550289 | D33: [동양] FY2024 외부감사 | E33: 1000501994 | F33: 주식회사 동양 | G33: 유가증권 | H33: Enhanced | I33: 제조업 | J33: 레미콘 제조업 | K33: Industrial Products | M33: 노민경 | N33: 김재연 | O33: 박상옥 | P33: 이재성 | Q33: 이경훈 | R33: 정지현 | S33: 김현진 | W33: V | X33: V | Y33: V | Z33: V | AA33: V | AG33: =IF(OR(Z33="V",AB33="V"),"V","") -> V | AH33: V | AI33: V | AJ33: V
A34: 29 | B34: CM1 | C34: 1514621 | D34: 한섬_2024년 외부감사 | E34: 1000315256 | F34: 한섬 | G34: 유가증권 | H34: Enhanced | I34: 제조업 | J34: 여자용 겉옷 제조업 | K34: Consumer Products | M34: 노민경 | N34: 도정욱 | O34: 조일상 | P34: 김주형 | Q34: 오서영 | R34: 신은경 | S34: 이민성 | W34: V | X34: V | Y34: V | Z34: V | AA34: V | AB34: V | AC34: V | AD34: V | AE34: V | AF34: V | AG34: =IF(OR(Z34="V",AB34="V"),"V","") -> V | AH34: V | AI34: V | AJ34: V
A35: 30 | B35: IM2 | C35: 1514486 | D35: 2024년 세아제강 회계감사 | E35: 1001215348 | F35: 주식회사 세아제강 | G35: 유가증권 | H35: Enhanced | I35: 제조업 | J35: 철강관 제조업 | K35: Industrial Products | L35: SAP S4 HANA | M35: 김미희 | N35: 박상옥 | O35: 정양기 | P35: 배기웅 | Q35: 이동준 | R35: 성기찬 | S35: 이승현 | W35: V | X35: V | Y35: V | Z35: V | AA35: V | AB35: V | AC35: V | AD35: V | AE35: V | AF35: V | AG35: =IF(OR(Z35="V",AB35="V"),"V","") -> V | AH35: V | AI35: V | AJ35: V
A36: 31 | B36: CM2 | C36: 1536028 | D36: 더블유씨피_외부감사_FY24 | E36: 1000734708 | F36: 더블유씨피 주식회사 | G36: 코스닥 | H36: Enhanced | I36: 제조업 | J36: 축전지 제조업 | K36: Industrial Products | M36: 김수영 | N36: 현윤호 | O36: 정창길 | P36: 김성욱 | Q36: 김종수 | W36: V | X36: V | Y36: V | Z36: V | AA36: V | AG36: =IF(OR(Z36="V",AB36="V"),"V","") -> V | AH36: V | AI36: V | AJ36: V
A37: 32 | B37: CM2 | C37: 1515113 | D37: 남해화학 FY2024 외부감사 | E37: 1000326244 | F37: 남해화학 | G37: 유가증권 | H37: Enhanced | I37: 제조업 | J37: 복합비료 및 기타 화학비료 제조업 | K37: Industrial Products | L37: SAP S4 HANA | M37: 이동영 | N37: 황구철 | O37: 이종우 | P37: 송규원 | Q37: 박재범 | R37: 곽혜진 | S37: 송지환 | W37: V | X37: V | Y37: V | Z37: V | AA37: V | AB37: V | AC37: V | AD37: V | AE37: V | AF37: V | AG37: =IF(OR(Z37="V",AB37="V"),"V","") -> V | AH37: V | AI37: V | AJ37: V
A38: 33 | B38: IGH | C38: 1527570 | D38: [한독] FY2024 지정감사 | E38: 1000316823 | F38: (주)한독 | G38: 유가증권 | H38: Enhanced | I38: 제조업 | J38: 완제 의약품 제조업 | K38: Healthcare | L38: SAP S4 HANA | M38: 정주희 | N38: 김시우 | O38: 임근구 | P38: 김주인 | Q38: 박경호 | U38: 기말 제외 요청 | V38: 기말 샘플링이 간편하다고 판단하여 AITS 김말에는 미적용 | W38: V | X38: V | Y38: V | Z38: V | AA38: V | AG38: =IF(OR(Z38="V",AB38="V"),"V","") -> V | AH38: V | AI38: V | AJ38: V
A39: 34 | B39: CM1 | C39: 1518174 | D39: 현대리바트 2024년 외부감사(지정) | E39: 1001161053 | F39: (주)현대리바트 | G39: 유가증권 | I39: 제조업 | J39: 제조업 | U39: 적용제외 | X39: V | AG39: =IF(OR(Z39="V",AB39="V"),"V","")
A40: 35 | B40: IM3 | C40: 1522049 | D40: FY24_대웅제약_외부감사(주기적지정) | E40: 1000315000 | F40: (주)대웅제약 | G40: 유가증권 | I40: 제조업 | J40: 의약품 제조업 | U40: 적용제외 | V40: 1. 매출 실재성 Elevated 또는 Siginificant | X40: V | AG40: =IF(OR(Z40="V",AB40="V"),"V","")
A41: 36 | B41: ICE1 | C41: 1511896 | D41: FY2024_외부감사_파트론 | E41: 1000323554 | F41: 주식회사 파트론 | G41: 코스닥 | H41: Enhanced | I41: 제조업 | J41: 제조업 | K41: Industrial Products | L41: Legacy | M41: 황인영 | N41: 한상현 | O41: 윤주헌 | P41: 이한수 | Q41: 정주연 | R41: 이희정 | U41: 제외 요청_20241216 | V41: 거래가 복잡하여 감사팀에서 직접 Sampling | W41: V | X41: V | Y41: V | Z41: V | AG41: =IF(OR(Z41="V",AB41="V"),"V","") -> V | AH41: V | AI41: V | AJ41: V
A42: 37 | B42: IGH | C42: 1547363 | D42: [지누스]2024년 외부감사 | E42: 1000682279 | F42: 지누스 | G42: 유가증권 | H42: Enhanced | I42: 도소매업 | J42: 상품 종합 도매업 | K42: Retail | L42: SAP ECC | M42: 이동영 | N42: 박관종 | O42: 이덕영 | P42: 정용욱 | Q42: 천지연 | W42: V | X42: V | Y42: V | Z42: V | AA42: V | AB42: V | AG42: =IF(OR(Z42="V",AB42="V"),"V","") -> V | AH42: V | AJ42: X
A43: 38 | B43: IGH | C43: 1545810 | D43: [한화갤러리아] FY2024 외부감사 | E43: 1001330099 | F43: 한화갤러리아 (주) | G43: 유가증권 | H43: Enhanced | I43: 서비스 및 도소매업 | J43: 백화점 | K43: Retail | M43: 송은혜 | N43: 조일상 | O43: 엄준식 | P43: 노영일 | Q43: 오재연 | R43: 김민경 | S43: 황진서 | W43: V | X43: V | Y43: V | AA43: V | AB43: V | AC43: V | AD43: V | AE43: V | AF43: V | AG43: =IF(OR(Z43="V",AB43="V"),"V","") -> V | AH43: V | AI43: V | AJ43: X
A44: 39 | B44: CM1 | C44: 1516793 | D44: 동원F&B 외부감사_FY2024 | E44: 1000317517 | F44: (주)동원에프엔비 | G44: 유가증권 | H44: Enhanced | I44: 제조업 | J44: 기타식품제조업 | K44: Consumer Products | L44: SAP ECC | M44: 송은혜 | N44: 도정욱 | O44: 박정수 | P44: 손진영 | Q44: 최연주 | R44: 김석영 | T44: Y | W44: V | X44: V | Y44: V | Z44: V | AA44: V | AB44: V | AC44: V | AD44: V | AE44: V | AF44: V | AG44: =IF(OR(Z44="V",AB44="V"),"V","") -> V | AH44: V | AI44: V | AJ44: V
A45: 40 | B45: ICE1 | C45: 1545633 | D45: 에이치엘비_외부감사_FY24 | E45: 1000314979 | F45: 에이치엘비 | G45: 코스닥 | I45: 제조업 | J45: 의료용품 및 기타 의약 관련제품 제조업 | U45: 적용제외 | V45: 1. 기존 MUS 예상 샘플 3건(연환산) | X45: V | AG45: =IF(OR(Z45="V",AB45="V"),"V","")
A46: 41 | B46: IM1 | C46: 1529786 | D46: FY2024_에코프로비엠_법정감사 | E46: 1000676800 | F46: 에코프로비엠 | G46: 코스닥 | H46: Enhanced | I46: 제조업 | J46: 축전지 제조업 | K46: Industrial Products | L46: SAP S4 HANA | M46: 전혜지 | N46: 전현호 | O46: 이주영 | P46: 문상웅 | Q46: 이호재 | U46: 기말 제외 요청 | V46: 기말 미사용 | W46: V | X46: V | Y46: V | Z46: V | AA46: V | AG46: =IF(OR(Z46="V",AB46="V"),"V","") -> V | AH46: V | AI46: V | AJ46: V
A47: 42 | B47: IM4 | C47: 1548549 | D47: FY24_성일하이텍_외부감사 | E47: 1000772068 | F47: 성일하이텍 (주) | G47: 코스닥 | H47: Enhanced | I47: 제조업 | J47: 제조업 | K47: Industrial Products | M47: 김수연 | N47: 최세홍 | O47: 이정수 | P47: 김현기 | Q47: 정준성 | R47: 이수민 | W47: V | X47: V | Y47: V | Z47: V | AA47: V | AB47: V | AG47: =IF(OR(Z47="V",AB47="V"),"V","") -> V | AH47: V | AI47: V | AJ47: V
A48: 43 | B48: IM4 | C48: 1548319 | D48: FY24 STX 외부감사 | E48: 1000314686 | F48: STX | G48: 유가증권 | H48: Enhanced | I48: 도소매업 | J48: 상품종합도매 | K48: Retail | M48: 이현경 | N48: 최연석 | O48: 전태웅 | P48: 서세훈 | Q48: 이승호 | R48: 박주원 | W48: V | X48: V | Y48: V | Z48: V | AA48: V | AB48: V | AC48: V | AD48: V | AE48: V | AF48: V | AG48: =IF(OR(Z48="V",AB48="V"),"V","") -> V | AH48: V | AI48: V | AJ48: V
A49: 44 | B49: IM2 | C49: 1550023 | D49: FY2024_삼표시멘트_회계감사 | E49: 1000682277 | F49: 삼표시멘트 | G49: 코스닥 | H49: Enhanced | I49: 제조업 | J49: 기타 비금속 광물제품 제조업 | K49: Industrial Products | M49: 이채영 | N49: 신동준 | O49: 남상민 | P49: 김은석 | Q49: 김경오 | R49: 홍재필 | S49: 최영수 | W49: V | X49: V | Y49: V | Z49: V | AA49: V | AB49: V | AG49: =IF(OR(Z49="V",AB49="V"),"V","") -> V | AH49: V | AI49: V | AJ49: V
A50: 45 | B50: ICE2 | C50: 1546794 | D50: FY2024 해성디에스 외부감사 | E50: 1000315676 | F50: 해성디에스(주) | G50: 유가증권 | H50: Enhanced | I50: 제조업 | J50: 전자부품 제조업 | K50: Industrial Products | M50: 김미희 | N50: 윤주헌 | O50: 염승훈 | P50: 정지훈 | Q50: 이동찬 | R50: 황현인 | S50: 김민국 | W50: V | X50: V | Y50: V | Z50: V | AA50: V | AB50: V | AC50: V | AD50: V | AE50: V | AF50: V | AG50: =IF(OR(Z50="V",AB50="V"),"V","") -> V | AH50: V | AI50: V | AJ50: V
A51: 46 | B51: IM1 | C51: 1548415 | D51: 2024 SK에너지 외부감사 | E51: 1000325286 | F51: SK에너지 | G51: 대형비상장 | H51: Enhanced | I51: 제조업 | J51: 석유 정제품 제조업 | K51: Energy and Natural Resources | M51: 전혜지 | N51: 강성채 | O51: 변상현 | P51: 이민규 | Q51: 탁현우 | R51: 김민준 | W51: V | X51: V | Y51: V | Z51: V | AA51: V | AB51: V | AC51: V | AD51: V | AE51: V | AF51: V | AG51: =IF(OR(Z51="V",AB51="V"),"V","") -> V | AH51: V | AJ51: V
A52: 47 | B52: ICE3 | C52: 1545760 | D52: FY24_삼성디스플레이_외부감사 | E52: 1000325445 | F52: 삼성디스플레이 | G52: 대형비상장 | H52: Enhanced | I52: 제조업 | J52: 액정 표시장치 제조업 | K52: Industrial Products | M52: N/A | N52: 최진석 | O52: 설유진 | P52: 장진 | Q52: 윤종석 | R52: 이은상 | T52: Y | W52: V | X52: V | Y52: V | AA52: V | AB52: V | AC52: V | AD52: V | AE52: V | AF52: V | AG52: =IF(OR(Z52="V",AB52="V"),"V","") -> V | AH52: V | AJ52: V
A53: 48 | B53: ICE3 | C53: 1546464 | D53: FY24 카카오모빌리티 외부감사 | E53: 1000851251 | F53: 카카오모빌리티 | G53: 대형비상장 | I53: 서비스업 | J53: 그 외 기타 정보 서비스업 | K53: Services | M53: N/A | N53: 민성진 | O53: 강상현 | P53: 김의진 | Q53: 정병열 | U53: 제외 요청_20241008 | V53: 샘플수 많지 않음 | W53: V | X53: V | Y53: V | AG53: =IF(OR(Z53="V",AB53="V"),"V","")
A54: 49 | B54: B&F2 | C54: 1533193 | D54: 키움예스저축은행 외부감사 FY24 | E54: 1000709046 | F54: 주식회사 키움예스저축은행 | G54: 외감 | H54: Enhanced | I54: 금융업 | J54: 상호저축은행업 | K54: Banking | L54: Legacy | M54: N/A | N54: 신대철 | O54: 임수빈 | P54: 이세연 | Q54: 이다정 | U54: 부적합 제외 | V54: 금융회사 매출통제 적용 불가 | W54: V | X54: V | Y54: V | Z54: V | AG54: =IF(OR(Z54="V",AB54="V"),"V","") -> V | AH54: V | AI54: V | AJ54: V
A55: 50 | B55: B&F3 | C55: 1527656 | D55: 한화저축은행 FY2024 외부감사 | E55: 1000764277 | F55: (주)한화저축은행 | G55: 외감 | H55: Enhanced | I55: 금융업 | J55: 상호저축은행 | K55: Banking | M55: N/A | N55: 복정수 | O55: 김종석 | P55: 유성일 | Q55: 장지예 | R55: 정종훈 | S55: 손유덕 | W55: V | X55: V | Y55: V | Z55: V | AA55: V | AB55: V | AC55: V | AD55: V | AE55: V | AF55: V | AG55: =IF(OR(Z55="V",AB55="V"),"V","") -> V | AH55: V | AI55: V | AJ55: V
A56: 51 | B56: CM2 | C56: 1545490 | D56: FY2024 BYC 외부감사 | E56: 1001044635 | F56: (주)BYC | G56: 유가증권 | H56: Enhanced | I56: 제조업 | J56: 속옷 및 잠옷 제조업 | K56: Consumer Products | M56: 노민경 | N56: 황구철 | O56: 이종우 | P56: 마진영 | Q56: 박진숙 | R56: 김호용 | S56: 김건희 | U56: 추가 신청 | W56: V | Y56: V | Z56: V | AA56: V | AB56: V | AC56: V | AD56: V | AE56: V | AF56: V | AG56: =IF(OR(Z56="V",AB56="V"),"V","") -> V | AH56: V | AI56: V | AJ56: V
A57: 52 | B57: ICE2 | C57: 1550076 | D57: 2024년 케이씨 외부감사 | E57: 1000317541 | F57: (주)케이씨 | G57: 유가증권 | H57: Enhanced | I57: 제조업 | J57: 산업처리공정 제어장비 제조업 | K57: Industrial Products | M57: 김미희 | N57: 강승미 | O57: 최연택 | P57: 강영호 | Q57: 정진우 | R57: 박강준 | S57: 강동준 | T57: Y | U57: 추가 신청 | W57: V | Y57: V | Z57: V | AA57: V | AB57: V | AC57: V | AD57: V | AE57: V | AF57: V | AG57: =IF(OR(Z57="V",AB57="V"),"V","") -> V | AH57: V | AI57: V | AJ57: X
A58: 53 | B58: CM1 | C58: 1545702 | D58: FY24 원일특강 외부감사 | E58: 1000810369 | F58: 주식회사 원일특강 | G58: 코스닥 | H58: Enhanced | I58: 제조업 | J58: 철강선 제조업 | K58: Industrial Products | L58: SAP ECC | M58: 손지연 | N58: 도정욱 | O58: 박관종 | P58: 김예현 | Q58: 최윤정 | R58: 류종헌 | U58: 제외 요청_20241205 | V58: 1. AITS 담당자 측에 제출한 자료는 상반기 분개장으로, 분개장 내 매출전표들이 모두 High/Medium/Low로 누락없이 평가되었으며, 추가감사절차가 요구되지 않는 Low 항목을 제외한 금액은 약 733억으로, 733억에 해당하는 매출전표에 대해서만 MUS를 수행하기로 결정함. (모집단 금액이 절반 이하로 감소) 2. 다만, MUS에 사용될 모집단 파일이 분개장 중 매출전표인데, 매출전표 각 건이 여러 납품건의 합계로 구성되어 있어 샘플 하나당 여러 개의 증빙을 확인해야 하고, 거액의 음수전표가 다량이 포함되어 있음. 실질적인 샘플 수 감소 효과가 없어짐. 3. 따라서 MUS를 수행하기 위해 매출원장을 사용하는 것은 효율성 측면에서 타당하지 않다고 판단하였고, 거래명세서와 정확히 일대일로 대응되는 납품리스트를 별도로 수령하여 MUS를 수행하기로 결정함. 4. 다만 회사 실무상 H/M로 평가된 733억원어치의 매출분개장 리스트와 납품리스트를 정확히 대응할 수 없음. 즉, MUS 수행 대상 모집단을 매출분개장이 아닌 납품리스트로 선정한다면 Low 항목을 포함한 반기매출 전체에 해당하는 납품리스트가 모집단이 되어야 함. 5. 당기 CAR가 S에서 B로 하향되었고, 3분기 납품리스트를 가공하여 MUS를 수행한 결과 54개의 샘플만이 추출되었고, 연환산시 72개로 전기 대비 샘플 수가 크게 감소함(80% 이상) 6. 이에 따라 AITS를 통한 샘플링을 수행하지 않고, 전기와 동일한 자료와 동일한 방식을 사용하되, 모집단 가공절차만을 추가로 수행하기로 결정함. | W58: V | Y58: V | Z58: V | AG58: =IF(OR(Z58="V",AB58="V"),"V","") -> V | AH58: V | AI58: V | AJ58: V
A59: 54 | B59: ICE2 | C59: 1545607 | D59: 씨제이올리브영 외부감사_FY24 | E59: 1001067392 | F59: 씨제이올리브영 주식회사 | G59: 대형비상장 | H59: Enhanced | I59: 도소매업 | J59: 소매업 | K59: Retail | M59: N/A | N59: 김중규 | O59: 김원석 | P59: 김진영 | Q59: 이경민 | R59: 이정민 | U59: 부적합 제외 | V59: AITs 결과 H&M 75% 초과 | W59: V | Y59: V | Z59: V | AG59: =IF(OR(Z59="V",AB59="V"),"V","") -> V | AH59: V | AJ59: X
A60: 55 | B60: CM1 | C60: 1544619 | D60: 티케이지휴켐스 외부감사 FY24 | E60: 1000316632 | F60: 티케이지휴켐스㈜ | G60: 유가증권 | H60: Enhanced | I60: 제조업 | J60: 바이오 연료 및 혼합물 제조업 | K60: Industrial Products | M60: 손지연 | N60: 권영찬 | O60: 박관종 | P60: 손진영 | Q60: 이종현 | R60: 심지연 | T60: Y | U60: 추가 신청_240909 | W60: V | Z60: V | AA60: V | AB60: V | AC60: V | AD60: V | AE60: V | AF60: V | AG60: =IF(OR(Z60="V",AB60="V"),"V","") -> V | AH60: V | AI60: V | AJ60: V
A61: 56 | B61: IM2 | C61: 1527025 | D61: 2024년 KG스틸 회계감사 | E61: 1000317103 | F61: KG스틸(주) | G61: 유가증권 | H61: Enhanced | I61: 제조업 | J61: 냉간 압연 및 압출 제품 제조업 | K61: Industrial Products | M61: 노민경 | N61: 이경석 | O61: 노상호 | P61: 한정희 | Q61: 박보람 | R61: 최제형 | U61: 추가 신청_240911 | W61: V | Z61: V | AA61: V | AB61: V | AC61: V | AD61: V | AE61: V | AF61: V | AG61: =IF(OR(Z61="V",AB61="V"),"V","") -> V | AH61: V | AI61: V | AJ61: V
A62: 57 | B62: CM2 | C62: 1546066 | D62: 니프코코리아 FY24 회계감사 | E62: 1000316316 | F62: 니프코코리아 | H62: Enhanced | J62: 제조업(기계장비,조립용플라스틱) | O62: 조한얼 | P62: 이치백 | Q62: 김지훈 | R62: 이동준 | U62: 추가 신청_250210 | V62: ITA에서 ORG생성 | W62: V | AB62: V | AC62: V | AD62: V | AE62: V | AF62: V | AG62: =IF(OR(Z62="V",AB62="V"),"V","") -> V | AH62: V | AI62: V | AJ62: V
A63: 58 | B63: CM1 | C63: 1544627 | D63: (주)동원홈푸드 외부감사_FY24 | E63: 1000317622 | F63: 동원홈푸드 | J63: 기타 식품 첨가물 제조업 | O63: 박정수 | P63: 손진영 | Q63: 최연주 | R63: 유홍재 | U63: 추가 신청_250210 | V63: ITA에서 ORG생성 | W63: V | AB63: V | AC63: V | AD63: V | AE63: V | AF63: V | AG63: =IF(OR(Z63="V",AB63="V"),"V","") -> V | AH63: V | AJ63: V
D64: 화신 | F64: 화신 | W64: V | AG64: =IF(OR(Z64="V",AB64="V"),"V","") | AI64: V
D65: Placeholder07 | W65: V | AG65: =IF(OR(Z65="V",AB65="V"),"V","")
D66: Placeholder06 | W66: V | AG66: =IF(OR(Z66="V",AB66="V"),"V","")
D67: Placeholder05 | W67: V | AG67: =IF(OR(Z67="V",AB67="V"),"V","")
D68: Placeholder04 | W68: V | AG68: =IF(OR(Z68="V",AB68="V"),"V","")
D69: Placeholder03 | W69: V | AG69: =IF(OR(Z69="V",AB69="V"),"V","")
D70: Placeholder02 | W70: V | AG70: =IF(OR(Z70="V",AB70="V"),"V","")

Sheet FY24_결과
L1: =SUBTOTAL(1,L3:L1072) -> 2.183194e+14 | M1: =SUBTOTAL(1,M3:M1072) -> 6356058.9 | N1: =SUBTOTAL(1,N3:N1072) -> 0.039362492 | O1: =SUBTOTAL(1,O3:O1072) -> 0.17686232 | P1: =SUBTOTAL(1,P3:P1072) -> 0.78377519
B2: No | C2: Timing | D2: 최종 | E2: Org Code | F2: Organizatin Name | G2: Engagement Name | H2: Analysis Name | I2: 대상기간 | J2: Usecase | K2: In-scope | L2: Gross activity | M2: Total entries | N2: H % | O2: M % | P2: L % | Q2: High risk entries | R2: ₩ value in high | S2: Medium risk entries | T2: ₩ value in medium | U2: Low risk entries | V2: ₩ value in low | W2: 비고
B3: 1 | C3: Interim | D3: O | E3: 1000314822 | F3: 삼성전자 ㈜ | G3: FY2024 3Q 삼성전자DX v2 | H3: FY2024 1Q 삼성전자DX v2 | I3: 2024-01-01 ~ 2024-03-31 | J3: High Risk Journal Entry | K3: X | L3: =R3+T3+V3 -> 6.0741513e+15 | M3: =Q3+S3+U3 -> 32890267 | N3: =R3/$L3 -> 0.0026727374 | O3: =T3/$L3 -> 0 | P3: =V3/$L3 -> 0.99732726 | Q3: 58 | R3: 16234611602693 | S3: 0 | T3: 0 | U3: 32890209 | V3: 6.0579167e+15
B4: 1 | C4: Interim | D4: O | E4: 1000314822 | F4: 삼성전자 ㈜ | G4: FY2024 3Q 삼성전자DX v2 | H4: FY2024 1Q 삼성전자DX v2 | I4: 2024-01-01 ~ 2024-03-31 | J4: Operating Expense | K4: O | L4: =R4+T4+V4 -> 63507912518644 | M4: =Q4+S4+U4 -> 40664 | N4: =R4/$L4 -> 0.0082462063 | O4: =T4/$L4 -> 0.96057518 | P4: =V4/$L4 -> 0.031178611 | Q4: 361 | R4: 523699350172 | S4: 12236 | T4: 61004124673722 | U4: 28067 | V4: 1980088494750
B5: 1 | C5: Interim | D5: X | E5: 1000314822 | F5: 삼성전자 ㈜ | G5: FY2024 3Q 삼성전자DX v2 | H5: FY2024 1Q 삼성전자DX v2 | I5: 2024-01-01 ~ 2024-03-31 | J5: Revenue | K5: O | L5: =R5+T5+V5 -> 42397203703949 | M5: =Q5+S5+U5 -> 1739454 | N5: =R5/$L5 -> 0.10273341 | O5: =T5/$L5 -> 0.029147672 | P5: =V5/$L5 -> 0.86811891 | Q5: 444 | R5: 4355609470531 | S5: 712 | T5: 1235779775689 | U5: 1738298 | V5: 36805814457729
B6: 1 | C6: Interim | D6: O | E6: 1000314822 | F6: 삼성전자 ㈜ | G6: FY2024 3Q 삼성전자DX v2 | H6: FY2024 2Q 삼성전자DX v2 | I6: 2024-04-01 ~ 2024-06-30 | J6: High Risk Journal Entry | K6: X | L6: =R6+T6+V6 -> 6.8886035e+15 | M6: =Q6+S6+U6 -> 34598701 | N6: =R6/$L6 -> 0.0034901864 | O6: =T6/$L6 -> 0 | P6: =V6/$L6 -> 0.99650981 | Q6: 141 | R6: 24042510091003 | S6: 0 | T6: 0 | U6: 34598560 | V6: 6.864561e+15
B7: 1 | C7: Interim | D7: O | E7: 1000314822 | F7: 삼성전자 ㈜ | G7: FY2024 3Q 삼성전자DX v2 | H7: FY2024 2Q 삼성전자DX v2 | I7: 2024-04-01 ~ 2024-06-30 | J7: Operating Expense | K7: O | L7: =R7+T7+V7 -> 3180736834948 | M7: =Q7+S7+U7 -> 42350 | N7: =R7/$L7 -> 0.058285778 | O7: =T7/$L7 -> 0.46423787 | P7: =V7/$L7 -> 0.47747636 | Q7: 386 | R7: 185391719919 | S7: 14695 | T7: 1476618482950 | U7: 27269 | V7: 1518726632079
B8: 1 | C8: Interim | D8: O | E8: 1000314822 | F8: 삼성전자 ㈜ | G8: FY2024 3Q 삼성전자DX v2 | H8: FY2024 2Q 삼성전자DX v2 | I8: 2024-04-01 ~ 2024-06-30 | J8: Revenue | K8: X | L8: =R8+T8+V8 -> 74148957714347 | M8: =Q8+S8+U8 -> 1846026 | N8: =R8/$L8 -> 0.054923191 | O8: =T8/$L8 -> 0.50818472 | P8: =V8/$L8 -> 0.43689209 | Q8: 269 | R8: 4072497347503 | S8: 1553 | T8: 37681367215512 | U8: 1844204 | V8: 32395093151332 | W8: Medium 51% 중 48%가 재무제표에 영향을 미치지 않는 매출/매출 상계전표 4건. 해당 전표 유형 소명 시 특이사항 없음
B9: 1 | C9: Interim | D9: O | E9: 1000314822 | F9: 삼성전자 ㈜ | G9: FY2024 3Q 삼성전자DX v2 | H9: FY2024 3Q 삼성전자DX v2 | I9: 2024-07-01 ~ 2024-09-30 | J9: High Risk Journal Entry | K9: X | L9: =R9+T9+V9 -> 6.0550242e+15 | M9: =Q9+S9+U9 -> 35976661 | N9: =R9/$L9 -> 0.00049098483 | O9: =T9/$L9 -> 0 | P9: =V9/$L9 -> 0.99950902 | Q9: 516 | R9: 2972925015969 | S9: 0 | T9: 0 | U9: 35976145 | V9: 6.0520513e+15
B10: 1 | C10: Interim | D10: O | E10: 1000314822 | F10: 삼성전자 ㈜ | G10: FY2024 3Q 삼성전자DX v2 | H10: FY2024 3Q 삼성전자DX v2 | I10: 2024-07-01 ~ 2024-09-30 | J10: Operating Expense | K10: O | L10: =R10+T10+V10 -> 3352891667207 | M10: =Q10+S10+U10 -> 43742 | N10: =R10/$L10 -> 0.058960678 | O10: =T10/$L10 -> 0.407074 | P10: =V10/$L10 -> 0.53396532 | Q10: 462 | R10: 197688766994 | S10: 13011 | T10: 1364875029362 | U10: 30269 | V10: 1790327870851
B11: 1 | C11: Interim | D11: X | E11: 1000314822 | F11: 삼성전자 ㈜ | G11: FY2024 3Q 삼성전자DX v2 | H11: FY2024 3Q 삼성전자DX v2 | I11: 2024-07-01 ~ 2024-09-30 | J11: Revenue | K11: O | L11: =R11+T11+V11 -> 38356494496946 | M11: =Q11+S11+U11 -> 1963137 | N11: =R11/$L11 -> 0.080830717 | O11: =T11/$L11 -> 0.029777111 | P11: =V11/$L11 -> 0.88939217 | Q11: 258 | R11: 3100382958794 | S11: 765 | T11: 1142145599922 | U11: 1962114 | V11: 34113965938230
B12: 1 | C12: Interim | D12: O | E12: 1000314822 | F12: 삼성전자 ㈜ | G12: FY2024 3Q 삼성전자DS v2 | H12: FY2024 1Q 삼성전자DS v2 | I12: 2024-01-01 ~ 2024-03-31 | J12: High Risk Journal Entry | K12: X | L12: =R12+T12+V12 -> 1.8428805e+15 | M12: =Q12+S12+U12 -> 11616648 | N12: =R12/$L12 -> 0.006175013 | O12: =T12/$L12 -> 0 | P12: =V12/$L12 -> 0.99382499 | Q12: 36 | R12: 11379811127073 | S12: 0 | T12: 0 | U12: 11616612 | V12: 1.8315007e+15
B13: 1 | C13: Interim | D13: O | E13: 1000314822 | F13: 삼성전자 ㈜ | G13: FY2024 3Q 삼성전자DS v2 | H13: FY2024 1Q 삼성전자DS v2 | I13: 2024-01-01 ~ 2024-03-31 | J13: Operating Expense | K13: O | L13: =R13+T13+V13 -> 1680967827854 | M13: =Q13+S13+U13 -> 2076 | N13: =R13/$L13 -> 0.005033242 | O13: =T13/$L13 -> 0.40306655 | P13: =V13/$L13 -> 0.59190021 | Q13: 4 | R13: 8460717912 | S13: 143 | T13: 677541902037 | U13: 1929 | V13: 994965207905
B14: 1 | C14: Interim | D14: O | E14: 1000314822 | F14: 삼성전자 ㈜ | G14: FY2024 3Q 삼성전자DS v2 | H14: FY2024 1Q 삼성전자DS v2 | I14: 2024-01-01 ~ 2024-03-31 | J14: Revenue | K14: X | L14: =R14+T14+V14 -> 36928160378920 | M14: =Q14+S14+U14 -> 62801 | N14: =R14/$L14 -> 0.20886857 | O14: =T14/$L14 -> 0.069332216 | P14: =V14/$L14 -> 0.72179921 | Q14: 63 | R14: 7713132147622 | S14: 394 | T14: 2560311190546 | U14: 62344 | V14: 26654717040752
B15: 1 | C15: Interim | D15: O | E15: 1000314822 | F15: 삼성전자 ㈜ | G15: FY2024 3Q 삼성전자DS v2 | H15: FY2024 2Q 삼성전자DS v2 | I15: 2024-04-01 ~ 2024-06-30 | J15: High Risk Journal Entry | K15: X | L15: =R15+T15+V15 -> 1.7166934e+15 | M15: =Q15+S15+U15 -> 12207122 | N15: =R15/$L15 -> 0.0022929093 | O15: =T15/$L15 -> 0 | P15: =V15/$L15 -> 0.99770709 | Q15: 25 | R15: 3936222284335 | S15: 0 | T15: 0 | U15: 12207097 | V15: 1.7127572e+15
B16: 1 | C16: Interim | D16: O | E16: 1000314822 | F16: 삼성전자 ㈜ | G16: FY2024 3Q 삼성전자DS v2 | H16: FY2024 2Q 삼성전자DS v2 | I16: 2024-04-01 ~ 2024-06-30 | J16: Operating Expense | K16: O | L16: =R16+T16+V16 -> 1690198904030 | M16: =Q16+S16+U16 -> 959 | N16: =R16/$L16 -> 0.0091258447 | O16: =T16/$L16 -> 0.47288959 | P16: =V16/$L16 -> 0.51798456 | Q16: 4 | R16: 15424492636 | S16: 71 | T16: 799277471801 | U16: 884 | V16: 875496939593
B17: 1 | C17: Interim | D17: O | E17: 1000314822 | F17: 삼성전자 ㈜ | G17: FY2024 3Q 삼성전자DS v2 | H17: FY2024 2Q 삼성전자DS v2 | I17: 2024-04-01 ~ 2024-06-30 | J17: Revenue | K17: X | L17: =R17+T17+V17 -> 37764286340695 | M17: =Q17+S17+U17 -> 58471 | N17: =R17/$L17 -> 0.11204398 | O17: =T17/$L17 -> 0.052068677 | P17: =V17/$L17 -> 0.83588734 | Q17: 52 | R17: 4231260886516 | S17: 492 | T17: 1966336414874 | U17: 57927 | V17: 31566689039305
B18: 1 | C18: Interim | D18: O | E18: 1000314822 | F18: 삼성전자 ㈜ | G18: FY2024 3Q 삼성전자DS v2 | H18: FY2024 3Q 삼성전자DS v2 | I18: 2024-07-01 ~ 2024-09-30 | J18: High Risk Journal Entry | K18: X | L18: =R18+T18+V18 -> 1.8913127e+15 | M18: =Q18+S18+U18 -> 12709702 | N18: =R18/$L18 -> 0.00014072779 | O18: =T18/$L18 -> 0 | P18: =V18/$L18 -> 0.99985927 | Q18: 25 | R18: 266160251511 | S18: 0 | T18: 0 | U18: 12709677 | V18: 1.8910466e+15
B19: 1 | C19: Interim | D19: O | E19: 1000314822 | F19: 삼성전자 ㈜ | G19: FY2024 3Q 삼성전자DS v2 | H19: FY2024 3Q 삼성전자DS v2 | I19: 2024-07-01 ~ 2024-09-30 | J19: Operating Expense | K19: O | L19: =R19+T19+V19 -> 1589094064615 | M19: =Q19+S19+U19 -> 1699 | N19: =R19/$L19 -> 0.0052550487 | O19: =T19/$L19 -> 0.53397516 | P19: =V19/$L19 -> 0.46076979 | Q19: 4 | R19: 8350766765 | S19: 106 | T19: 848536763307 | U19: 1589 | V19: 732206534543
B20: 1 | C20: Interim | D20: O | E20: 1000314822 | F20: 삼성전자 ㈜ | G20: FY2024 3Q 삼성전자DS v2 | H20: FY2024 3Q 삼성전자DS v2 | I20: 2024-07-01 ~ 2024-09-30 | J20: Revenue | K20: X | L20: =R20+T20+V20 -> 36353065896141 | M20: =Q20+S20+U20 -> 54498 | N20: =R20/$L20 -> 0.09121981 | O20: =T20/$L20 -> 0.039870948 | P20: =V20/$L20 -> 0.86890924 | Q20: 50 | R20: 3316119755318 | S20: 302 | T20: 1449431187300 | U20: 54146 | V20: 31587514953523
... B44: 6 | C44: Interim | D44: O | E44: 1000325538 | F44: SK네트웍스 ㈜ | G44: FY2024 2Q SK네트웍스 | H44: FY2024 2Q SK네트웍스 v6 | I44: 2024-01-01 ~ 2024-06-30 | J44: Operating Expense | K44: O | L44: =R44+T44+V44 -> 6634194145 | M44: =Q44+S44+U44 -> 5947 | N44: =R44/$L44 -> 0 | O44: =T44/$L44 -> 0.066555011 | P44: =V44/$L44 -> 0.93344499 | Q44: 0 | R44: 0 | S44: 195 | T44: 441538862 | U44: 5752 | V44: 6192655283
B45: 6 | C45: Interim | D45: X | E45: 1000325538 | F45: SK네트웍스 ㈜ | G45: FY2024 2Q SK네트웍스 | H45: FY2024 2Q SK네트웍스 v6 | I45: 2024-01-01 ~ 2024-06-30 | J45: Revenue | K45: O | L45: =R45+T45+V45 -> 6639049794656 | M45: =Q45+S45+U45 -> 234545 | N45: =R45/$L45 -> 0.019494706 | O45: =T45/$L45 -> 0.36198134 | P45: =V45/$L45 -> 0.61852396 | Q45: 113 | R45: 129426322624 | S45: 2860 | T45: 2403212120823 | U45: 231572 | V45: 4106411351209 | W45: 월말에 매출정산으로 100개 라인을 초과하는 전표가 존재.
B46: 6 | C46: Final | D46: O | E46: 1000325538 | F46: SK네트웍스 ㈜ | G46: FY2024 SK네트웍스 | H46: FY2024 SK네트웍스 | I46: 2024-01-01 ~ 2024-12-31 | J46: High Risk Journal Entry | K46: X | L46: =R46+T46+V46 -> 865239830173994 | M46: =Q46+S46+U46 -> 8684780 | N46: =R46/$L46 -> 0.00071746621 | O46: =T46/$L46 -> 0 | P46: =V46/$L46 -> 0.99928253 | Q46: 294 | R46: 620780342708 | S46: 0 | T46: 0 | U46: 8684486 | V46: 864619049831286
B47: 6 | C47: Final | D47: O | E47: 1000325538 | F47: SK네트웍스 ㈜ | G47: FY2024 SK네트웍스 | H47: FY2024 SK네트웍스 | I47: 2024-01-01 ~ 2024-12-31 | J47: Operating Expense | K47: O | L47: =R47+T47+V47 -> 12918718273 | M47: =Q47+S47+U47 -> 11766 | N47: =R47/$L47 -> 0 | O47: =T47/$L47 -> 0.0443103 | P47: =V47/$L47 -> 0.9556897 | Q47: 0 | R47: 0 | S47: 658 | T47: 572432279 | U47: 11108 | V47: 12346285994
B48: 6 | C48: Final | D48: X | E48: 1000325538 | F48: SK네트웍스 ㈜ | G48: FY2024 SK네트웍스 | H48: FY2024 SK네트웍스 | I48: 2024-01-01 ~ 2024-06-30 | J48: Revenue | K48: X | L48: =R48+T48+V48 -> 14830065797603 | M48: =Q48+S48+U48 -> 305276 | N48: =R48/$L48 -> 0.027292208 | O48: =T48/$L48 -> 0.58853936 | P48: =V48/$L48 -> 0.38416844 | Q48: 136 | R48: 404745233366 | S48: 13234 | T48: 8728077367008 | U48: 291906 | V48: 5697243197229
B49: 7 | C49: Interim | D49: X | E49: 1000326122 | F49: 엘지이노텍 주식회사 | G49: FY2024 2Q LG이노텍 v2 | H49: FY2024 2Q LG이노텍 v2 KR | I49: 2024-01-01 ~ 2024-06-30 | J49: Cost of Sales | K49: X | L49: =R49+T49+V49 -> 23157624943763 | M49: =Q49+S49+U49 -> 76750 | N49: =R49/$L49 -> 0 | O49: =T49/$L49 -> 0.034402473 | P49: =V49/$L49 -> 0.96559753 | Q49: 0 | R49: 0 | S49: 1445 | T49: 796679566304 | U49: 75305 | V49: 22360945377459
B50: 7 | C50: Interim | D50: X | E50: 1000326122 | F50: 엘지이노텍 주식회사 | G50: FY2024 2Q LG이노텍 v2 | H50: FY2024 2Q LG이노텍 v2 KR | I50: 2024-01-01 ~ 2024-06-30 | J50: High Risk Journal Entry | K50: X | L50: =R50+T50+V50 -> 495348627853980 | M50: =Q50+S50+U50 -> 7791663 | N50: =R50/$L50 -> 0.0018367962 | O50: =T50/$L50 -> 0 | P50: =V50/$L50 -> 0.9981632 | Q50: 12 | R50: 909854500716 | S50: 0 | T50: 0 | U50: 7791651 | V50: 494438773353264
B51: 7 | C51: Interim | D51: X | E51: 1000326122 | F51: 엘지이노텍 주식회사 | G51: FY2024 2Q LG이노텍 v2 | H51: FY2024 2Q LG이노텍 v2 KR | I51: 2024-01-01 ~ 2024-06-30 | J51: Operating Expense | K51: X | L51: =R51+T51+V51 -> 1610288512221 | M51: =Q51+S51+U51 -> 813061 | N51: =R51/$L51 -> 0.028181451 | O51: =T51/$L51 -> 0.22668749 | P51: =V51/$L51 -> 0.74513106 | Q51: 71 | R51: 45380266421 | S51: 7018 | T51: 365032253610 | U51: 805972 | V51: 1199875992190
B52: 7 | C52: Interim | D52: X | E52: 1000326122 | F52: 엘지이노텍 주식회사 | G52: FY2024 2Q LG이노텍 v2 | H52: FY2024 2Q LG이노텍 v2 KR | I52: 2024-01-01 ~ 2024-06-30 | J52: Revenue | K52: X | L52: =R52+T52+V52 -> 12050267614336 | M52: =Q52+S52+U52 -> 185867 | N52: =R52/$L52 -> 0.021991405 | O52: =T52/$L52 -> 0.088071665 | P52: =V52/$L52 -> 0.88993693 | Q52: 292 | R52: 265002310449 | S52: 6312 | T52: 1061287129151 | U52: 179263 | V52: 10723978174736
B53: 7 | C53: Interim | D53: X | E53: 1000326122 | F53: 엘지이노텍 주식회사 | G53: FY2024 2Q LG이노텍 v2 | H53: FY2024 2Q LG이노텍 v2 JP | I53: 2024-01-01 ~ 2024-06-30 | J53: High Risk Journal Entry | K53: X | L53: =R53+T53+V53 -> 1939911903 | M53: =Q53+S53+U53 -> 11476 | N53: =R53/$L53 -> 0 | O53: =T53/$L53 -> 0 | P53: =V53/$L53 -> 1 | Q53: 0 | R53: 0 | S53: 0 | T53: 0 | U53: 11476 | V53: 1939911903 | W53: AITS 이용가능.
B54: 7 | C54: Interim | D54: X | E54: 1000326122 | F54: 엘지이노텍 주식회사 | G54: FY2024 2Q LG이노텍 v2 | H54: FY2024 2Q LG이노텍 v2 JP | I54: 2024-01-01 ~ 2024-06-30 | J54: Operating Expense | K54: X | L54: =R54+T54+V54 -> 91522816 | M54: =Q54+S54+U54 -> 1571 | N54: =R54/$L54 -> 0 | O54: =T54/$L54 -> 0.11947141 | P54: =V54/$L54 -> 0.88052859 | Q54: 0 | R54: 0 | S54: 76 | T54: 10934360 | U54: 1495 | V54: 80588456 | W54: 전표숫자 자체가 낮아서 이용불가
B55: 7 | C55: Interim | D55: X | E55: 1000326122 | F55: 엘지이노텍 주식회사 | G55: FY2024 2Q LG이노텍 v2 | H55: FY2024 2Q LG이노텍 v2 JP | I55: 2024-01-01 ~ 2024-06-30 | J55: Revenue | K55: X | L55: =R55+T55+V55 -> 394418166 | M55: =Q55+S55+U55 -> 37 | N55: =R55/$L55 -> 0 | O55: =T55/$L55 -> 0.56219298 | P55: =V55/$L55 -> 0.43780702 | Q55: 0 | R55: 0 | S55: 12 | T55: 221739124 | U55: 25 | V55: 172679042 | W55: "매출채권 / 매출"로 정상전표이나 매출 전표 숫자가 적어서, Rare Flow로 대부분 Trigger
B56: 7 | C56: Interim | D56: X | E56: 1000326122 | F56: 엘지이노텍 주식회사 | G56: FY2024 2Q LG이노텍 v2 | H56: FY2024 2Q LG이노텍 v2 EU | I56: 2024-01-01 ~ 2024-06-30 | J56: High Risk Journal Entry | K56: X | L56: =R56+T56+V56 -> 23824400 | M56: =Q56+S56+U56 -> 10947 | N56: =R56/$L56 -> 0.0009676634 | O56: =T56/$L56 -> 0 | P56: =V56/$L56 -> 0.99903234 | Q56: 2 | R56: 23054 | S56: 0 | T56: 0 | U56: 10945 | V56: 23801346
B57: 7 | C57: Interim | D57: X | E57: 1000326122 | F57: 엘지이노텍 주식회사 | G57: FY2024 2Q LG이노텍 v2 | H57: FY2024 2Q LG이노텍 v2 EU | I57: 2024-01-01 ~ 2024-06-30 | J57: Operating Expense | K57: X | L57: =R57+T57+V57 -> 1082056.6 | M57: =Q57+S57+U57 -> 1847 | N57: =R57/$L57 -> 0 | O57: =T57/$L57 -> 0.22619139 | P57: =V57/$L57 -> 0.77380861 | Q57: 0 | R57: 0 | S57: 66 | T57: 244751.88 | U57: 1781 | V57: 837304.68
B58: 7 | C58: Interim | D58: X | E58: 1000326122 | F58: 엘지이노텍 주식회사 | G58: FY2024 2Q LG이노텍 v2 | H58: FY2024 2Q LG이노텍 v2 EU | I58: 2024-01-01 ~ 2024-06-30 | J58: Revenue | K58: X | L58: =R58+T58+V58 -> 1583331 | M58: =Q58+S58+U58 -> 21 | N58: =R58/$L58 -> 0 | O58: =T58/$L58 -> 1 | P58: =V58/$L58 -> 0 | Q58: 0 | R58: 0 | S58: 21 | T58: 1583331 | U58: 0 | V58: 0 | W58: "매출채권 / 매출"로 정상전표이나 매출 전표 숫자가 적어서, Rare Flow로 대부분 Trigger
B59: 12 | C59: Interim | D59: X | E59: 1000316262 | F59: 에스케이가스㈜ | G59: FY2024 2Q SK가스 | H59: FY2024 2Q SK가스 | I59: 2024-01-01 ~ 2024-06-30 | J59: High Risk Journal Entry | K59: X | L59: =R59+T59+V59 -> 147069777501432 | M59: =Q59+S59+U59 -> 1457818 | N59: =R59/$L59 -> 0.00029083957 | O59: =T59/$L59 -> 0 | P59: =V59/$L59 -> 0.99970916 | Q59: 2 | R59: 42773710249 | S59: 0 | T59: 0 | U59: 1457816 | V59: 147027003791183
B60: 12 | C60: Interim | D60: X | E60: 1000316262 | F60: 에스케이가스㈜ | G60: FY2024 2Q SK가스 | H60: FY2024 2Q SK가스 | I60: 2024-01-01 ~ 2024-06-30 | J60: Operating Expense | K60: O | L60: =R60+T60+V60 -> 745518841905 | M60: =Q60+S60+U60 -> 34323 | N60: =R60/$L60 -> 0.024255587 | O60: =T60/$L60 -> 0.6995563 | P60: =V60/$L60 -> 0.27618811 | Q60: 21 | R60: 18082996971 | S60: 2718 | T60: 521532402436 | U60: 31584 | V60: 205903442498
B61: 12 | C61: Interim | D61: X | E61: 1000316262 | F61: 에스케이가스㈜ | G61: FY2024 2Q SK가스 | H61: FY2024 2Q SK가스 | I61: 2024-01-01 ~ 2024-06-30 | J61: Revenue | K61: O | L61: =R61+T61+V61 -> 3659185228424 | M61: =Q61+S61+U61 -> 129201 | N61: =R61/$L61 -> 0.00068848838 | O61: =T61/$L61 -> 0.17919654 | P61: =V61/$L61 -> 0.82011497 | Q61: 2 | R61: 2519306503 | S61: 6048 | T61: 655713347446 | U61: 123151 | V61: 3000952574475
B62: 13 | C62: Interim | D62: O | E62: 1000326018 | F62: 하이트진로 ㈜ | G62: FY2024 3Q 하이트진로 주식회사 v2 | H62: FY2024 3Q 하이트진로 주식회사 v2 | I62: 2024-01-01 ~ 2024-06-30 | J62: High Risk Journal Entry | K62: X | L62: =R62+T62+V62 -> 234737328710916 | M62: =Q62+S62+U62 -> 9700422 | N62: =R62/$L62 -> 0.062888876 | O62: =T62/$L62 -> 0 | P62: =V62/$L62 -> 0.93711112 | Q62: 18 | R62: 14762366869465 | S62: 0 | T62: 0 | U62: 9700404 | V62: 219974961841451
B63: 13 | C63: Interim | D63: O | E63: 1000326018 | F63: 하이트진로 ㈜ | G63: FY2024 3Q 하이트진로 주식회사 v2 | H63: FY2024 3Q 하이트진로 주식회사 v2 | I63: 2024-01-01 ~ 2024-06-30 | J63: Operating Expense | K63: O | L63: =R63+T63+V63 -> 843311844883 | M63: =Q63+S63+U63 -> 542640 | N63: =R63/$L63 -> 0.16592181 | O63: =T63/$L63 -> 0.19063154 | P63: =V63/$L63 -> 0.64344665 | Q63: 896 | R63: 139923826530 | S63: 14556 | T63: 160761838843 | U63: 527188 | V63: 542626179510
B64: 13 | C64: Interim | D64: X | E64: 1000326018 | F64: 하이트진로 ㈜ | G64: FY2024 3Q 하이트진로 주식회사 v2 | H64: FY2024 3Q 하이트진로 주식회사 v2 | I64: 2024-01-01 ~ 2024-06-30 | J64: Revenue | K64: O | L64: =R64+T64+V64 -> 4223521426263 | M64: =Q64+S64+U64 -> 613122 | N64: =R64/$L64 -> 0.016295358 | O64: =T64/$L64 -> 0.49217484 | P64: =V64/$L64 -> 0.49152981 | Q64: 158 | R64: 68823792260 | S64: 579 | T64: 2078710964274 | U64: 612385 | V64: 2075986669729 | W64: Medium 49% 중 48%가 재무제표에 영향을 미치지 않는 매출/매출 상계전표 41건. 해당 전표 유형 소명 시 특이사항 없음
B65: 13 | C65: Final | D65: O | E65: 1000326018 | F65: 하이트진로 ㈜ | G65: FY2024 하이트진로 주식회사 | H65: FY2024 하이트진로 주식회사 | I65: 2024-01-01 ~ 2024-12-31 | J65: High Risk Journal Entry | K65: X | L65: =R65+T65+V65 -> 297958037490820 | M65: =Q65+S65+U65 -> 12819000 | N65: =R65/$L65 -> 0.049936004 | O65: =T65/$L65 -> 0 | P65: =V65/$L65 -> 0.950064 | Q65: 95 | R65: 14878833617299 | S65: 0 | T65: 0 | U65: 12818905 | V65: 283079203873521
B66: 13 | C66: Final | D66: O | E66: 1000326018 | F66: 하이트진로 ㈜ | G66: FY2024 하이트진로 주식회사 | H66: FY2024 하이트진로 주식회사 | I66: 2024-01-01 ~ 2024-12-31 | J66: Operating Expense | K66: O | L66: =R66+T66+V66 -> 1183800801376 | M66: =Q66+S66+U66 -> 779303 | N66: =R66/$L66 -> 0.13018686 | O66: =T66/$L66 -> 0.1892926 | P66: =V66/$L66 -> 0.68052054 | Q66: 1310 | R66: 154115313650 | S66: 32760 | T66: 224084732348 | U66: 745233 | V66: 805600755378
B67: 13 | C67: Final | D67: X | E67: 1000326018 | F67: 하이트진로 ㈜ | G67: FY2024 하이트진로 주식회사 | H67: FY2024 하이트진로 주식회사 | I67: 2024-01-01 ~ 2024-12-31 | J67: Revenue | K67: X | L67: =R67+T67+V67 -> 5558447823656 | M67: =Q67+S67+U67 -> 807574 | N67: =R67/$L67 -> 0.017525766 | O67: =T67/$L67 -> 0.51998576 | P67: =V67/$L67 -> 0.46248847 | Q67: 254 | R67: 97416054440 | S67: 12701 | T67: 2890313715983 | U67: 794619 | V67: 2570718053233
B68: 14 | C68: Interim | D68: O | E68: 1000315188 | F68: ㈜ 제일기획 | G68: FY2024 2Q 제일기획 | H68: FY2024 2Q 제일기획 | I68: 2024-01-01 ~ 2024-06-30 | J68: High Risk Journal Entry | K68: X | L68: =R68+T68+V68 -> 98604186451390 | M68: =Q68+S68+U68 -> 663563 | N68: =R68/$L68 -> 0.30550135 | O68: =T68/$L68 -> 0 | P68: =V68/$L68 -> 0.69449865 | Q68: 10 | R68: 30123711838750 | S68: 0 | T68: 0 | U68: 663553 | V68: 68480474612640
B69: 14 | C69: Interim | D69: O | E69: 1000315188 | F69: ㈜ 제일기획 | G69: FY2024 2Q 제일기획 | H69: FY2024 2Q 제일기획 | I69: 2024-01-01 ~ 2024-06-30 | J69: Operating Expense | K69: O | L69: =R69+T69+V69 -> 861155467875 | M69: =Q69+S69+U69 -> 151960 | N69: =R69/$L69 -> 8.9773767e-06 | O69: =T69/$L69 -> 0.15398797 | P69: =V69/$L69 -> 0.84600306 | Q69: 12 | R69: 7730917 | S69: 1238 | T69: 132607578490 | U69: 150710 | V69: 728540158468
B70: 14 | C70: Interim | D70: O | E70: 1000315188 | F70: ㈜ 제일기획 | G70: FY2024 2Q 제일기획 | H70: FY2024 2Q 제일기획 | I70: 2024-01-01 ~ 2024-06-30 | J70: Revenue | K70: O | L70: =R70+T70+V70 -> 6012600961752 | M70: =Q70+S70+U70 -> 23671 | N70: =R70/$L70 -> 0 | O70: =T70/$L70 -> 0.00070812336 | P70: =V70/$L70 -> 0.99929188 | Q70: 0 | R70: 0 | S70: 34 | T70: 4257663206 | U70: 23637 | V70: 6008343298546
B71: 14 | C71: Final | D71: O | E71: 1000315188 | F71: ㈜ 제일기획 | G71: FY2024 YE 제일기획 | H71: FY2024 YE 제일기획(Y1B0) | I71: 2024-01-01 ~ 2024-12-31 | J71: High Risk Journal Entry | K71: X | L71: =R71+T71+V71 -> 196604637024494 | M71: =Q71+S71+U71 -> 1451149 | N71: =R71/$L71 -> 0.3053029 | O71: =T71/$L71 -> 0 | P71: =V71/$L71 -> 0.6946971 | Q71: 17 | R71: 60023965299262 | S71: 0 | T71: 0 | U71: 1451132 | V71: 136580671725232
B72: 14 | C72: Final | D72: O | E72: 1000315188 | F72: ㈜ 제일기획 | G72: FY2024 YE 제일기획 | H72: FY2024 YE 제일기획(Y1B0) | I72: 2024-01-01 ~ 2024-12-31 | J72: Operating Expense | K72: O | L72: =R72+T72+V72 -> 1679012697884 | M72: =Q72+S72+U72 -> 276905 | N72: =R72/$L72 -> 7.1252064e-05 | O72: =T72/$L72 -> 0.14388635 | P72: =V72/$L72 -> 0.8560424 | Q72: 6 | R72: 119633121 | S72: 1563 | T72: 241587003767 | U72: 275336 | V72: 1437306060996
B73: 14 | C73: Final | D73: O | E73: 1000315188 | F73: ㈜ 제일기획 | G73: FY2024 YE 제일기획 | H73: FY2024 YE 제일기획(Y1B0) | I73: 2024-01-01 ~ 2024-12-31 | J73: Revenue | K73: O | L73: =R73+T73+V73 -> 12229961052969 | M73: =Q73+S73+U73 -> 48823 | N73: =R73/$L73 -> 9.684064e-05 | O73: =T73/$L73 -> 0.0016355427 | P73: =V73/$L73 -> 0.99826762 | Q73: 1 | R73: 1184357258 | S73: 90 | T73: 20002623653 | U73: 48732 | V73: 12208774072058
B74: 14 | C74: Final | D74: O | E74: 1000315188 | F74: ㈜ 제일기획 | G74: FY2024 YE 제일기획 | H74: FY2024 YE 제일기획(Y7Z2) | I74: 2024-01-01 ~ 2024-12-31 | J74: High Risk Journal Entry | K74: X | L74: =R74+T74+V74 -> 6623869767 | M74: =Q74+S74+U74 -> 31379 | N74: =R74/$L74 -> 0.0076172326 | O74: =T74/$L74 -> 0 | P74: =V74/$L74 -> 0.99238277 | Q74: 3 | R74: 50455557 | S74: 0 | T74: 0 | U74: 31376 | V74: 6573414210
B75: 14 | C75: Final | D75: O | E75: 1000315188 | F75: ㈜ 제일기획 | G75: FY2024 YE 제일기획 | H75: FY2024 YE 제일기획(Y7Z2) | I75: 2024-01-01 ~ 2024-12-31 | J75: Operating Expense | K75: O | L75: =R75+T75+V75 -> 140614428 | M75: =Q75+S75+U75 -> 4338 | N75: =R75/$L75 -> 0 | O75: =T75/$L75 -> 0.003013439 | P75: =V75/$L75 -> 0.99698656 | Q75: 0 | R75: 0 | S75: 49 | T75: 423733 | U75: 4289 | V75: 140190695
B76: 14 | C76: Final | D76: O | E76: 1000315188 | F76: ㈜ 제일기획 | G76: FY2024 YE 제일기획 | H76: FY2024 YE 제일기획(Y7Z2) | I76: 2024-01-01 ~ 2024-12-31 | J76: Revenue | K76: O | L76: =R76+T76+V76 -> 1114435016 | M76: =Q76+S76+U76 -> 2723 | N76: =R76/$L76 -> 0 | O76: =T76/$L76 -> 0.012738142 | P76: =V76/$L76 -> 0.98726186 | Q76: 0 | R76: 0 | S76: 3 | T76: 14195832 | U76: 2720 | V76: 1100239184
... B110: 22 | C110: Interim | D110: O | E110: 1000953509 | F110: 아세아시멘트㈜ | G110: FY2024 2Q 아세아시멘트 | H110: FY2024 2Q 아세아시멘트 v4 | I110: 2024-01-01 ~ 2024-06-30 | J110: Operating Expense | K110: O | L110: =R110+T110+V110 -> 106521882913 | M110: =Q110+S110+U110 -> 19055 | N110: =R110/$L110 -> 0.010456869 | O110: =T110/$L110 -> 0.15627237 | P110: =V110/$L110 -> 0.83327076 | Q110: 3 | R110: 1113885425 | S110: 213 | T110: 16646427306 | U110: 18839 | V110: 88761570182
B111: 22 | C111: Interim | D111: O | E111: 1000953509 | F111: 아세아시멘트㈜ | G111: FY2024 2Q 아세아시멘트 | H111: FY2024 2Q 아세아시멘트 v4 | I111: 2024-01-01 ~ 2024-06-30 | J111: Revenue | K111: X | L111: =R111+T111+V111 -> 289102794427 | M111: =Q111+S111+U111 -> 7246 | N111: =R111/$L111 -> 0.23057186 | O111: =T111/$L111 -> 0.43590584 | P111: =V111/$L111 -> 0.3335223 | Q111: 78 | R111: 66658970350 | S111: 1225 | T111: 126021596272 | U111: 5943 | V111: 96422227805 | W111: 월말에 매출정산으로 100개 라인을 초과하는 전표가 존재.
B112: 22 | C112: Final | D112: O | E112: 1000953509 | F112: 아세아시멘트㈜ | G112: FY2024 아세아시멘트 | H112: FY2024 아세아시멘트 | I112: 2024-01-01 ~ 2024-12-31 | J112: High Risk Journal Entry | K112: X | L112: =R112+T112+V112 -> 21152750633844 | M112: =Q112+S112+U112 -> 541859 | N112: =R112/$L112 -> 0.054088966 | O112: =T112/$L112 -> 0 | P112: =V112/$L112 -> 0.94591103 | Q112: 6 | R112: 1144130405849 | S112: 0 | T112: 0 | U112: 541853 | V112: 20008620227995
B113: 22 | C113: Final | D113: O | E113: 1000953509 | F113: 아세아시멘트㈜ | G113: FY2024 아세아시멘트 | H113: FY2024 아세아시멘트 | I113: 2024-01-01 ~ 2024-12-31 | J113: Operating Expense | K113: O | L113: =R113+T113+V113 -> 4097552991 | M113: =Q113+S113+U113 -> 3308 | N113: =R113/$L113 -> 0 | O113: =T113/$L113 -> 0.02836391 | P113: =V113/$L113 -> 0.97163609 | Q113: 0 | R113: 0 | S113: 29 | T113: 116222625 | U113: 3279 | V113: 3981330366
B114: 22 | C114: Final | D114: O | E114: 1000953509 | F114: 아세아시멘트㈜ | G114: FY2024 아세아시멘트 | H114: FY2024 아세아시멘트 | I114: 2024-01-01 ~ 2024-12-31 | J114: Revenue | K114: X | L114: =R114+T114+V114 -> 557755680549 | M114: =Q114+S114+U114 -> 15212 | N114: =R114/$L114 -> 0 | O114: =T114/$L114 -> 0.04758851 | P114: =V114/$L114 -> 0.95241149 | Q114: 0 | R114: 0 | S114: 809 | T114: 26542761616 | U114: 14403 | V114: 531212918933
B115: 23 | C115: Interim | D115: O | E115: 1000326195 | F115: 씨제이프레시웨이 주식회사 | G115: FY2024 씨제이프레시웨이 외부감사_v2 | H115: FY2024 씨제이프레시웨이 외부감사_v5 | I115: 2024-01-01 ~ 2024-06-30 | J115: High Risk Journal Entry | K115: X | L115: =R115+T115+V115 -> 51977321071314 | M115: =Q115+S115+U115 -> 175336242 | N115: =R115/$L115 -> 0.0092986418 | O115: =T115/$L115 -> 0 | P115: =V115/$L115 -> 0.99070136 | Q115: 60 | R115: 483318488906 | S115: 0 | T115: 0 | U115: 175336182 | V115: 51494002582408
B116: 23 | C116: Interim | D116: O | E116: 1000326195 | F116: 씨제이프레시웨이 주식회사 | G116: FY2024 씨제이프레시웨이 외부감사_v2 | H116: FY2024 씨제이프레시웨이 외부감사_v5 | I116: 2024-01-01 ~ 2024-06-30 | J116: Operating Expense | K116: O | L116: =R116+T116+V116 -> 504306434441 | M116: =Q116+S116+U116 -> 7004130 | N116: =R116/$L116 -> 0.082775425 | O116: =T116/$L116 -> 0.55633032 | P116: =V116/$L116 -> 0.36089425 | Q116: 1485 | R116: 41744179309 | S116: 108569 | T116: 280560960873 | U116: 6894076 | V116: 182001294259
B117: 23 | C117: Interim | D117: O | E117: 1000326195 | F117: 씨제이프레시웨이 주식회사 | G117: FY2024 씨제이프레시웨이 외부감사_v2 | H117: FY2024 씨제이프레시웨이 외부감사_v5 | I117: 2024-01-01 ~ 2024-06-30 | J117: Revenue | K117: O | L117: =R117+T117+V117 -> 2502926126599 | M117: =Q117+S117+U117 -> 32765758 | N117: =R117/$L117 -> 0.00041633696 | O117: =T117/$L117 -> 0.05607333 | P117: =V117/$L117 -> 0.94351033 | Q117: 113 | R117: 1042060655 | S117: 24417 | T117: 140347401856 | U117: 32741228 | V117: 2361536664088
B118: 23 | C118: Final | D118: O | E118: 1000326195 | F118: 씨제이프레시웨이 주식회사 | G118: FY2024 씨제이프레시웨이 외부감사 | H118: FY2024 씨제이프레시웨이 외부감사 | I118: 2024-01-01 ~ 2024-12-31 | J118: High Risk Journal Entry | K118: X | L118: =R118+T118+V118 -> 66733907729140 | M118: =Q118+S118+U118 -> 188466301 | N118: =R118/$L118 -> 0 | O118: =T118/$L118 -> 0 | P118: =V118/$L118 -> 1 | Q118: 0 | R118: 0 | S118: 0 | T118: 0 | U118: 188466301 | V118: 66733907729140
B119: 23 | C119: Final | D119: O | E119: 1000326195 | F119: 씨제이프레시웨이 주식회사 | G119: FY2024 씨제이프레시웨이 외부감사 | H119: FY2024 씨제이프레시웨이 외부감사 | I119: 2024-01-01 ~ 2024-12-31 | J119: Operating Expense | K119: O | L119: =R119+T119+V119 -> 544688524737 | M119: =Q119+S119+U119 -> 7712762 | N119: =R119/$L119 -> 0 | O119: =T119/$L119 -> 0 | P119: =V119/$L119 -> 1 | Q119: 0 | R119: 0 | S119: 0 | T119: 0 | U119: 7712762 | V119: 544688524737
B120: 23 | C120: Final | D120: O | E120: 1000326195 | F120: 씨제이프레시웨이 주식회사 | G120: FY2024 씨제이프레시웨이 외부감사 | H120: FY2024 씨제이프레시웨이 외부감사 | I120: 2024-01-01 ~ 2024-12-31 | J120: Revenue | K120: O | L120: =R120+T120+V120 -> 2725718108607 | M120: =Q120+S120+U120 -> 35440092 | N120: =R120/$L120 -> 0 | O120: =T120/$L120 -> 0 | P120: =V120/$L120 -> 1 | Q120: 0 | R120: 0 | S120: 0 | T120: 0 | U120: 35440092 | V120: 2725718108607
B121: 24 | C121: Interim | D121: X | E121: 1000326228 | F121: 보령 | G121: FY2024 2Q 보령 | H121: FY2024 2Q 보령 | I121: 2024-01-01 ~ 2024-06-30 | J121: High Risk Journal Entry | K121: X | L121: =R121+T121+V121 -> 16555355805682 | M121: 4507232 | N121: =R121/$L121 -> 0.0026248731 | O121: =T121/$L121 -> 0 | P121: =V121/$L121 -> 0.99737513 | Q121: 7 | R121: 43455707709 | S121: 0 | T121: 0 | U121: 4507225 | V121: 16511900097973
B122: 24 | C122: Interim | D122: X | E122: 1000326228 | F122: 보령 | G122: FY2024 2Q 보령 | H122: FY2024 2Q 보령 | I122: 2024-01-01 ~ 2024-06-30 | J122: Operating Expense | K122: O | L122: =R122+T122+V122 -> 140173562668 | M122: 391336 | N122: =R122/$L122 -> 0.0074059556 | O122: =T122/$L122 -> 0.36546092 | P122: =V122/$L122 -> 0.62713313 | Q122: 122 | R122: 1038119182 | S122: 14610 | T122: 51227959032 | U122: 376604 | V122: 87907484454
B123: 24 | C123: Interim | D123: X | E123: 1000326228 | F123: 보령 | G123: FY2024 2Q 보령 | H123: FY2024 2Q 보령 | I123: 2024-01-01 ~ 2024-06-30 | J123: Revenue | K123: O | L123: =R123+T123+V123 -> 555025663729 | M123: 261828 | N123: =R123/$L123 -> 0.015650201 | O123: =T123/$L123 -> 0.093958849 | P123: =V123/$L123 -> 0.89039095 | Q123: 55 | R123: 8686263427 | S123: 1494 | T123: 52149572779 | U123: 260279 | V123: 494189827523
B124: 25 | C124: Interim | D124: O | E124: 1000325863 | F124: 주식회사 E1 | G124: FY2024 2Q E1 | H124: FY2024 2Q E1 v2 | I124: 2024-01-01 ~ 2024-06-30 | J124: High Risk Journal Entry | K124: X | L124: =R124+T124+V124 -> 187087770480712 | M124: =Q124+S124+U124 -> 2169364 | N124: =R124/$L124 -> 0.012860049 | O124: =T124/$L124 -> 0.053098704 | P124: =V124/$L124 -> 0.93404125 | Q124: 21 | R124: 2405957886415 | S124: 32592 | T124: 9934118166151 | U124: 2136751 | V124: 174747694428146
B125: 25 | C125: Interim | D125: O | E125: 1000325863 | F125: 주식회사 E1 | G125: FY2024 2Q E1 | H125: FY2024 2Q E1 v2 | I125: 2024-01-01 ~ 2024-06-30 | J125: Operating Expense | K125: O | L125: =R125+T125+V125 -> 71285202585 | M125: =Q125+S125+U125 -> 49312 | N125: =R125/$L125 -> 0.063490996 | O125: =T125/$L125 -> 0.11059397 | P125: =V125/$L125 -> 0.82591503 | Q125: 11 | R125: 4525968529 | S125: 665 | T125: 7883713647 | U125: 48636 | V125: 58875520409
B126: 25 | C126: Interim | D126: O | E126: 1000325863 | F126: 주식회사 E1 | G126: FY2024 2Q E1 | H126: FY2024 2Q E1 v2 | I126: 2024-01-01 ~ 2024-06-30 | J126: Revenue | K126: O | L126: =R126+T126+V126 -> 8135790031341 | M126: =Q126+S126+U126 -> 325173 | N126: =R126/$L126 -> 0.014251765 | O126: =T126/$L126 -> 0.037009459 | P126: =V126/$L126 -> 0.94873878 | Q126: 6 | R126: 115949364171 | S126: 188 | T126: 301101191480 | U126: 324979 | V126: 7718739475690
B127: 25 | C127: Final | D127: O | E127: 1000325863 | F127: 주식회사 E1 | G127: FY2024 E1 | H127: FY2024 E1 | I127: 2024-07-01 ~ 2024-12-31 | J127: High Risk Journal Entry | K127: X | L127: =R127+T127+V127 -> 247555887874834 | M127: =Q127+S127+U127 -> 2123073 | N127: =R127/$L127 -> 0.0061303875 | O127: =T127/$L127 -> 0 | P127: =V127/$L127 -> 0.99386961 | Q127: 51 | R127: 1517613521796 | S127: 0 | T127: 0 | U127: 2123022 | V127: 246038274353038
B128: 25 | C128: Final | D128: O | E128: 1000325863 | F128: 주식회사 E1 | G128: FY2024 E1 | H128: FY2024 E1 | I128: 2024-07-01 ~ 2024-12-31 | J128: Operating Expense | K128: O | L128: =R128+T128+V128 -> 86632065929 | M128: =Q128+S128+U128 -> 50312 | N128: =R128/$L128 -> 0.053921318 | O128: =T128/$L128 -> 0.2304386 | P128: =V128/$L128 -> 0.71564008 | Q128: 28 | R128: 4671315207 | S128: 2833 | T128: 19963372265 | U128: 47451 | V128: 61997378457
B129: 25 | C129: Final | D129: O | E129: 1000325863 | F129: 주식회사 E1 | G129: FY2024 E1 | H129: FY2024 E1 | I129: 2024-07-01 ~ 2024-12-31 | J129: Revenue | K129: O | L129: =R129+T129+V129 -> 8821529340702 | M129: =Q129+S129+U129 -> 294724 | N129: =R129/$L129 -> 0.049853116 | O129: =T129/$L129 -> 0.070848366 | P129: =V129/$L129 -> 0.87929852 | Q129: 8 | R129: 439780727735 | S129: 894 | T129: 624990942617 | U129: 293822 | V129: 7756757670350
B130: 27 | C130: Interim | D130: X | E130: 1000317490 | F130: ㈜ 팜스코 | G130: FY2024 2Q 팜스코 | H130: FY2024 2Q 팜스코 | I130: 2024-01-01 ~ 2024-06-30 | J130: High Risk Journal Entry | K130: X | L130: =R130+T130+V130 -> 22052776359688 | M130: =Q130+S130+U130 -> 255304 | N130: =R130/$L130 -> 0.011634684 | O130: =T130/$L130 -> 0 | P130: =V130/$L130 -> 0.98836532 | Q130: 9 | R130: 256577088411 | S130: 0 | T130: 0 | U130: 255295 | V130: 21796199271277
B131: 27 | C131: Interim | D131: X | E131: 1000317490 | F131: ㈜ 팜스코 | G131: FY2024 2Q 팜스코 | H131: FY2024 2Q 팜스코 | I131: 2024-01-01 ~ 2024-06-30 | J131: Operating Expense | K131: O | L131: =R131+T131+V131 -> 101100497190 | M131: =Q131+S131+U131 -> 57117 | N131: =R131/$L131 -> 0.076492466 | O131: =T131/$L131 -> 0.2771854 | P131: =V131/$L131 -> 0.64632213 | Q131: 20 | R131: 7733426367 | S131: 1649 | T131: 28023582197 | U131: 55448 | V131: 65343488626
B132: 27 | C132: Interim | D132: X | E132: 1000317490 | F132: ㈜ 팜스코 | G132: FY2024 2Q 팜스코 | H132: FY2024 2Q 팜스코 | I132: 2024-01-01 ~ 2024-06-30 | J132: Revenue | K132: O | L132: =R132+T132+V132 -> 1072629069808 | M132: =Q132+S132+U132 -> 5005 | N132: =R132/$L132 -> 0.0010006876 | O132: =T132/$L132 -> 0.25553948 | P132: =V132/$L132 -> 0.74345984 | Q132: 1 | R132: 1073366580 | S132: 126 | T132: 274099069615 | U132: 4878 | V132: 797456633613
B133: 28 | C133: Interim | D133: X | E133: 1000501994 | F133: 주식회사 동양 | G133: FY2024 2Q 동양 | H133: FY2024 2Q 동양 | I133: 2024-01-01 ~ 2024-06-30 | J133: High Risk Journal Entry | K133: X | L133: =R133+T133+V133 -> 13961503621956 | M133: =Q133+S133+U133 -> 532775 | N133: =R133/$L133 -> 0.0018749177 | O133: =T133/$L133 -> 0 | P133: =V133/$L133 -> 0.99812508 | Q133: 4 | R133: 26176670067 | S133: 0 | T133: 0 | U133: 532771 | V133: 13935326951889
B134: 28 | C134: Interim | D134: X | E134: 1000501994 | F134: 주식회사 동양 | G134: FY2024 2Q 동양 | H134: FY2024 2Q 동양 | I134: 2024-01-01 ~ 2024-06-30 | J134: Operating Expense | K134: O | L134: =R134+T134+V134 -> 47961880247 | M134: =Q134+S134+U134 -> 51579 | N134: =R134/$L134 -> 2.2827108e-05 | O134: =T134/$L134 -> 0.057310609 | P134: =V134/$L134 -> 0.94266656 | Q134: 2 | R134: 1094831 | S134: 1090 | T134: 2748724547 | U134: 50487 | V134: 45212060869
B135: 28 | C135: Interim | D135: X | E135: 1000501994 | F135: 주식회사 동양 | G135: FY2024 2Q 동양 | H135: FY2024 2Q 동양 | I135: 2024-01-01 ~ 2024-06-30 | J135: Revenue | K135: O | L135: =R135+T135+V135 -> 257252204690 | M135: =Q135+S135+U135 -> 37322 | N135: =R135/$L135 -> 0 | O135: =T135/$L135 -> 0.03380173 | P135: =V135/$L135 -> 0.96619827 | Q135: 0 | R135: 0 | S135: 121 | T135: 8695569540 | U135: 37201 | V135: 248556635150
... B178: 41 | C178: Interim | D178: X | E178: 1000676800 | F178: 에코프로비엠 | G178: FY2024 2Q 에코프로비엠 | H178: FY2024 2Q 에코프로비엠 | I178: 2024-01-01 ~ 2024-06-30 | J178: Operating Expense | K178: O | L178: =R178+T178+V178 -> 145093237061 | M178: =Q178+S178+U178 -> 33640 | N178: =R178/$L178 -> 0.058540001 | O178: =T178/$L178 -> 0.35097853 | P178: =V178/$L178 -> 0.59048147 | Q178: 99 | R178: 8493758310 | S178: 3081 | T178: 50924611402 | U178: 30460 | V178: 85674867349
B179: 41 | C179: Interim | D179: X | E179: 1000676800 | F179: 에코프로비엠 | G179: FY2024 2Q 에코프로비엠 | H179: FY2024 2Q 에코프로비엠 | I179: 2024-01-01 ~ 2024-06-30 | J179: Revenue | K179: O | L179: =R179+T179+V179 -> 490189384348 | M179: =Q179+S179+U179 -> 1332 | N179: =R179/$L179 -> 0.00085940846 | O179: =T179/$L179 -> 0.47313738 | P179: =V179/$L179 -> 0.52600321 | Q179: 2 | R179: 421272906 | S179: 418 | T179: 231926920441 | U179: 912 | V179: 257841191001 | W179: 대부분 정상전표(매출채권/매출)이나, 매출 전표 숫자 자체가 적어, 위험전표로 식별
B180: 42 | C180: Interim | D180: X | E180: 1000772068 | F180: 성일하이텍 ㈜ | G180: FY2024 2Q 성일하이텍 | H180: FY2024 2Q 성일하이텍 | I180: 2024-01-01 ~ 2024-06-30 | J180: High Risk Journal Entry | K180: X | L180: =R180+T180+V180 -> 3904345954160 | M180: =Q180+S180+U180 -> 48611 | N180: =R180/$L180 -> 0.047632459 | O180: =T180/$L180 -> 0 | P180: =V180/$L180 -> 0.95236754 | Q180: 7 | R180: 185973599436 | S180: 0 | T180: 0 | U180: 48604 | V180: 3718372354724
B181: 42 | C181: Interim | D181: X | E181: 1000772068 | F181: 성일하이텍 ㈜ | G181: FY2024 2Q 성일하이텍 | H181: FY2024 2Q 성일하이텍 | I181: 2024-01-01 ~ 2024-06-30 | J181: Operating Expense | K181: O | L181: =R181+T181+V181 -> 53546280569 | M181: =Q181+S181+U181 -> 11067 | N181: =R181/$L181 -> 0.12978928 | O181: =T181/$L181 -> 0.27525576 | P181: =V181/$L181 -> 0.59495497 | Q181: 4 | R181: 6949732950 | S181: 645 | T181: 14738922119 | U181: 10418 | V181: 31857625500
B182: 42 | C182: Interim | D182: X | E182: 1000772068 | F182: 성일하이텍 ㈜ | G182: FY2024 2Q 성일하이텍 | H182: FY2024 2Q 성일하이텍 | I182: 2024-01-01 ~ 2024-06-30 | J182: Revenue | K182: O | L182: =R182+T182+V182 -> 83648164253 | M182: =Q182+S182+U182 -> 308 | N182: =R182/$L182 -> 0 | O182: =T182/$L182 -> 0.12021189 | P182: =V182/$L182 -> 0.87978811 | Q182: 0 | R182: 0 | S182: 10 | T182: 10055503516 | U182: 298 | V182: 73592660737
B183: 43 | C183: Interim | D183: O | E183: 1000314686 | F183: STX | G183: FY2024 3Q STX | H183: FY2024 3Q STX | I183: 2024-01-01 ~ 2024-09-30 | J183: High Risk Journal Entry | K183: X | L183: =R183+T183+V183 -> 11041158387010 | M183: =Q183+S183+U183 -> 151539 | N183: =R183/$L183 -> 7.4007315e-05 | O183: =T183/$L183 -> 0 | P183: =V183/$L183 -> 0.99992599 | Q183: 4 | R183: 817126486 | S183: 0 | T183: 0 | U183: 151535 | V183: 11040341260524
B184: 43 | C184: Interim | D184: O | E184: 1000314686 | F184: STX | G184: FY2024 3Q STX | H184: FY2024 3Q STX | I184: 2024-01-01 ~ 2024-09-30 | J184: Operating Expense | K184: O | L184: =R184+T184+V184 -> 9206901064 | M184: =Q184+S184+U184 -> 2282 | N184: =R184/$L184 -> 0 | O184: =T184/$L184 -> 0.036925025 | P184: =V184/$L184 -> 0.96307497 | Q184: 0 | R184: 0 | S184: 205 | T184: 339965052 | U184: 2077 | V184: 8866936012
B185: 43 | C185: Interim | D185: O | E185: 1000314686 | F185: STX | G185: FY2024 3Q STX | H185: FY2024 3Q STX | I185: 2024-01-01 ~ 2024-09-30 | J185: Revenue | K185: O | L185: =R185+T185+V185 -> 596905902178 | M185: =Q185+S185+U185 -> 1193 | N185: =R185/$L185 -> 0.0038946596 | O185: =T185/$L185 -> 0.023396082 | P185: =V185/$L185 -> 0.97270926 | Q185: 1 | R185: 2324745283 | S185: 7 | T185: 13965259594 | U185: 1185 | V185: 580615897301
B186: 43 | C186: Final | D186: O | E186: 1000314686 | F186: STX | G186: FY2024 4Q STX | H186: FY2024 4Q STX | I186: 2024-10-01 ~ 2024-12-31 | J186: High Risk Journal Entry | K186: X | L186: =R186+T186+V186 -> 4097348557504 | M186: =Q186+S186+U186 -> 52211 | N186: =R186/$L186 -> 0.016488425 | O186: =T186/$L186 -> 0 | P186: =V186/$L186 -> 0.98351158 | Q186: 11 | R186: 67558822511 | S186: 0 | T186: 0 | U186: 52200 | V186: 4029789734993
B187: 43 | C187: Final | D187: O | E187: 1000314686 | F187: STX | G187: FY2024 4Q STX | H187: FY2024 4Q STX | I187: 2024-10-01 ~ 2024-12-31 | J187: Operating Expense | K187: O | L187: =R187+T187+V187 -> 2084285846 | M187: =Q187+S187+U187 -> 735 | N187: =R187/$L187 -> 0 | O187: =T187/$L187 -> 0.039203131 | P187: =V187/$L187 -> 0.96079687 | Q187: 0 | R187: 0 | S187: 50 | T187: 81710532 | U187: 685 | V187: 2002575314
B188: 43 | C188: Final | D188: O | E188: 1000314686 | F188: STX | G188: FY2024 4Q STX | H188: FY2024 4Q STX | I188: 2024-10-01 ~ 2024-12-31 | J188: Revenue | K188: O | L188: =R188+T188+V188 -> 171593177386 | M188: =Q188+S188+U188 -> 479 | N188: =R188/$L188 -> 0 | O188: =T188/$L188 -> 0.16740993 | P188: =V188/$L188 -> 0.83259007 | Q188: 0 | R188: 0 | S188: 51 | T188: 28726402555 | U188: 428 | V188: 142866774831
B189: 44 | C189: Interim | D189: X | E189: 1000682277 | F189: 삼표시멘트 | G189: FY2024 2Q 삼표시멘트 | H189: FY2024 2Q 삼표시멘트 | I189: 2024-01-01 ~ 2024-06-30 | J189: High Risk Journal Entry | K189: X | L189: =R189+T189+V189 -> 14988710464140 | M189: =Q189+S189+U189 -> 193877 | N189: =R189/$L189 -> 0.05321492 | O189: =T189/$L189 -> 0 | P189: =V189/$L189 -> 0.94678508 | Q189: 5 | R189: 797623035256 | S189: 0 | T189: 0 | U189: 193872 | V189: 14191087428884
B190: 44 | C190: Interim | D190: X | E190: 1000682277 | F190: 삼표시멘트 | G190: FY2024 2Q 삼표시멘트 | H190: FY2024 2Q 삼표시멘트 | I190: 2024-01-01 ~ 2024-06-30 | J190: Operating Expense | K190: O | L190: =R190+T190+V190 -> 171985057346 | M190: =Q190+S190+U190 -> 22303 | N190: =R190/$L190 -> 0.00058243432 | O190: =T190/$L190 -> 0.18600306 | P190: =V190/$L190 -> 0.81341451 | Q190: 1 | R190: 100170000 | S190: 1221 | T190: 31989746312 | U190: 21081 | V190: 139895141034
B191: 44 | C191: Interim | D191: X | E191: 1000682277 | F191: 삼표시멘트 | G191: FY2024 2Q 삼표시멘트 | H191: FY2024 2Q 삼표시멘트 | I191: 2024-01-01 ~ 2024-06-30 | J191: Revenue | K191: O | L191: =R191+T191+V191 -> 379657347432 | M191: =Q191+S191+U191 -> 7057 | N191: =R191/$L191 -> 0.002825251 | O191: =T191/$L191 -> 0.0045520848 | P191: =V191/$L191 -> 0.99262266 | Q191: 1 | R191: 1072627312 | S191: 19 | T191: 1728232442 | U191: 7037 | V191: 376856487678
... B227: 52 | C227: Final | D227: O | E227: 1000317541 | F227: (주)케이씨 | G227: FY2024 케이씨 YE | H227: FY2024 케이씨 YE | I227: 2024-01-01 ~ 2024-12-31 | J227: Revenue | K227: O | L227: =R227+T227+V227 -> 149691006709 | M227: =Q227+S227+U227 -> 4520 | N227: =R227/$L227 -> 0.00017862302 | O227: =T227/$L227 -> 0.091844239 | P227: =V227/$L227 -> 0.90797714 | Q227: 1 | R227: 26738260 | S227: 403 | T227: 13748256640 | U227: 4116 | V227: 135916011809
B228: 53 | C228: Interim | D228: X | E228: 1000810369 | F228: 주식회사 원일특강 | G228: FY2024 2Q 원일특강 | H228: FY2024 2Q 원일특강 | I228: 2024-01-01 ~ 2024-06-30 | J228: High Risk Journal Entry | K228: X | L228: 4469754781584 | M228: =Q228+S228+U228 -> 482819 | N228: =R228/$L228 -> 0.05419737 | O228: =T228/$L228 -> 0 | P228: =V228/$L228 -> 0.94580263 | Q228: 5 | R228: 242248953273 | S228: 0 | T228: 0 | U228: 482814 | V228: 4227505828311
B229: 53 | C229: Interim | D229: X | E229: 1000810369 | F229: 주식회사 원일특강 | G229: FY2024 2Q 원일특강 | H229: FY2024 2Q 원일특강 | I229: 2024-01-01 ~ 2024-06-30 | J229: Operating Expense | K229: X | L229: 4722844932 | M229: =Q229+S229+U229 -> 7890 | N229: =R229/$L229 -> 0.002477628 | O229: =T229/$L229 -> 0.11602285 | P229: =V229/$L229 -> 0.88149953 | Q229: 22 | R229: 11701453 | S229: 357 | T229: 547957907 | U229: 7511 | V229: 4163185572
B230: 53 | C230: Interim | D230: X | E230: 1000810369 | F230: 주식회사 원일특강 | G230: FY2024 2Q 원일특강 | H230: FY2024 2Q 원일특강 | I230: 2024-01-01 ~ 2024-06-30 | J230: Revenue | K230: X | L230: 178304597971 | M230: =Q230+S230+U230 -> 9129 | N230: =R230/$L230 -> 0.02321154 | O230: =T230/$L230 -> 0.3944671 | P230: =V230/$L230 -> 0.58232136 | Q230: 19 | R230: 4138724220 | S230: 1948 | T230: 70335297087 | U230: 7162 | V230: 103830576664
B231: 54 | C231: Interim | D231: X | E231: 1001067392 | F231: 씨제이올리브영주식회사 | G231: FY2024 2Q 씨제이올리브영 | H231: FY2024 2Q 씨제이올리브영 v7 | I231: 2024-01-01 ~ 2024-06-30 | J231: High Risk Journal Entry | K231: X | L231: =R231+T231+V231 -> 84810825937880 | M231: =Q231+S231+U231 -> 16496388 | N231: =R231/$L231 -> 0.015303261 | O231: =T231/$L231 -> 0 | P231: =V231/$L231 -> 0.98469674 | Q231: 234 | R231: 1297882192366 | S231: 0 | T231: 0 | U231: 16496154 | V231: 83512943745514
B232: 54 | C232: Interim | D232: X | E232: 1001067392 | F232: 씨제이올리브영주식회사 | G232: FY2024 2Q 씨제이올리브영 | H232: FY2024 2Q 씨제이올리브영 v7 | I232: 2024-01-01 ~ 2024-06-30 | J232: Operating Expense | K232: X | L232: =R232+T232+V232 -> 1078463949698 | M232: =Q232+S232+U232 -> 2178261.9 | N232: =R232/$L232 -> 0.046449929 | O232: =T232/$L232 -> 0.41843748 | P232: =V232/$L232 -> 0.53511259 | Q232: 11.66 | R232: 50094574395 | S232: 619.23 | T232: 451269738929 | U232: 2177631 | V232: 577099636374
B233: 54 | C233: Interim | D233: X | E233: 1001067392 | F233: 씨제이올리브영주식회사 | G233: FY2024 2Q 씨제이올리브영 | H233: FY2024 2Q 씨제이올리브영 v7 | I233: 2024-01-01 ~ 2024-06-30 | J233: Revenue | K233: X | L233: =R233+T233+V233 -> 1012543046280 | M233: =Q233+S233+U233 -> 1938460 | N233: =R233/$L233 -> 0.25142093 | O233: =T233/$L233 -> 0.006705836 | P233: =V233/$L233 -> 0.74187324 | Q233: 7260 | R233: 254574512093 | S233: 196111 | T233: 6789947562 | U233: 1735089 | V233: 751178586625 | W233: 월말에 매출정산으로 100개 라인을 초과하는 전표가 존재.
...

Sheet FY24_비용
A1: 본부명 | B1: 계약코드 | C1: 계약명 | D1: EP | E1: USD | N1: T/M | O1: 항목 | Q1: 금액(개수) | S1: 비고
A2: ICE2 | B2: 1529846 | C2: FY24 삼성전자 외부감사 | D2: 한상현 | E2: =$Q$13 -> 4106.0607 | N2: FY24 발생비용
A3: ICE1 | B3: 1527608 | C3: SK하이닉스 FY2024 외부감사 | D3: 윤주헌 | E3: =$Q$13 -> 4106.0607 | H3: 본부명 | I3: Eng 수 | J3: 금액(USD) | N3: A | O3: GUP 수 | Q3: 38 | R3: ea | S3: Global비용청구 단위는 Engagement가 아닌 GUP(Global Ultimate Parent)
A4: IM4 | B4: 1531176 | C4: 두산에너빌리티_FY2024 외부감사 | D4: 강정구 | E4: =$Q$13 -> 4106.0607 | H4: B&F2 | I4: =COUNTIF(A:A,H4) -> 1 | J4: =ROUND(I4*$Q$13,2) -> 4106.06 | N4: B | O4: GUP당 비용 | Q4: 4500 | R4: $
A5: IM3 | B5: 1526468 | C5: 기아 주식회사 2024년 외부감사 | D5: 전현호 | E5: =$Q$13 -> 4106.0607 | H5: B&F3 | I5: =COUNTIF(A:A,H5) -> 1 | J5: =ROUND(I5*$Q$13,2) -> 4106.06 | N5: C | O5: 총비용 | P5: A*B | Q5: =Q3*Q4 -> 171000 | R5: $
A6: IM1 | B6: 1516473 | C6: FY2024_SK네트웍스_법정감사 | D6: 이주영 | E6: =$Q$13 -> 4106.0607 | H6: CM1 | I6: =COUNTIF(A:A,H6) -> 7 | J6: =ROUND(I6*$Q$13,2)+0.01 -> 28742.43 | N6: D | O6: Billed to ASPAC | Q6: -27000 | R6: $ | S6: ASPAC지원금
A7: ICE1 | B7: 1511883 | C7: LG이노텍 2024년 외부감사 | D7: 민성진 | E7: =$Q$13 -> 4106.0607 | H7: CM2 | I7: =COUNTIF(A:A,H7) -> 4 | J7: =ROUND(I7*$Q$13,2) -> 16424.24 | N7: E | O7: 차감 후 비용 | P7: C+D | Q7: =Q5+Q6 -> 144000 | R7: $
A8: IGH | B8: 1527322 | C8: [SK가스] FY24 외부감사 | D8: 조승희 | E8: =$Q$13 -> 4106.0607 | H8: ICE1 | I8: =COUNTIF(A:A,H8) -> 3 | J8: =ROUND(I8*$Q$13,2) -> 12318.18 | N8: F | O8: 원천세 포함 비용 | P8: E/0.9 | Q8: =ROUND(Q7/0.9,2) -> 160000
A9: CM1 | B9: 1515048 | C9: FY2024 하이트진로 주식회사 외부감사 | D9: 김중규 | E9: =$Q$13 -> 4106.0607 | H9: ICE2 | I9: =COUNTIF(A:A,H9) -> 5 | J9: =ROUND(I9*$Q$13,2) -> 20530.3 | N9: 비용배부
A10: IGH | B10: 1523946 | C10: [제일기획] FY2024 지정감사 | D10: 이덕영 | E10: =$Q$13 -> 4106.0607 | H10: ICE3 | I10: =COUNTIF(A:A,H10) -> 1 | J10: =ROUND(I10*$Q$13,2) -> 4106.06 | N10: G | O10: FY23 추가비용 | Q10: =9000+11666.67 -> 20666.67 | R10: $ | S10: FY23 추가 사용 3건 $9,000, FY23 원천세 $11,666.66
A11: IM2 | B11: 1512425 | C11: 2024년 SK이노베이션 지정감사 | D11: 이채능 | E11: =$Q$13 -> 4106.0607 | H11: IM1 | I11: =COUNTIF(A:A,H11) -> 5 | J11: =ROUND(I11*$Q$13,2) -> 20530.3 | N11: H | O11: 배부대상 비용 | P11: G+F | Q11: =Q8+Q10 -> 180666.67 | R11: $
A12: IM1 | B12: 1530311 | C12: OCI주식회사 FY24 법정감사 | D12: 나재광 | E12: =$Q$13 -> 4106.0607 | H12: IM2 | I12: =COUNTIF(A:A,H12) -> 6 | J12: =ROUND(I12*$Q$13,2)+0.01 -> 24636.37 | N12: I | O12: Eng수 | Q12: 44 | R12: ea
A13: CM1 | B13: 1528166 | C13: 현대백화점 2024년 외부감사 | D13: 신장훈 | E13: =$Q$13 -> 4106.0607 | H13: IM3 | I13: =COUNTIF(A:A,H13) -> 1 | J13: =ROUND(I13*$Q$13,2) -> 4106.06 | N13: J | O13: Eng당 비용 | P13: H/I | Q13: =Q11/Q12 -> 4106.0607 | R13: $
A14: IM2 | B14: 1514244 | C14: 아세아시멘트 2024년 회계감사 | D14: 정양기 | E14: =$Q$13 -> 4106.0607 | H14: IM4 | I14: =COUNTIF(A:A,H14) -> 4 | J14: =ROUND(I14*$Q$13,2) -> 16424.24 | N14: K | O14: 환율 | Q14: 1466.5 | R14: \/$ | S14: 2025.03.31 기준
A15: ICE2 | B15: 1546791 | C15: FY2024 씨제이프레시웨이 외부감사 | D15: 김정기 | E15: =$Q$13 -> 4106.0607 | H15: IGH | I15: =COUNTIF(A:A,H15) -> 6 | J15: =ROUND(I15*$Q$13,2)+0.01 -> 24636.37 | N15: L | O15: Eng당 비용 | P15: J*K | Q15: =ROUND(Q13*Q14,2) -> 6021538 | R15: \
A16: IM1 | B16: 1522493 | C16: FY24_보령 법정감사 | D16: 박상훈 | E16: =$Q$13 -> 4106.0607 | H16: 합계 | I16: =SUM(I4:I15) -> 44 | J16: =SUM(J4:J15) -> 180666.67 | K16: =J16=Q11 -> TRUE
A17: IM2 | B17: 1514071 | C17: E1 FY24 외부감사(주기적지정) | D17: 조화수 | E17: =$Q$13 -> 4106.0607
A18: IM4 | B18: 1513980 | C18: 팜스코 - FY24 외부감사 | D18: 김도현 | E18: =$Q$13 -> 4106.0607
A19: IGH | B19: 1550289 | C19: [동양] FY2024 외부감사 | D19: 박상옥 | E19: =$Q$13 -> 4106.0607
A20: CM1 | B20: 1514621 | C20: 한섬_2024년 외부감사 | D20: 조일상 | E20: =$Q$13 -> 4106.0607
A21: IM2 | B21: 1514486 | C21: 2024년 세아제강 회계감사 | D21: 정양기 | E21: =$Q$13 -> 4106.0607
A22: CM2 | B22: 1536028 | C22: 더블유씨피_외부감사_FY24 | D22: 정창길 | E22: =$Q$13 -> 4106.0607
A23: CM2 | B23: 1515113 | C23: 남해화학 FY2024 외부감사 | D23: 이종우 | E23: =$Q$13 -> 4106.0607
A24: IGH | B24: 1527570 | C24: [한독] FY2024 지정감사 | D24: 임근구 | E24: =$Q$13 -> 4106.0607
